Workbook

Sheet Kostenübersicht
A1: Sofortangebot — Laufende Geschäftskosten
A2: Stand: 2026-09-02 · Head of Finance · Bestandsaufnahme CoS-F-001 · Beleg-Details je Rechnung stehen im Blatt 'Rechnungsjournal' · orange = auffällig, bitte klären · grau = noch kein Beleg · Umsatzsteuer-Status aktualisiert 17.09.2026: Regelbesteuerung (Verzicht nach § 19 Abs. 2 UStG), Details in docs/preismodell.md.
A4: Dienst | B4: Kategorie | C4: Währung | D4: Monatsbetrag (aktuellster Beleg, brutto) | E4: Abrechnungsrhythmus | F4: Vertragsstand / Kündigungsfrist | G4: USt-Behandlung | H4: Status | I4: Quelle / Notiz
A5: Supabase | B5: Hosting / Datenbank | C5: USD | D5: 53.83 | E5: monatlich: Pro Plan $25 Grundgebühr + nutzungsbasierte Zusatzkosten (Compute, Realtime, Egress, Functions, …) | F5: 2 Projekte laut Doku vorgesehen (Staging + Produktion 'yqlledouhfovytifeekd') | G5: Reverse Charge (§ 13b UStG, Singapur-Anbieter). AKTUALISIERT 17.09.2026: Mit der Regelbesteuerung (Verzicht nach § 19 Abs. 2 UStG, Entscheidung Sandy vom 17.09.2026) ist die Steuer durchlaufend — angemeldet und im selben Zug als Vorsteuer gezogen, Saldo null. Der Monatsbetrag in Spalte D ist damit der volle Kostenwert. | H5: auffällig — Betrag bestätigt, Trend + Projektanzahl bitte klären | I5: 4 Belege (Journal 2026-003/006/008/016): 23.05. $25,00 / 23.06. $49,97 / 23.07. $54,30 / 23.08. $53,83 — nach dem Anstieg jetzt erstmals leicht rückläufig. Rechnungen zeigten bis Juli 5 Projekt-Referenzen, dokumentiert sind nur 2; im August-Beleg taucht eine davon erstmals nicht mehr auf (jetzt 4). Bitte weiter beobachten/klären, ob alle nötig sind.
A6: Vercel | B6: Hosting / Deployment | C6: USD | D6: 23.8 | E6: monatlich: Pro Plan $20 + 19% USt, seit Juni zusätzlich 'Observability Plus' Position mit $0,00 | F6: Kündigungsfrist unbekannt | G6: USt. direkt ausgewiesen (EU VAT EU056329113), kein Reverse Charge | H6: bestätigt | I6: 4 Belege (Journal 2026-002/005/007/015): 22.05., 22.06., 22.07., 22.08. — durchgängig $23,80, stabil. Zahlungsart jetzt bestätigt: Kreditkarte Visa •••3991.
A7: Anthropic — direkt | B7: KI / API | C7: USD | D7: 53.55 | E7: unklar — Beleg trägt 'Prepaid extra usage, Individual plan', evtl. einmaliger Nachkauf statt Fixbetrag | F7: unbekannt | G7: USt. direkt ausgewiesen (EU VAT IE4276970QH), kein Reverse Charge | H7: auffällig — bitte klären ob wiederkehrend | I7: 1 Beleg (Journal 2026-010) vom 17.08.2026 über $45,00 + USt = $53,55, Geschäftsadresse Wielandstraße 11, mit hinterlegter deutscher Steuernummer.
A8: Claude Pro (Apple/iTunes) | B8: KI / Software | C8: EUR | D8: 22 | E8: monatlich, automatische Verlängerung, Zahlung per PayPal | F8: monatlich kündbar (Apple-Abo) | G8: USt. direkt von Apple ausgewiesen, kein Reverse Charge | H8: auffällig — geschäftlich/privat + fehlende Monate klären | I8: 2 Belege (Journal 2026-001/009): 04.05. und 03.08., je 22,00 € — Juni/Juli-Belege fehlen noch. Separates Abo zur direkten Anthropic-Rechnung, andere Rechnungsadresse (Krampasplatz 4b). Bitte klären: zweite geschäftliche Claude-Lizenz oder privates Abo?
A9: OpenAI | B9: KI / API | C9: USD | D9: 17.85 | E9: nutzungsbasiert, Beleg zeigt eine Guthaben-Aufladung ('usage credit'), kein fester Monatsbetrag erkennbar | F9: unbekannt | G9: USt. direkt ausgewiesen (EU OSS VAT EU372041333), kein Reverse Charge | H9: bestätigt | I9: 1 Beleg (Journal 2026-004) vom 14.06.2026 über $15,00 + USt = $17,85. Rechnungsempfänger 'Hugo' / runningwithhugo@outlook.de — ist Sandys eigener Account, Name/E-Mail-Alias lässt sich bei OpenAI nachträglich nicht mehr ändern (geklärt 19.08.2026).
A10: Resend | B10: E-Mail | C10: ? | E10: unbekannt | F10: unbekannt | G10: unbekannt | H10: kein Beleg gefunden | I10: Im Code bestätigt (Paket 'resend', RESEND_API_KEY), aber noch keine Rechnung im Belege-Ordner.
A11: Domain sofortangebot.app | B11: Domain | C11: EUR | D11: 2.5 | E11: 'IONOS Mail Basic 5' (Postfach) laufend 2,50 €/Monat. Domain .app + 'Domain Guard' (Privatsphärenschutz) jährlich, zusammen 13,00 € brutto — nächste Fälligkeit ~06/2027. | F11: Vertragsnummer 111811442 bei IONOS SE — Achtung: bündelt auf denselben Rechnungen auch mehrere fremde Domains, siehe Journal | G11: USt. direkt von IONOS ausgewiesen (USt-IdNr. DE815563912), kein Reverse Charge | H11: bestätigt | I11: 5 Belege (Journal 2026-011 bis 2026-015/017 — Rechnungsnummern siehe dort) unter einer gebündelten IONOS-Rechnung. Domain sofortangebot.app wurde 08.06.2026 registriert. Sandy hat am 02.09.2026 bestätigt, dass 'Domain Guard' und 'IONOS Mail Basic 5' ebenfalls zu sofortangebot.app gehören. Fremde Domains ('einfach-anfrage.com', 'einfachanfrage-hochzeitsfotografie.de' u. a.) laufen über denselben IONOS-Vertrag, aber NICHT mitgezählt.
A12: Sentry | B12: Monitoring / Error-Tracking | C12: ? | E12: unbekannt | F12: unbekannt | G12: unbekannt | H12: kein Beleg gefunden | I12: Im Code gefunden ('@sentry/nextjs'), nicht in Sandys Ausgangsliste, noch keine Rechnung im Ordner.
A13: Stripe | B13: Zahlungsabwicklung | C13: ? | E13: transaktionsbasiert (keine feste Monatsgebühr erwartet) | F13: unbekannt | G13: unbekannt | H13: kein Beleg erwartet | I13: Im Code bestätigt ('stripe' Paket). Gebühren pro Transaktion statt Fixkosten — relevant erst mit Umsatz-Tracking in Phase 2.
A14: GitHub Actions (Backup-Artefakte) | B14: CI / Infra | C14: ? | E14: nutzungsbasiert (Speicher/Minuten) | F14: abhängig vom GitHub-Plan | G14: unbekannt | H14: zu prüfen | I14: Tägliches DB-Backup speichert Artefakte 30/90/365 Tage. Kann bei privatem Repo über das Freikontingent hinaus Kosten verursachen — noch kein Beleg.
A16: DIN Media — VOB Gesamtausgabe 2019 (E-Book) | B16: Fachliteratur — einmalig | C16: EUR einmalig | E16: einmalig, 54,00 € brutto am 04.09.2026 (Beleg 2026-018) | F16: kein Vertrag, Einmalkauf | G16: USt. 7 % ermaessigt (E-Book), von DIN Media ausgewiesen | H16: bestätigt — kein laufender Posten, steht deshalb ohne Monatsbetrag und faellt nicht in die Monatssummen
A18: Summe USD-Positionen (siehe Status-Spalte für Vorbehalte) | D18: =SUMIF(C5:C16,"USD",D5:D16)
A19: Summe EUR-Positionen (siehe Status-Spalte für Vorbehalte) | D19: =SUMIF(C5:C16,"EUR",D5:D16)
A20: Summe gesamt in EUR (USD-Positionen zum BMF-Kurs August 2026) | D20: =D19+D18/Rechnungsjournal!$B$42
A21: Hinweis: USD- und EUR-Positionen werden weiterhin getrennt summiert, weil die Belege in unterschiedlichen Währungen vorliegen. Die Gesamtsumme in EUR rechnet die USD-Positionen mit dem amtlichen BMF-Umsatzsteuer-Umrechnungskurs des jeweils letzten Monats um (§ 16 Abs. 6 UStG) — die Kurse stehen im Blatt 'Rechnungsjournal' unter der Journaltabelle. Beleg-Details je Rechnung (Rechnungsnummer, Netto/USt/Brutto, Beleg-Datei) stehen ebenfalls im Blatt 'Rechnungsjournal'.

Sheet Rechnungsjournal
A1: Rechnungsjournal — Belege im Detail (für Buchhaltung / Steuerberater)
A2: Ein Beleg = eine Zeile, chronologisch. Enthält alles, was ein Steuerberater für die Verbuchung braucht: Rechnungsnummer, Leistungszeitraum, Netto/USt/Brutto, steuerliche Einordnung (Reverse Charge ja/nein), Zahlungsart und die Original-Beleg-Datei im Rechnungen-Ordner. Bitte Zeilen hier nie überschreiben, nur neue anhängen (Nachvollziehbarkeit).
A4: Beleg-Nr. | B4: Rechnungsdatum | C4: Rechnungsnr. (Anbieter) | D4: Leistungszeitraum | E4: Anbieter | F4: Anbieter-Land | G4: Dienst | H4: Rechnungsempfänger lt. Beleg | I4: Währung | J4: Netto-Betrag | K4: USt-Satz | L4: USt-Betrag | M4: Brutto-Betrag | N4: Sofortangebot-Anteil (Brutto) | O4: Steuerliche Einordnung | P4: Betrag EUR (Brutto, ca.) | Q4: Zahlungsart | R4: Beleg-Datei (Ordner 'Rechnungen') | S4: Auffälligkeit / Notiz | T4: Vorsteuer EUR (erst ab Regelbesteuerung, F-006 = B)
A5: 2026-001 | B5: 46146 | C5: MVS2VFHBYG / Dok. 846129332588 | D5: 04.05.–03.06.2026 (Abo-Monat) | E5: Apple Distribution International Ltd. (Vertrieb für Claude Pro) | F5: Irland | G5: Claude Pro (Apple/iTunes) | H5: Sandra Holm, Krampasplatz 4b, 14199 Berlin | I5: EUR | J5: 18.49 | K5: 0.19 | L5: 3.51 | M5: 22 | N5: 22 | O5: USt. (19%) direkt von Apple ausgewiesen, kein Reverse Charge. | P5: =M5 | Q5: PayPal | R5: Deine Rechnung von Apple.eml | S5: Abo verlängert sich automatisch monatlich. Rechnungsadresse weicht von den übrigen Belegen ab (Krampasplatz 4b statt Wielandstraße 11) — bitte klären, welche Adresse aktuell/richtig ist. | T5: =ROUND(L5,2)
A6: 2026-002 | B6: 46164 | C6: TT0BDQ8S-0001 | D6: 22.05.–21.06.2026 | E6: Vercel Inc. | F6: USA | G6: Vercel | H6: einfachanfrage's projects, Wielandstraße 11, 12159 Berlin (einfachanfrage@outlook.com) | I6: USD | J6: 20 | K6: 0.19 | L6: 3.8 | M6: 23.8 | N6: 23.8 | O6: USt. (19%) direkt von Vercel ausgewiesen (EU VAT EU056329113), kein Reverse Charge. | P6: =M6/$B$39 | Q6: Kreditkarte Visa •••3991 | R6: Invoice-TT0BDQ8S-0001.pdf / Receipt-2392-5328.pdf | S6: Zahlungsart nachträglich ergänzt (Update 2026-09-02) anhand Zahlungsbeleg Receipt-2392-5328.pdf. | T6: =ROUND(L6/$B$39,2)
A7: 2026-003 | B7: 46165 | C7: MVGOOM-00003 | D7: 23.05.–22.06.2026 | E7: Supabase Pte. Ltd. | F7: Singapur | G7: Supabase | H7: Sandra Holm, Wielandstraße 11, Berlin (einfachanfrage@outlook.com) | I7: USD | J7: 25 | K7: Reverse Charge | L7: 0 | M7: 25 | N7: 25 | O7: Reverse Charge — Supabase weist keine USt aus. Sandy startet als Kleinunternehmerin nach §19 UStG (bestätigt 19.08.2026), Gewerbe aber noch nicht angemeldet. Nach Kleinunternehmerregelung i. d. R. keine Vorsteuer ziehbar, aber die USt-Pflicht auf reverse-charge-Leistungen aus dem Ausland (§13b UStG) kann trotzdem bestehen bleiben — das ist keine verbindliche Auskunft von mir, bitte mit Steuerberater final klären, sobald einer feststeht. | P7: =M7/$B$39 | Q7: unbekannt | R7: Invoice-MVGOOM-00003.pdf | S7: Nur Pro-Plan-Grundgebühr, keine Nutzungsgebühren in diesem Monat. | T7: 0,00 (durchlaufend)
A8: 2026-004 | B8: 46187 | C8: YL9K6L19-0001 | D8: — | E8: OpenAI OpCo, LLC | F8: USA | G8: OpenAI | H8: Hugo, Wielandstraße 11, 12159 Berlin (runningwithhugo@outlook.de) | I8: USD | J8: 15 | K8: 0.19 | L8: 2.85 | M8: 17.85 | N8: 17.85 | O8: USt. (19%) direkt von OpenAI ausgewiesen (EU OSS VAT EU372041333), kein Reverse Charge. | P8: =M8/$B$40 | Q8: unbekannt | R8: Invoice-YL9K6L19-0001.pdf | S8: Geklärt (19.08.2026): Konto gehört Sandy, 'Hugo' ist ein historischer Nutzername/E-Mail-Alias bei OpenAI, der sich im Nachhinein nicht mehr auf 'Sandra Holm' ändern lässt. Kein falscher Account — nur zur Info für den Steuerberater vermerkt, falls Name/E-Mail auf dem Beleg auffallen. | T8: =ROUND(L8/$B$40,2)
A9: 2026-005 | B9: 46195 | C9: TT0BDQ8S-0003 | D9: 22.06.–21.07.2026 | E9: Vercel Inc. | F9: USA | G9: Vercel | H9: einfachanfrage's projects, Wielandstraße 11, 12159 Berlin (einfachanfrage@outlook.com) | I9: USD | J9: 20 | K9: 0.19 | L9: 3.8 | M9: 23.8 | N9: 23.8 | O9: USt. (19%) direkt von Vercel ausgewiesen (EU VAT EU056329113), kein Reverse Charge. | P9: =M9/$B$40 | Q9: Kreditkarte Visa •••3991 | R9: Invoice-TT0BDQ8S-0003.pdf / Receipt-2268-5813.pdf | S9: Zusätzliche Position 'Observability Plus' mit $0,00 seit diesem Monat. Zahlungsart nachträglich ergänzt (Update 2026-09-02) anhand Zahlungsbeleg Receipt-2268-5813.pdf. | T9: =ROUND(L9/$B$40,2)
A10: 2026-006 | B10: 46196 | C10: MVGOOM-00005 | D10: 23.05.–22.06.2026 (Nutzung) + 23.06.–22.07.2026 (Pro Plan) | E10: Supabase Pte. Ltd. | F10: Singapur | G10: Supabase | H10: Sandra Holm, Wielandstraße 11, Berlin (einfachanfrage@outlook.com) | I10: USD | J10: 49.97 | K10: Reverse Charge | L10: 0 | M10: 49.97 | N10: 49.97 | O10: Reverse Charge — Supabase weist keine USt aus. Sandy startet als Kleinunternehmerin nach §19 UStG (bestätigt 19.08.2026), Gewerbe aber noch nicht angemeldet. Nach Kleinunternehmerregelung i. d. R. keine Vorsteuer ziehbar, aber die USt-Pflicht auf reverse-charge-Leistungen aus dem Ausland (§13b UStG) kann trotzdem bestehen bleiben — das ist keine verbindliche Auskunft von mir, bitte mit Steuerberater final klären, sobald einer feststeht. | P10: =M10/$B$40 | Q10: unbekannt | R10: Invoice-MVGOOM-00005.pdf / Receipt-MVGOOM-00005.pdf | S10: Erstmals nennenswerte Nutzungsgebühren (Compute Hours) zusätzlich zur Pro-Plan-Grundgebühr. Zahlungsbeleg (Receipt-MVGOOM-00005.pdf) nachträglich ergänzt (Update 2026-09-02), keine neue Zeile — identischer Betrag/Zeitraum wie diese Rechnung. | T10: 0,00 (durchlaufend)
A11: 2026-007 | B11: 46225 | C11: TT0BDQ8S-0004 | D11: 22.07.–21.08.2026 | E11: Vercel Inc. | F11: USA | G11: Vercel | H11: einfachanfrage's projects, Wielandstraße 11, 12159 Berlin (einfachanfrage@outlook.com) | I11: USD | J11: 20 | K11: 0.19 | L11: 3.8 | M11: 23.8 | N11: 23.8 | O11: USt. (19%) direkt von Vercel ausgewiesen (EU VAT EU056329113), kein Reverse Charge. | P11: =M11/$B$41 | Q11: Kreditkarte Visa •••3991 | R11: Invoice-TT0BDQ8S-0004.pdf / Receipt-2842-3830.pdf | S11: Zahlungsart nachträglich ergänzt (Update 2026-09-02) anhand Zahlungsbeleg Receipt-2842-3830.pdf. | T11: =ROUND(L11/$B$41,2)
A12: 2026-008 | B12: 46226 | C12: MVGOOM-00006 | D12: 23.06.–22.07.2026 (Nutzung) + 23.07.–22.08.2026 (Pro Plan) | E12: Supabase Pte. Ltd. | F12: Singapur | G12: Supabase | H12: Sandra Holm, Wielandstraße 11, Berlin (einfachanfrage@outlook.com) | I12: USD | J12: 54.3 | K12: Reverse Charge | L12: 0 | M12: 54.3 | N12: 54.3 | O12: Reverse Charge — Supabase weist keine USt aus. Sandy startet als Kleinunternehmerin nach §19 UStG (bestätigt 19.08.2026), Gewerbe aber noch nicht angemeldet. Nach Kleinunternehmerregelung i. d. R. keine Vorsteuer ziehbar, aber die USt-Pflicht auf reverse-charge-Leistungen aus dem Ausland (§13b UStG) kann trotzdem bestehen bleiben — das ist keine verbindliche Auskunft von mir, bitte mit Steuerberater final klären, sobald einer feststeht. | P12: =M12/$B$41 | Q12: unbekannt | R12: Invoice-MVGOOM-00006.pdf / Receipt-MVGOOM-00006.pdf | S12: Nutzungsgebühren weiter gestiegen, neu: 'Realtime Peak Connections' $10,00. Rechnung listet 5 verschiedene Projekt-Referenzen, dokumentiert sind nur 2 (Staging + Produktion). Zahlungsbeleg (Receipt-MVGOOM-00006.pdf) nachträglich ergänzt (Update 2026-09-02), keine neue Zeile. | T12: 0,00 (durchlaufend)
A13: 2026-009 | B13: 46237 | C13: MVS3312KT5 / Dok. 674170779929 | D13: 03.08.–02.09.2026 (Abo-Monat) | E13: Apple Distribution International Ltd. (Vertrieb für Claude Pro) | F13: Irland | G13: Claude Pro (Apple/iTunes) | H13: Sandra Holm, Krampasplatz 4b, 14199 Berlin | I13: EUR | J13: 18.49 | K13: 0.19 | L13: 3.51 | M13: 22 | N13: 22 | O13: USt. (19%) direkt von Apple ausgewiesen, kein Reverse Charge. | P13: =M13 | Q13: PayPal | R13: Deine Käufe bei Apple.eml | S13: Belege für die Juni- und Juli-Abbuchung dieses Abos fehlen noch (vermutlich auch je ~22 €) — bitte in Apple-Kaufhistorie/Postfach nachsehen und ergänzen. | T13: =ROUND(L13,2)
A14: 2026-010 | B14: 46251 | C14: CBBICKXQ-0001 | D14: — | E14: Anthropic, PBC | F14: USA | G14: Anthropic — direkt | H14: Sandra Holm, Wielandstraße 11, 12159 Berlin, DE STN 89365407818 | I14: USD | J14: 45 | K14: 0.19 | L14: 8.55 | M14: 53.55 | N14: 53.55 | O14: USt. (19%) direkt von Anthropic ausgewiesen (EU VAT IE4276970QH), kein Reverse Charge. | P14: =M14/$B$42 | Q14: unbekannt (Online-Zahlung) | R14: Invoice-CBBICKXQ-0001.pdf | S14: Rechnung nennt eine deutsche Steuernummer (DE STN 89365407818) — da laut Sandy noch kein Gewerbe angemeldet ist (Stand 19.08.2026), vermutlich Sandys private Steuer-ID, nicht zwingend eine Geschäfts-Steuernummer. Position heißt 'Prepaid extra usage, Individual plan' — bitte klären: wiederkehrender Posten oder einmaliger Nachkauf von Nutzungsvolumen? | T14: =ROUND(L14/$B$42,2)
A15: 2026-011 | B15: 46138 | C15: 100185593347 | D15: Abrechnung 26.04.2026 (Vertragszeitraum Domain: 25.04.2026–24.04.2027) | E15: IONOS SE | F15: Deutschland | G15: Domain sofortangebot.app | H15: Sandra Holm, Wielandstr. 11, 12159 Berlin | I15: EUR | J15: 0.81 | K15: 0.19 | L15: 0.15 | M15: 0.96 | N15: 0 | O15: USt. (19%) direkt von IONOS ausgewiesen (deutscher Anbieter, USt-IdNr. DE815563912), kein Reverse Charge. | P15: =M15 | Q15: PayPal | R15: IONOS Rechnung 2026-04-26 - RG_100185593347.pdf | S15: Rechnung betrifft ausschließlich die Domain 'einfach-anfrage.com' (Position 1) — das ist NICHT sofortangebot.app, sondern offensichtlich ein anderes/älteres Projekt. Deshalb Sofortangebot-Anteil = 0,00 €. Alle 5 IONOS-Rechnungen (April–August 2026) laufen unter derselben Vertragsnummer 111811442, die mehrere Domains bündelt — bitte im Blick behalten, dass hier nicht versehentlich fremde Projektkosten mitgezählt werden. Neu entdeckt und nachgetragen: Update 2026-09-02. | T15: =ROUND(L15,2)
A16: 2026-012 | B16: 46168 | C16: 100187536255 | D16: Abrechnung 26.05.2026 (Vertragszeiträume: 11.05.2026–10.05.2027 bzw. 22.05.2026–21.05.2027) | E16: IONOS SE | F16: Deutschland | G16: Domain sofortangebot.app | H16: Sandra Holm, Wielandstr. 11, 12159 Berlin | I16: EUR | J16: 27.73 | K16: 0.19 | L16: 5.27 | M16: 33 | N16: 0 | O16: USt. (19%) direkt von IONOS ausgewiesen (deutscher Anbieter, USt-IdNr. DE815563912), kein Reverse Charge. | P16: =M16 | Q16: PayPal | R16: IONOS Rechnung 2026-05-26 - RG_100187536255.pdf | S16: Rechnung betrifft drei fremde Domains ('einfachanfrage.com', 'einfachanfrage-hochzeitsfotografie.de', 'einfachanfrage-tattoo.de') plus deren Registrierungsgebühren — keine davon ist sofortangebot.app. Deshalb Sofortangebot-Anteil = 0,00 €. Neu entdeckt und nachgetragen: Update 2026-09-02. | T16: =ROUND(L16,2)
A17: 2026-013 | B17: 46199 | C17: 100189466040 | D17: Abrechnung 26.06.2026 (Domain .app + Domain Guard: 08.06.2026–07.06.2027; IONOS Mail Basic 5: 08.06.–07.07.2026) | E17: IONOS SE | F17: Deutschland | G17: Domain sofortangebot.app | H17: Sandra Holm, Wielandstr. 11, 12159 Berlin | I17: EUR | J17: 13.03 | K17: 0.19 | L17: 2.47 | M17: 15.5 | N17: 15.5 | O17: USt. (19%) direkt von IONOS ausgewiesen, kein Reverse Charge. Hinweis für Steuerberater: Die Spalte 'Betrag (EUR)' auf IONOS-Rechnungen zeigt Brutto-Positionsbeträge, obwohl daneben eine MwSt.-Spalte steht — Netto/USt werden nur für die Rechnungssumme insgesamt ausgewiesen, nicht je Zeile. Der Sofortangebot-Anteil (Brutto) wurde deshalb direkt aus den Positionsbeträgen gebildet. | P17: =M17 | Q17: PayPal | R17: IONOS Rechnung 2026-06-26 - RG_100189466040.pdf | S17: Erste Rechnung mit sofortangebot.app: Domain .app registriert 08.06.2026 (12,00 € brutto). Sandy hat am 02.09.2026 bestätigt, dass 'Domain Guard' (1,00 € brutto, Privatsphärenschutz) UND 'IONOS Mail Basic 5' (2,50 €/Monat, ab 08.06.2026) ebenfalls zu sofortangebot.app gehören — damit ist die komplette Rechnung (15,50 €) dem Sofortangebot-Anteil zugeordnet. Alle 5 IONOS-Rechnungen laufen unter Vertragsnummer 111811442, die mehrere fremde Domains bündelt (siehe 2026-011/012), die weiterhin ausgeschlossen bleiben. Neu entdeckt: Update 2026-09-02, Zuordnung bestätigt 2026-09-02. | T17: =ROUND(L17,2)
A18: 2026-014 | B18: 46229 | C18: 100191208015 | D18: 08.07.–07.08.2026 (IONOS Mail Basic 5) | E18: IONOS SE | F18: Deutschland | G18: Domain sofortangebot.app | H18: Sandra Holm, Wielandstr. 11, 12159 Berlin | I18: EUR | J18: 2.1 | K18: 0.19 | L18: 0.4 | M18: 2.5 | N18: 2.5 | O18: USt. (19%) direkt von IONOS ausgewiesen, kein Reverse Charge. | P18: =M18 | Q18: PayPal | R18: IONOS Rechnung 2026-07-26 - RG_100191208015.pdf | S18: Nur Position 'IONOS Mail Basic 5' (2,50 €) — dasselbe Postfach wie in 2026-013. Sandy hat am 02.09.2026 bestätigt, dass es zu sofortangebot.app gehört. Neu entdeckt: Update 2026-09-02, Zuordnung bestätigt 2026-09-02. | T18: =ROUND(L18,2)
A19: 2026-015 | B19: 46256 | C19: TT0BDQ8S-0005 | D19: 22.08.–21.09.2026 | E19: Vercel Inc. | F19: USA | G19: Vercel | H19: einfachanfrage's projects, Wielandstraße 11, 12159 Berlin (einfachanfrage@outlook.com) | I19: USD | J19: 20 | K19: 0.19 | L19: 3.8 | M19: 23.8 | N19: 23.8 | O19: USt. (19%) direkt von Vercel ausgewiesen (EU VAT EU056329113), kein Reverse Charge. | P19: =M19/$B$42 | Q19: Kreditkarte Visa •••3991 | R19: Invoice-TT0BDQ8S-0005.pdf / Receipt-2017-0960.pdf | S19: Weiterhin 'Observability Plus' Position mit $0,00. Zahlungsart über Zahlungsbeleg bestätigt: Visa-Karte endet auf 3991 (gilt rückwirkend auch für 2026-002/005/007, dort ergänzt). | T19: =ROUND(L19/$B$42,2)
A20: 2026-016 | B20: 46257 | C20: MVGOOM-00007 | D20: 23.07.–22.08.2026 (Nutzung) + 23.08.–22.09.2026 (Pro Plan) | E20: Supabase Pte. Ltd. | F20: Singapur | G20: Supabase | H20: Sandra Holm, Wielandstraße 11, Berlin (einfachanfrage@outlook.com) | I20: USD | J20: 53.83 | K20: Reverse Charge | L20: 0 | M20: 53.83 | N20: 53.83 | O20: Reverse Charge — Supabase weist keine USt aus. Sandy startet als Kleinunternehmerin nach §19 UStG (bestätigt 19.08.2026), Gewerbe aber noch nicht angemeldet. Nach Kleinunternehmerregelung i. d. R. keine Vorsteuer ziehbar, aber die USt-Pflicht auf reverse-charge-Leistungen aus dem Ausland (§13b UStG) kann trotzdem bestehen bleiben — das ist keine verbindliche Auskunft von mir, bitte mit Steuerberater final klären, sobald einer feststeht. | P20: =M20/$B$42 | Q20: unbekannt | R20: Invoice-MVGOOM-00007.pdf / Receipt-MVGOOM-00007.pdf | S20: Nutzungsgebühren leicht gesunken ggü. Juli ($54,30 → $53,83). Positiv aufgefallen: nur noch 4 Projekt-Referenzen in den Positionen sichtbar (bkldyddstovvkkhpiqiy, ezgyklsigzaowrrpqtpv, qsdbnckgzllyypmkmzhc, yqlledouhfovytifeekd) — die fünfte aus den Vormonaten ('ytvysmwepajatcdhkgup') taucht hier nicht mehr auf. Könnte bedeuten, dass ein ungenutztes Projekt zwischenzeitlich entfernt wurde (siehe offener Punkt '5 vs. 2 dokumentierte Projekte'). | T20: 0,00 (durchlaufend)
A21: 2026-017 | B21: 46260 | C21: 100192688572 | D21: 08.08.–07.09.2026 (IONOS Mail Basic 5) | E21: IONOS SE | F21: Deutschland | G21: Domain sofortangebot.app | H21: Sandra Holm, Wielandstr. 11, 12159 Berlin | I21: EUR | J21: 2.1 | K21: 0.19 | L21: 0.4 | M21: 2.5 | N21: 2.5 | O21: USt. (19%) direkt von IONOS ausgewiesen, kein Reverse Charge. | P21: =M21 | Q21: PayPal | R21: IONOS Rechnung 2026-08-26 - RG_100192688572.pdf | S21: Wie Juli: nur 'IONOS Mail Basic 5' (2,50 €). Sandy hat am 02.09.2026 bestätigt, dass es zu sofortangebot.app gehört (siehe 2026-013/014). | T21: =ROUND(L21,2)
A22: 2026-018 | B22: 46269 | C22: B6818653 | D22: Leistung/Lieferung 04.09.2026 (Download), Bestellung 02.09.2026 | E22: DIN Media GmbH | F22: Deutschland | G22: Fachliteratur — VOB Gesamtausgabe 2019, Teil A/B/C (E-Book) | H22: Sandra Holm, Wielandstr. 11, 12159 Berlin | I22: EUR | J22: 50.47 | K22: 0.07 | L22: 3.53 | M22: 54 | N22: 54 | O22: USt. (7 % ermaessigt, § 12 Abs. 2 Nr. 14 UStG — E-Book) direkt von DIN Media ausgewiesen, USt-IdNr. DE811236989. Inlandsrechnung, kein Reverse Charge. | P22: =M22 | Q22: Vorkasse, bezahlt 03.09.2026 (Auftrag 11964539), Rechnung weist 54,00 EUR als bereits gezahlt aus | R22: 406270316_ZUGFeRD.pdf | S22: ERSTE ECHTE E-RECHNUNG IM EINGANG. ZUGFeRD/Factur-X, Profil EXTENDED, EN-16931-konform, TestIndicator=false; strukturierter Teil factur-x.xml im PDF/A-3 eingebettet. 11-Punkte-Pruefung nach § 14 UStG vollstaendig bestanden, Sicht- und XML-Teil stimmen ueberein. Einmalige Anschaffung — bewusst NICHT im Blatt Kostenuebersicht/Monatsverlauf, die nur laufende Kosten fuehren. Bestellt ueber die Privatadresse sk-holm@hotmail.de, kuenftig rechnung@sofortangebot.app verwenden. | T22: =ROUND(L22,2)
S23: Summe erfasste Vorsteuer 2026 (Reverse Charge steht mit 0, weil durchlaufend) → | T23: =ROUND(SUM(T5:T22),2)
S24: davon noch OFFEN — aus zwei verschiedenen Gruenden (Belege 2026-001, -009, -012) → | T24: =ROUND(T5+T13+T16,2)
S25: unstrittig abziehbar → | T25: =ROUND(T23-T24,2)
S26: KORREKTUR 17.09.2026 (Head of Finance), nach einem berechtigten Einwand von Sandy: Die erste Fassung dieser Zeilen hat 14,76 EUR als strittig gefuehrt und dabei die KLEINBETRAGSREGELUNG uebersehen. Nach § 33 UStDV braucht eine Rechnung bis 250 EUR brutto WEDER Namen NOCH Anschrift des Leistungsempfaengers — nur Lieferant, Datum, Leistung, Bruttobetrag und Steuersatz. Damit ist Beleg 2026-004 (OpenAI, "Hugo", 15,50 EUR brutto) vollstaendig abzugsfaehig, und bei den Apple-Belegen ist die abweichende Anschrift ebenfalls unschaedlich. Fast alle Belege dieses Betriebs liegen unter 250 EUR. ES BLEIBEN ZWEI ECHTE PUNKTE, beide KEINE Formfehler: (1) 2026-001 und 2026-009, Claude Pro ueber Apple, zusammen 7,02 EUR — offen ist die BETRIEBLICHE VERANLASSUNG (geschaeftlich oder privat genutzt), seit 02.09. vermerkt. (2) 2026-012, IONOS, 5,27 EUR — die Rechnung betrifft drei fremde Domains, Sofortangebot-Anteil 0,00 EUR, also insoweit keine betriebliche Veranlassung. Ausnahme von § 33 UStDV, die hier nicht greift: bei Reverse-Charge-Umsaetzen (§ 13b) gilt die Erleichterung NICHT — die Supabase-Belege brauchen weiter volle Angaben.
A37: Umrechnung USD → EUR — BMF-Umsatzsteuer-Umrechnungskurse (§ 16 Abs. 6 UStG)
A38: Monat 2026 | B38: Kurs (USD je 1 EUR)
A39: Mai | B39: 1.1673
A40: Juni | B40: 1.1518
A41: Juli | B41: 1.1417
A42: August | B42: 1.1593
A44: Maßgeblich ist der Monat des Rechnungsdatums (bei Supabase zugleich der Monat, in dem die Dauerleistung endet und die Steuer nach § 13b UStG entsteht). Quelle: BMF-Schreiben vom 01.09.2026, Gz. III C 3 - S 7329/00014/008/112, monatlich fortgeschriebene Übersicht 2026. Neuen Monat hier ergänzen — Spalte P rechnet dann von selbst. Für EUR-Belege verweist Spalte P unverändert auf den Bruttobetrag.

Sheet Monatsverlauf
A1: Monatsverlauf laufende Kosten
A2: Werte werden per Formel aus dem 'Rechnungsjournal' gezogen (nach Rechnungsmonat, Dienst und Währung) — beim Ergänzen neuer Belege im Journal aktualisiert sich diese Ansicht automatisch. Leere Zelle = noch kein Beleg für diesen Monat gefunden.
A4: Dienst | B4: Mai 2026 | C4: Jun 2026 | D4: Jul 2026 | E4: Aug 2026 | F4: Sep 2026 | G4: Okt 2026 | H4: Nov 2026 | I4: Dez 2026 | J4: Gesamt (Zeitraum)
A5: Supabase | B5: =IF(COUNTIFS(Rechnungsjournal!$G$5:$G$34,$A5,Rechnungsjournal!$B$5:$B$34,">="&DATE(2026,5,1),Rechnungsjournal!$B$5:$B$34,"<"&DATE(2026,6,1))=0,"",SUMIFS(Rechnungsjournal!$N$5:$N$34,Rechnungsjournal!$G$5:$G$34,$A5,Rechnungsjournal!$B$5:$B$34,">="&DATE(2026,5,1),Rechnungsjournal!$B$5:$B$34,"<"&DATE(2026,6,1))) | C5: =IF(COUNTIFS(Rechnungsjournal!$G$5:$G$34,$A5,Rechnungsjournal!$B$5:$B$34,">="&DATE(2026,6,1),Rechnungsjournal!$B$5:$B$34,"<"&DATE(2026,7,1))=0,"",SUMIFS(Rechnungsjournal!$N$5:$N$34,Rechnungsjournal!$G$5:$G$34,$A5,Rechnungsjournal!$B$5:$B$34,">="&DATE(2026,6,1),Rechnungsjournal!$B$5:$B$34,"<"&DATE(2026,7,1))) | D5: =IF(COUNTIFS(Rechnungsjournal!$G$5:$G$34,$A5,Rechnungsjournal!$B$5:$B$34,">="&DATE(2026,7,1),Rechnungsjournal!$B$5:$B$34,"<"&DATE(2026,8,1))=0,"",SUMIFS(Rechnungsjournal!$N$5:$N$34,Rechnungsjournal!$G$5:$G$34,$A5,Rechnungsjournal!$B$5:$B$34,">="&DATE(2026,7,1),Rechnungsjournal!$B$5:$B$34,"<"&DATE(2026,8,1))) | E5: =IF(COUNTIFS(Rechnungsjournal!$G$5:$G$34,$A5,Rechnungsjournal!$B$5:$B$34,">="&DATE(2026,8,1),Rechnungsjournal!$B$5:$B$34,"<"&DATE(2026,9,1))=0,"",SUMIFS(Rechnungsjournal!$N$5:$N$34,Rechnungsjournal!$G$5:$G$34,$A5,Rechnungsjournal!$B$5:$B$34,">="&DATE(2026,8,1),Rechnungsjournal!$B$5:$B$34,"<"&DATE(2026,9,1))) | F5: =IF(COUNTIFS(Rechnungsjournal!$G$5:$G$34,$A5,Rechnungsjournal!$B$5:$B$34,">="&DATE(2026,9,1),Rechnungsjournal!$B$5:$B$34,"<"&DATE(2026,10,1))=0,"",SUMIFS(Rechnungsjournal!$N$5:$N$34,Rechnungsjournal!$G$5:$G$34,$A5,Rechnungsjournal!$B$5:$B$34,">="&DATE(2026,9,1),Rechnungsjournal!$B$5:$B$34,"<"&DATE(2026,10,1))) | G5: =IF(COUNTIFS(Rechnungsjournal!$G$5:$G$34,$A5,Rechnungsjournal!$B$5:$B$34,">="&DATE(2026,10,1),Rechnungsjournal!$B$5:$B$34,"<"&DATE(2026,11,1))=0,"",SUMIFS(Rechnungsjournal!$N$5:$N$34,Rechnungsjournal!$G$5:$G$34,$A5,Rechnungsjournal!$B$5:$B$34,">="&DATE(2026,10,1),Rechnungsjournal!$B$5:$B$34,"<"&DATE(2026,11,1))) | H5: =IF(COUNTIFS(Rechnungsjournal!$G$5:$G$34,$A5,Rechnungsjournal!$B$5:$B$34,">="&DATE(2026,11,1),Rechnungsjournal!$B$5:$B$34,"<"&DATE(2026,12,1))=0,"",SUMIFS(Rechnungsjournal!$N$5:$N$34,Rechnungsjournal!$G$5:$G$34,$A5,Rechnungsjournal!$B$5:$B$34,">="&DATE(2026,11,1),Rechnungsjournal!$B$5:$B$34,"<"&DATE(2026,12,1))) | I5: =IF(COUNTIFS(Rechnungsjournal!$G$5:$G$34,$A5,Rechnungsjournal!$B$5:$B$34,">="&DATE(2026,12,1),Rechnungsjournal!$B$5:$B$34,"<"&DATE(2027,1,1))=0,"",SUMIFS(Rechnungsjournal!$N$5:$N$34,Rechnungsjournal!$G$5:$G$34,$A5,Rechnungsjournal!$B$5:$B$34,">="&DATE(2026,12,1),Rechnungsjournal!$B$5:$B$34,"<"&DATE(2027,1,1))) | J5: =SUM(B5:I5)
A6: Vercel | B6: =IF(COUNTIFS(Rechnungsjournal!$G$5:$G$34,$A6,Rechnungsjournal!$B$5:$B$34,">="&DATE(2026,5,1),Rechnungsjournal!$B$5:$B$34,"<"&DATE(2026,6,1))=0,"",SUMIFS(Rechnungsjournal!$N$5:$N$34,Rechnungsjournal!$G$5:$G$34,$A6,Rechnungsjournal!$B$5:$B$34,">="&DATE(2026,5,1),Rechnungsjournal!$B$5:$B$34,"<"&DATE(2026,6,1))) | C6: =IF(COUNTIFS(Rechnungsjournal!$G$5:$G$34,$A6,Rechnungsjournal!$B$5:$B$34,">="&DATE(2026,6,1),Rechnungsjournal!$B$5:$B$34,"<"&DATE(2026,7,1))=0,"",SUMIFS(Rechnungsjournal!$N$5:$N$34,Rechnungsjournal!$G$5:$G$34,$A6,Rechnungsjournal!$B$5:$B$34,">="&DATE(2026,6,1),Rechnungsjournal!$B$5:$B$34,"<"&DATE(2026,7,1))) | D6: =IF(COUNTIFS(Rechnungsjournal!$G$5:$G$34,$A6,Rechnungsjournal!$B$5:$B$34,">="&DATE(2026,7,1),Rechnungsjournal!$B$5:$B$34,"<"&DATE(2026,8,1))=0,"",SUMIFS(Rechnungsjournal!$N$5:$N$34,Rechnungsjournal!$G$5:$G$34,$A6,Rechnungsjournal!$B$5:$B$34,">="&DATE(2026,7,1),Rechnungsjournal!$B$5:$B$34,"<"&DATE(2026,8,1))) | E6: =IF(COUNTIFS(Rechnungsjournal!$G$5:$G$34,$A6,Rechnungsjournal!$B$5:$B$34,">="&DATE(2026,8,1),Rechnungsjournal!$B$5:$B$34,"<"&DATE(2026,9,1))=0,"",SUMIFS(Rechnungsjournal!$N$5:$N$34,Rechnungsjournal!$G$5:$G$34,$A6,Rechnungsjournal!$B$5:$B$34,">="&DATE(2026,8,1),Rechnungsjournal!$B$5:$B$34,"<"&DATE(2026,9,1))) | F6: =IF(COUNTIFS(Rechnungsjournal!$G$5:$G$34,$A6,Rechnungsjournal!$B$5:$B$34,">="&DATE(2026,9,1),Rechnungsjournal!$B$5:$B$34,"<"&DATE(2026,10,1))=0,"",SUMIFS(Rechnungsjournal!$N$5:$N$34,Rechnungsjournal!$G$5:$G$34,$A6,Rechnungsjournal!$B$5:$B$34,">="&DATE(2026,9,1),Rechnungsjournal!$B$5:$B$34,"<"&DATE(2026,10,1))) | G6: =IF(COUNTIFS(Rechnungsjournal!$G$5:$G$34,$A6,Rechnungsjournal!$B$5:$B$34,">="&DATE(2026,10,1),Rechnungsjournal!$B$5:$B$34,"<"&DATE(2026,11,1))=0,"",SUMIFS(Rechnungsjournal!$N$5:$N$34,Rechnungsjournal!$G$5:$G$34,$A6,Rechnungsjournal!$B$5:$B$34,">="&DATE(2026,10,1),Rechnungsjournal!$B$5:$B$34,"<"&DATE(2026,11,1))) | H6: =IF(COUNTIFS(Rechnungsjournal!$G$5:$G$34,$A6,Rechnungsjournal!$B$5:$B$34,">="&DATE(2026,11,1),Rechnungsjournal!$B$5:$B$34,"<"&DATE(2026,12,1))=0,"",SUMIFS(Rechnungsjournal!$N$5:$N$34,Rechnungsjournal!$G$5:$G$34,$A6,Rechnungsjournal!$B$5:$B$34,">="&DATE(2026,11,1),Rechnungsjournal!$B$5:$B$34,"<"&DATE(2026,12,1))) | I6: =IF(COUNTIFS(Rechnungsjournal!$G$5:$G$34,$A6,Rechnungsjournal!$B$5:$B$34,">="&DATE(2026,12,1),Rechnungsjournal!$B$5:$B$34,"<"&DATE(2027,1,1))=0,"",SUMIFS(Rechnungsjournal!$N$5:$N$34,Rechnungsjournal!$G$5:$G$34,$A6,Rechnungsjournal!$B$5:$B$34,">="&DATE(2026,12,1),Rechnungsjournal!$B$5:$B$34,"<"&DATE(2027,1,1))) | J6: =SUM(B6:I6)
A7: Anthropic — direkt | B7: =IF(COUNTIFS(Rechnungsjournal!$G$5:$G$34,$A7,Rechnungsjournal!$B$5:$B$34,">="&DATE(2026,5,1),Rechnungsjournal!$B$5:$B$34,"<"&DATE(2026,6,1))=0,"",SUMIFS(Rechnungsjournal!$N$5:$N$34,Rechnungsjournal!$G$5:$G$34,$A7,Rechnungsjournal!$B$5:$B$34,">="&DATE(2026,5,1),Rechnungsjournal!$B$5:$B$34,"<"&DATE(2026,6,1))) | C7: =IF(COUNTIFS(Rechnungsjournal!$G$5:$G$34,$A7,Rechnungsjournal!$B$5:$B$34,">="&DATE(2026,6,1),Rechnungsjournal!$B$5:$B$34,"<"&DATE(2026,7,1))=0,"",SUMIFS(Rechnungsjournal!$N$5:$N$34,Rechnungsjournal!$G$5:$G$34,$A7,Rechnungsjournal!$B$5:$B$34,">="&DATE(2026,6,1),Rechnungsjournal!$B$5:$B$34,"<"&DATE(2026,7,1))) | D7: =IF(COUNTIFS(Rechnungsjournal!$G$5:$G$34,$A7,Rechnungsjournal!$B$5:$B$34,">="&DATE(2026,7,1),Rechnungsjournal!$B$5:$B$34,"<"&DATE(2026,8,1))=0,"",SUMIFS(Rechnungsjournal!$N$5:$N$34,Rechnungsjournal!$G$5:$G$34,$A7,Rechnungsjournal!$B$5:$B$34,">="&DATE(2026,7,1),Rechnungsjournal!$B$5:$B$34,"<"&DATE(2026,8,1))) | E7: =IF(COUNTIFS(Rechnungsjournal!$G$5:$G$34,$A7,Rechnungsjournal!$B$5:$B$34,">="&DATE(2026,8,1),Rechnungsjournal!$B$5:$B$34,"<"&DATE(2026,9,1))=0,"",SUMIFS(Rechnungsjournal!$N$5:$N$34,Rechnungsjournal!$G$5:$G$34,$A7,Rechnungsjournal!$B$5:$B$34,">="&DATE(2026,8,1),Rechnungsjournal!$B$5:$B$34,"<"&DATE(2026,9,1))) | F7: =IF(COUNTIFS(Rechnungsjournal!$G$5:$G$34,$A7,Rechnungsjournal!$B$5:$B$34,">="&DATE(2026,9,1),Rechnungsjournal!$B$5:$B$34,"<"&DATE(2026,10,1))=0,"",SUMIFS(Rechnungsjournal!$N$5:$N$34,Rechnungsjournal!$G$5:$G$34,$A7,Rechnungsjournal!$B$5:$B$34,">="&DATE(2026,9,1),Rechnungsjournal!$B$5:$B$34,"<"&DATE(2026,10,1))) | G7: =IF(COUNTIFS(Rechnungsjournal!$G$5:$G$34,$A7,Rechnungsjournal!$B$5:$B$34,">="&DATE(2026,10,1),Rechnungsjournal!$B$5:$B$34,"<"&DATE(2026,11,1))=0,"",SUMIFS(Rechnungsjournal!$N$5:$N$34,Rechnungsjournal!$G$5:$G$34,$A7,Rechnungsjournal!$B$5:$B$34,">="&DATE(2026,10,1),Rechnungsjournal!$B$5:$B$34,"<"&DATE(2026,11,1))) | H7: =IF(COUNTIFS(Rechnungsjournal!$G$5:$G$34,$A7,Rechnungsjournal!$B$5:$B$34,">="&DATE(2026,11,1),Rechnungsjournal!$B$5:$B$34,"<"&DATE(2026,12,1))=0,"",SUMIFS(Rechnungsjournal!$N$5:$N$34,Rechnungsjournal!$G$5:$G$34,$A7,Rechnungsjournal!$B$5:$B$34,">="&DATE(2026,11,1),Rechnungsjournal!$B$5:$B$34,"<"&DATE(2026,12,1))) | I7: =IF(COUNTIFS(Rechnungsjournal!$G$5:$G$34,$A7,Rechnungsjournal!$B$5:$B$34,">="&DATE(2026,12,1),Rechnungsjournal!$B$5:$B$34,"<"&DATE(2027,1,1))=0,"",SUMIFS(Rechnungsjournal!$N$5:$N$34,Rechnungsjournal!$G$5:$G$34,$A7,Rechnungsjournal!$B$5:$B$34,">="&DATE(2026,12,1),Rechnungsjournal!$B$5:$B$34,"<"&DATE(2027,1,1))) | J7: =SUM(B7:I7)
A8: Claude Pro (Apple/iTunes) | B8: =IF(COUNTIFS(Rechnungsjournal!$G$5:$G$34,$A8,Rechnungsjournal!$B$5:$B$34,">="&DATE(2026,5,1),Rechnungsjournal!$B$5:$B$34,"<"&DATE(2026,6,1))=0,"",SUMIFS(Rechnungsjournal!$N$5:$N$34,Rechnungsjournal!$G$5:$G$34,$A8,Rechnungsjournal!$B$5:$B$34,">="&DATE(2026,5,1),Rechnungsjournal!$B$5:$B$34,"<"&DATE(2026,6,1))) | C8: =IF(COUNTIFS(Rechnungsjournal!$G$5:$G$34,$A8,Rechnungsjournal!$B$5:$B$34,">="&DATE(2026,6,1),Rechnungsjournal!$B$5:$B$34,"<"&DATE(2026,7,1))=0,"",SUMIFS(Rechnungsjournal!$N$5:$N$34,Rechnungsjournal!$G$5:$G$34,$A8,Rechnungsjournal!$B$5:$B$34,">="&DATE(2026,6,1),Rechnungsjournal!$B$5:$B$34,"<"&DATE(2026,7,1))) | D8: =IF(COUNTIFS(Rechnungsjournal!$G$5:$G$34,$A8,Rechnungsjournal!$B$5:$B$34,">="&DATE(2026,7,1),Rechnungsjournal!$B$5:$B$34,"<"&DATE(2026,8,1))=0,"",SUMIFS(Rechnungsjournal!$N$5:$N$34,Rechnungsjournal!$G$5:$G$34,$A8,Rechnungsjournal!$B$5:$B$34,">="&DATE(2026,7,1),Rechnungsjournal!$B$5:$B$34,"<"&DATE(2026,8,1))) | E8: =IF(COUNTIFS(Rechnungsjournal!$G$5:$G$34,$A8,Rechnungsjournal!$B$5:$B$34,">="&DATE(2026,8,1),Rechnungsjournal!$B$5:$B$34,"<"&DATE(2026,9,1))=0,"",SUMIFS(Rechnungsjournal!$N$5:$N$34,Rechnungsjournal!$G$5:$G$34,$A8,Rechnungsjournal!$B$5:$B$34,">="&DATE(2026,8,1),Rechnungsjournal!$B$5:$B$34,"<"&DATE(2026,9,1))) | F8: =IF(COUNTIFS(Rechnungsjournal!$G$5:$G$34,$A8,Rechnungsjournal!$B$5:$B$34,">="&DATE(2026,9,1),Rechnungsjournal!$B$5:$B$34,"<"&DATE(2026,10,1))=0,"",SUMIFS(Rechnungsjournal!$N$5:$N$34,Rechnungsjournal!$G$5:$G$34,$A8,Rechnungsjournal!$B$5:$B$34,">="&DATE(2026,9,1),Rechnungsjournal!$B$5:$B$34,"<"&DATE(2026,10,1))) | G8: =IF(COUNTIFS(Rechnungsjournal!$G$5:$G$34,$A8,Rechnungsjournal!$B$5:$B$34,">="&DATE(2026,10,1),Rechnungsjournal!$B$5:$B$34,"<"&DATE(2026,11,1))=0,"",SUMIFS(Rechnungsjournal!$N$5:$N$34,Rechnungsjournal!$G$5:$G$34,$A8,Rechnungsjournal!$B$5:$B$34,">="&DATE(2026,10,1),Rechnungsjournal!$B$5:$B$34,"<"&DATE(2026,11,1))) | H8: =IF(COUNTIFS(Rechnungsjournal!$G$5:$G$34,$A8,Rechnungsjournal!$B$5:$B$34,">="&DATE(2026,11,1),Rechnungsjournal!$B$5:$B$34,"<"&DATE(2026,12,1))=0,"",SUMIFS(Rechnungsjournal!$N$5:$N$34,Rechnungsjournal!$G$5:$G$34,$A8,Rechnungsjournal!$B$5:$B$34,">="&DATE(2026,11,1),Rechnungsjournal!$B$5:$B$34,"<"&DATE(2026,12,1))) | I8: =IF(COUNTIFS(Rechnungsjournal!$G$5:$G$34,$A8,Rechnungsjournal!$B$5:$B$34,">="&DATE(2026,12,1),Rechnungsjournal!$B$5:$B$34,"<"&DATE(2027,1,1))=0,"",SUMIFS(Rechnungsjournal!$N$5:$N$34,Rechnungsjournal!$G$5:$G$34,$A8,Rechnungsjournal!$B$5:$B$34,">="&DATE(2026,12,1),Rechnungsjournal!$B$5:$B$34,"<"&DATE(2027,1,1))) | J8: =SUM(B8:I8)
A9: OpenAI | B9: =IF(COUNTIFS(Rechnungsjournal!$G$5:$G$34,$A9,Rechnungsjournal!$B$5:$B$34,">="&DATE(2026,5,1),Rechnungsjournal!$B$5:$B$34,"<"&DATE(2026,6,1))=0,"",SUMIFS(Rechnungsjournal!$N$5:$N$34,Rechnungsjournal!$G$5:$G$34,$A9,Rechnungsjournal!$B$5:$B$34,">="&DATE(2026,5,1),Rechnungsjournal!$B$5:$B$34,"<"&DATE(2026,6,1))) | C9: =IF(COUNTIFS(Rechnungsjournal!$G$5:$G$34,$A9,Rechnungsjournal!$B$5:$B$34,">="&DATE(2026,6,1),Rechnungsjournal!$B$5:$B$34,"<"&DATE(2026,7,1))=0,"",SUMIFS(Rechnungsjournal!$N$5:$N$34,Rechnungsjournal!$G$5:$G$34,$A9,Rechnungsjournal!$B$5:$B$34,">="&DATE(2026,6,1),Rechnungsjournal!$B$5:$B$34,"<"&DATE(2026,7,1))) | D9: =IF(COUNTIFS(Rechnungsjournal!$G$5:$G$34,$A9,Rechnungsjournal!$B$5:$B$34,">="&DATE(2026,7,1),Rechnungsjournal!$B$5:$B$34,"<"&DATE(2026,8,1))=0,"",SUMIFS(Rechnungsjournal!$N$5:$N$34,Rechnungsjournal!$G$5:$G$34,$A9,Rechnungsjournal!$B$5:$B$34,">="&DATE(2026,7,1),Rechnungsjournal!$B$5:$B$34,"<"&DATE(2026,8,1))) | E9: =IF(COUNTIFS(Rechnungsjournal!$G$5:$G$34,$A9,Rechnungsjournal!$B$5:$B$34,">="&DATE(2026,8,1),Rechnungsjournal!$B$5:$B$34,"<"&DATE(2026,9,1))=0,"",SUMIFS(Rechnungsjournal!$N$5:$N$34,Rechnungsjournal!$G$5:$G$34,$A9,Rechnungsjournal!$B$5:$B$34,">="&DATE(2026,8,1),Rechnungsjournal!$B$5:$B$34,"<"&DATE(2026,9,1))) | F9: =IF(COUNTIFS(Rechnungsjournal!$G$5:$G$34,$A9,Rechnungsjournal!$B$5:$B$34,">="&DATE(2026,9,1),Rechnungsjournal!$B$5:$B$34,"<"&DATE(2026,10,1))=0,"",SUMIFS(Rechnungsjournal!$N$5:$N$34,Rechnungsjournal!$G$5:$G$34,$A9,Rechnungsjournal!$B$5:$B$34,">="&DATE(2026,9,1),Rechnungsjournal!$B$5:$B$34,"<"&DATE(2026,10,1))) | G9: =IF(COUNTIFS(Rechnungsjournal!$G$5:$G$34,$A9,Rechnungsjournal!$B$5:$B$34,">="&DATE(2026,10,1),Rechnungsjournal!$B$5:$B$34,"<"&DATE(2026,11,1))=0,"",SUMIFS(Rechnungsjournal!$N$5:$N$34,Rechnungsjournal!$G$5:$G$34,$A9,Rechnungsjournal!$B$5:$B$34,">="&DATE(2026,10,1),Rechnungsjournal!$B$5:$B$34,"<"&DATE(2026,11,1))) | H9: =IF(COUNTIFS(Rechnungsjournal!$G$5:$G$34,$A9,Rechnungsjournal!$B$5:$B$34,">="&DATE(2026,11,1),Rechnungsjournal!$B$5:$B$34,"<"&DATE(2026,12,1))=0,"",SUMIFS(Rechnungsjournal!$N$5:$N$34,Rechnungsjournal!$G$5:$G$34,$A9,Rechnungsjournal!$B$5:$B$34,">="&DATE(2026,11,1),Rechnungsjournal!$B$5:$B$34,"<"&DATE(2026,12,1))) | I9: =IF(COUNTIFS(Rechnungsjournal!$G$5:$G$34,$A9,Rechnungsjournal!$B$5:$B$34,">="&DATE(2026,12,1),Rechnungsjournal!$B$5:$B$34,"<"&DATE(2027,1,1))=0,"",SUMIFS(Rechnungsjournal!$N$5:$N$34,Rechnungsjournal!$G$5:$G$34,$A9,Rechnungsjournal!$B$5:$B$34,">="&DATE(2026,12,1),Rechnungsjournal!$B$5:$B$34,"<"&DATE(2027,1,1))) | J9: =SUM(B9:I9)
A10: Resend | J10: =SUM(B10:I10)
A11: Domain sofortangebot.app | B11: =IF(COUNTIFS(Rechnungsjournal!$G$5:$G$34,$A11,Rechnungsjournal!$B$5:$B$34,">="&DATE(2026,5,1),Rechnungsjournal!$B$5:$B$34,"<"&DATE(2026,6,1))=0,"",SUMIFS(Rechnungsjournal!$N$5:$N$34,Rechnungsjournal!$G$5:$G$34,$A11,Rechnungsjournal!$B$5:$B$34,">="&DATE(2026,5,1),Rechnungsjournal!$B$5:$B$34,"<"&DATE(2026,6,1))) | C11: =IF(COUNTIFS(Rechnungsjournal!$G$5:$G$34,$A11,Rechnungsjournal!$B$5:$B$34,">="&DATE(2026,6,1),Rechnungsjournal!$B$5:$B$34,"<"&DATE(2026,7,1))=0,"",SUMIFS(Rechnungsjournal!$N$5:$N$34,Rechnungsjournal!$G$5:$G$34,$A11,Rechnungsjournal!$B$5:$B$34,">="&DATE(2026,6,1),Rechnungsjournal!$B$5:$B$34,"<"&DATE(2026,7,1))) | D11: =IF(COUNTIFS(Rechnungsjournal!$G$5:$G$34,$A11,Rechnungsjournal!$B$5:$B$34,">="&DATE(2026,7,1),Rechnungsjournal!$B$5:$B$34,"<"&DATE(2026,8,1))=0,"",SUMIFS(Rechnungsjournal!$N$5:$N$34,Rechnungsjournal!$G$5:$G$34,$A11,Rechnungsjournal!$B$5:$B$34,">="&DATE(2026,7,1),Rechnungsjournal!$B$5:$B$34,"<"&DATE(2026,8,1))) | E11: =IF(COUNTIFS(Rechnungsjournal!$G$5:$G$34,$A11,Rechnungsjournal!$B$5:$B$34,">="&DATE(2026,8,1),Rechnungsjournal!$B$5:$B$34,"<"&DATE(2026,9,1))=0,"",SUMIFS(Rechnungsjournal!$N$5:$N$34,Rechnungsjournal!$G$5:$G$34,$A11,Rechnungsjournal!$B$5:$B$34,">="&DATE(2026,8,1),Rechnungsjournal!$B$5:$B$34,"<"&DATE(2026,9,1))) | F11: =IF(COUNTIFS(Rechnungsjournal!$G$5:$G$34,$A11,Rechnungsjournal!$B$5:$B$34,">="&DATE(2026,9,1),Rechnungsjournal!$B$5:$B$34,"<"&DATE(2026,10,1))=0,"",SUMIFS(Rechnungsjournal!$N$5:$N$34,Rechnungsjournal!$G$5:$G$34,$A11,Rechnungsjournal!$B$5:$B$34,">="&DATE(2026,9,1),Rechnungsjournal!$B$5:$B$34,"<"&DATE(2026,10,1))) | G11: =IF(COUNTIFS(Rechnungsjournal!$G$5:$G$34,$A11,Rechnungsjournal!$B$5:$B$34,">="&DATE(2026,10,1),Rechnungsjournal!$B$5:$B$34,"<"&DATE(2026,11,1))=0,"",SUMIFS(Rechnungsjournal!$N$5:$N$34,Rechnungsjournal!$G$5:$G$34,$A11,Rechnungsjournal!$B$5:$B$34,">="&DATE(2026,10,1),Rechnungsjournal!$B$5:$B$34,"<"&DATE(2026,11,1))) | H11: =IF(COUNTIFS(Rechnungsjournal!$G$5:$G$34,$A11,Rechnungsjournal!$B$5:$B$34,">="&DATE(2026,11,1),Rechnungsjournal!$B$5:$B$34,"<"&DATE(2026,12,1))=0,"",SUMIFS(Rechnungsjournal!$N$5:$N$34,Rechnungsjournal!$G$5:$G$34,$A11,Rechnungsjournal!$B$5:$B$34,">="&DATE(2026,11,1),Rechnungsjournal!$B$5:$B$34,"<"&DATE(2026,12,1))) | I11: =IF(COUNTIFS(Rechnungsjournal!$G$5:$G$34,$A11,Rechnungsjournal!$B$5:$B$34,">="&DATE(2026,12,1),Rechnungsjournal!$B$5:$B$34,"<"&DATE(2027,1,1))=0,"",SUMIFS(Rechnungsjournal!$N$5:$N$34,Rechnungsjournal!$G$5:$G$34,$A11,Rechnungsjournal!$B$5:$B$34,">="&DATE(2026,12,1),Rechnungsjournal!$B$5:$B$34,"<"&DATE(2027,1,1))) | J11: =SUM(B11:I11)
A12: Sentry | J12: =SUM(B12:I12)
A13: Stripe | J13: =SUM(B13:I13)
A14: GitHub Actions (Backup-Artefakte) | J14: =SUM(B14:I14)
A16: Monatssumme USD | B16: =IF(B5="",0,B5)+IF(B6="",0,B6)+IF(B7="",0,B7)+IF(B9="",0,B9) | C16: =IF(C5="",0,C5)+IF(C6="",0,C6)+IF(C7="",0,C7)+IF(C9="",0,C9) | D16: =IF(D5="",0,D5)+IF(D6="",0,D6)+IF(D7="",0,D7)+IF(D9="",0,D9) | E16: =IF(E5="",0,E5)+IF(E6="",0,E6)+IF(E7="",0,E7)+IF(E9="",0,E9) | F16: =IF(F5="",0,F5)+IF(F6="",0,F6)+IF(F7="",0,F7)+IF(F9="",0,F9) | G16: =IF(G5="",0,G5)+IF(G6="",0,G6)+IF(G7="",0,G7)+IF(G9="",0,G9) | H16: =IF(H5="",0,H5)+IF(H6="",0,H6)+IF(H7="",0,H7)+IF(H9="",0,H9) | I16: =IF(I5="",0,I5)+IF(I6="",0,I6)+IF(I7="",0,I7)+IF(I9="",0,I9)
A17: Monatssumme EUR | B17: =IF(B8="",0,B8)+IF(B11="",0,B11) | C17: =IF(C8="",0,C8)+IF(C11="",0,C11) | D17: =IF(D8="",0,D8)+IF(D11="",0,D11) | E17: =IF(E8="",0,E8)+IF(E11="",0,E11) | F17: =IF(F8="",0,F8)+IF(F11="",0,F11) | G17: =IF(G8="",0,G8)+IF(G11="",0,G11) | H17: =IF(H8="",0,H8)+IF(H11="",0,H11) | I17: =IF(I8="",0,I8)+IF(I11="",0,I11)

Sheet Plan-Deckblatt
A1: Finanzplan Sofortangebot — Deckblatt (Fassung 2, 03.09.2026)
A2: Die Zahlen, die Sandy braucht, je Szenario. Alles Weitere ist Beleg: 'Plan-Annahmen' (alle Eingaben, gelb) · 'Plan-Kunden' (Kanalmodell und Zeitbudget) · 'Plan-Kosten' (Vollständigkeits-Katalog A–H) · 'Plan-24M' (Monatsraster) · 'Plan-Phase B' (Ausstiegsstufen). Diese Fassung rechnet mit der Rechtsform-Entscheidung vom Abend des 03.09.2026: Einzelunternehmen ab Oktober 2026, UG erst bei rund 20 zahlenden Betrieben. Die erste Fassung (UG ab Monat 1) ist ersetzt — der Vergleich steht unten, die Begründung in docs/chief-of-staff-finance-todos.md.
A6: Was der Plan jetzt kostet statt vorher: 15 € Gründung statt rund 1.700 € (Notar, Handelsregister, Stammkapital) und 800 €/Jahr Buchhaltung statt 3.000 €/Jahr — solange Sandy Einzelunternehmerin ist. Gewerbesteuer und IHK-Beitrag fallen im ganzen Horizont weg (Freibetrag § 11 GewStG, Gründerbefreiung § 3 Abs. 3 IHKG). — Nachtrag 17.09.2026: Mit der Regelbesteuerung sinken die laufenden Kosten um rund 17 €/Monat (Vorsteuer auf Lexware, Vercel, Anthropic, Claude Pro, IONOS). Das verschiebt den Break-even im realistischen Szenario NICHT (weiter Monat 11), verbessert aber den Tiefpunkt der Liquiditaet um rund 300 € und im vorsichtigen Szenario den ersten profitablen Monat von 23 auf 21.
A8: Szenario | B8: Vorsichtig | C8: Realistisch | D8: Optimistisch
A9: Neukunden aus dem Kanalplan (Σ 24 Monate, Marketing) | B9: ='Plan-Kunden'!$C$32 | C9: ='Plan-Kunden'!$C$61 | D9: ='Plan-Kunden'!$C$90
A10: davon zusätzlich durch Mundpropaganda | B10: ='Plan-Kunden'!$D$32 | C10: ='Plan-Kunden'!$D$61 | D10: ='Plan-Kunden'!$D$90
A11: Abwanderung Standardkunden pro Monat (Annahme) | B11: ='Plan-Annahmen'!$B$44 | C11: ='Plan-Annahmen'!$B$45 | D11: ='Plan-Annahmen'!$B$46
A12: Zahlende Betriebe am Ende (Monat 24) | B12: ='Plan-Kunden'!$K$32 | C12: ='Plan-Kunden'!$K$61 | D12: ='Plan-Kunden'!$K$90
A14: 1) Wann trägt es sich?
A15: Erster Monat mit positivem Monatsergebnis — NEUE Fassung | B15: =IFERROR(INDEX('Plan-24M'!$A$8:$A$31,MATCH(1,'Plan-24M'!$X$8:$X$31,0)),"> 24 Monate") | C15: =IFERROR(INDEX('Plan-24M'!$A$37:$A$60,MATCH(1,'Plan-24M'!$X$37:$X$60,0)),"> 24 Monate") | D15: =IFERROR(INDEX('Plan-24M'!$A$66:$A$89,MATCH(1,'Plan-24M'!$X$66:$X$89,0)),"> 24 Monate")
A16: … alte Fassung (UG ab Monat 1) | B16: > 24 Monate | C16: 15 | D16: 11
A17: … Kalendermonat | B17: =IFERROR(INDEX('Plan-24M'!$B$8:$B$31,MATCH(1,'Plan-24M'!$X$8:$X$31,0)),"> 24 Monate") | C17: =IFERROR(INDEX('Plan-24M'!$B$37:$B$60,MATCH(1,'Plan-24M'!$X$37:$X$60,0)),"> 24 Monate") | D17: =IFERROR(INDEX('Plan-24M'!$B$66:$B$89,MATCH(1,'Plan-24M'!$X$66:$X$89,0)),"> 24 Monate")
A18: … zahlende Betriebe in diesem Monat | B18: =IFERROR(INDEX('Plan-24M'!$D$8:$D$31,MATCH(1,'Plan-24M'!$X$8:$X$31,0)),"> 24 Monate") | C18: =IFERROR(INDEX('Plan-24M'!$D$37:$D$60,MATCH(1,'Plan-24M'!$X$37:$X$60,0)),"> 24 Monate") | D18: =IFERROR(INDEX('Plan-24M'!$D$66:$D$89,MATCH(1,'Plan-24M'!$X$66:$X$89,0)),"> 24 Monate")
A19: Umsatz Monat 24 (netto) | B19: ='Plan-24M'!$H$31 | C19: ='Plan-24M'!$H$60 | D19: ='Plan-24M'!$H$89
A20: Umsatz Jahr 1 (Sep 26 – Aug 27) | B20: =SUM('Plan-24M'!$H$8:$H$19) | C20: =SUM('Plan-24M'!$H$37:$H$48) | D20: =SUM('Plan-24M'!$H$66:$H$77)
A21: Umsatz Jahr 2 (Sep 27 – Aug 28) | B21: =SUM('Plan-24M'!$H$20:$H$31) | C21: =SUM('Plan-24M'!$H$49:$H$60) | D21: =SUM('Plan-24M'!$H$78:$H$89)
A23: 2) Wie viel muss Sandy vorstrecken? (mit Vorher/Nachher)
A24: Tiefpunkt der Liquidität — NEUE Fassung (Einzelunternehmen) | B24: =MIN(0,MIN('Plan-24M'!$W$8:$W$31)) | C24: =MIN(0,MIN('Plan-24M'!$W$37:$W$60)) | D24: =MIN(0,MIN('Plan-24M'!$W$66:$W$89))
A25: Tiefpunkt der Liquidität — alte Fassung (UG ab Monat 1) | B25: -14260 | C25: -9280 | D25: -7860
A26: Ersparnis gegenüber der alten Fassung | B26: =B24-B25 | C26: =C24-C25 | D26: =D24-D25
A27: … davon Reserven, die Vermögen bleiben | B27: ='Plan-24M'!$V$31 | C27: ='Plan-24M'!$V$60 | D27: ='Plan-24M'!$V$89
A28: … Monat des Tiefpunkts | B28: =MATCH(MIN('Plan-24M'!$W$8:$W$31),'Plan-24M'!$W$8:$W$31,0) | C28: =MATCH(MIN('Plan-24M'!$W$37:$W$60),'Plan-24M'!$W$37:$W$60,0) | D28: =MATCH(MIN('Plan-24M'!$W$66:$W$89),'Plan-24M'!$W$66:$W$89,0)
A29: Erster Monat mit dauerhaft positiver Liquidität | B29: =IFERROR(INDEX('Plan-24M'!$A$8:$A$31,MATCH(1,'Plan-24M'!$AD$8:$AD$31,0)),"> 24 Monate") | C29: =IFERROR(INDEX('Plan-24M'!$A$37:$A$60,MATCH(1,'Plan-24M'!$AD$37:$AD$60,0)),"> 24 Monate") | D29: =IFERROR(INDEX('Plan-24M'!$A$66:$A$89,MATCH(1,'Plan-24M'!$AD$66:$AD$89,0)),"> 24 Monate")
A30: Kumuliertes Ergebnis nach Steuerrücklage, Monat 24 | B30: ='Plan-24M'!$U$31 | C30: ='Plan-24M'!$U$60 | D30: ='Plan-24M'!$U$89
A32: 3) Wann wird aus dem Einzelunternehmen eine UG?
A33: UG-Monat (erste 20 aktive Betriebe) | B33: =IF('Plan-24M'!$O$6=999,"> 24 Monate",'Plan-24M'!$O$6) | C33: =IF('Plan-24M'!$O$35=999,"> 24 Monate",'Plan-24M'!$O$35) | D33: =IF('Plan-24M'!$O$64=999,"> 24 Monate",'Plan-24M'!$O$64)
A34: … Kalendermonat | B34: =IF('Plan-24M'!$O$6=999,"> 24 Monate",EDATE('Plan-Annahmen'!$B$8,'Plan-24M'!$O$6-1)) | C34: =IF('Plan-24M'!$O$35=999,"> 24 Monate",EDATE('Plan-Annahmen'!$B$8,'Plan-24M'!$O$35-1)) | D34: =IF('Plan-24M'!$O$64=999,"> 24 Monate",EDATE('Plan-Annahmen'!$B$8,'Plan-24M'!$O$64-1))
A35: … Notartermin spätestens im Monat (4–6 Wochen Vorlauf) | B35: =IF('Plan-24M'!$O$6=999,"> 24 Monate",'Plan-24M'!$O$6-1) | C35: =IF('Plan-24M'!$O$35=999,"> 24 Monate",'Plan-24M'!$O$35-1) | D35: =IF('Plan-24M'!$O$64=999,"> 24 Monate",'Plan-24M'!$O$64-1)
A36: Zusätzliche Kosten ab diesem Monat (€/Monat) | B36: =IF('Plan-24M'!$O$6=999,0,'Plan-Kosten'!$F$71) | C36: =IF('Plan-24M'!$O$35=999,0,'Plan-Kosten'!$F$71) | D36: =IF('Plan-24M'!$O$64=999,0,'Plan-Kosten'!$F$71)
A37: Einmalig im UG-Monat (Notar, Eröffnungsbilanz) | B37: =IF('Plan-24M'!$O$6=999,0,'Plan-Kosten'!$F$72) | C37: =IF('Plan-24M'!$O$35=999,0,'Plan-Kosten'!$F$72) | D37: =IF('Plan-24M'!$O$64=999,0,'Plan-Kosten'!$F$72)
A38: Zusätzlich gebunden: Stammkapital | B38: =IF('Plan-24M'!$O$6=999,0,'Plan-Kosten'!$F$73) | C38: =IF('Plan-24M'!$O$35=999,0,'Plan-Kosten'!$F$73) | D38: =IF('Plan-24M'!$O$64=999,0,'Plan-Kosten'!$F$73)
A40: Ab dem UG-Monat gilt mein Vorbehalt zur Besteuerung wieder: Das Raster rechnet die Steuer wie beim Einzelunternehmen (Gewinn oben auf Sandys Gehalt). Für die Einzelunternehmens-Phase ist das korrekt; ab der UG kämen Körperschaft- und Gewerbesteuer auf Gesellschaftsebene und danach Gehalt oder Ausschüttung — eine Steuerberater-Rechnung. Im vorsichtigen Szenario wird die UG im Horizont gar nicht erreicht, dort ist der Vorbehalt gegenstandslos.
A42: 4) Ab wann kann Sandy reduzieren — und ganz aufhören?
A43: Der Ausstieg ist eine Treppe: In Stufe B1 läuft das Teilzeitgehalt weiter und die Krankenversicherung bleibt beim Arbeitgeber — Sofortangebot muss nur die Lücke zu 2.500 € netto schließen. Erst in B2 kommt alles zusammen.
A45: WICHTIG, und anders als erwartet: Die Ausstiegs-Treppe bewegt sich durch die Rechtsform-Entscheidung NICHT — die Zahlen der alten und der neuen Fassung sind identisch. Der Grund: Jede Ausstiegsstufe verlangt mindestens 37 zahlende Betriebe und liegt damit weit über dem UG-Auslöser von rund 20. An dem Punkt, an dem Sandy reduzieren könnte, gibt es die UG längst — also gelten dort auch wieder die vollen UG-Kosten. Die Ersparnis der Einzelunternehmens-Phase wirkt ausschließlich in der Anlaufzeit davor: früherer Break-even und ein deutlich flacherer Liquiditäts-Tiefpunkt (Abschnitte 1 und 2).
A47: Stufe | B47: Nötige Betriebe (neu) | C47: Nötiger Umsatz/Monat (neu) | D47: Nötige Betriebe (alt)
A48: Stufe B1 — 30 Std./Woche | B48: ='Plan-Phase B'!$C$22 | C48: ='Plan-Phase B'!$C$23 | D48: 37
A49: Stufe B1 — 25 Std./Woche | B49: ='Plan-Phase B'!$D$22 | C49: ='Plan-Phase B'!$D$23 | D49: 45
A50: Stufe B2 — Anstellung fällt weg | B50: ='Plan-Phase B'!$E$22 | C50: ='Plan-Phase B'!$E$23 | D50: 107
A52: Erreicht in Monat … | B52: Vorsichtig | C52: Realistisch | D52: Optimistisch
A53: Stufe B1 (30 Std.) — neue Fassung | B53: =IFERROR(INDEX('Plan-24M'!$A$8:$A$31,MATCH(1,'Plan-24M'!$AA$8:$AA$31,0)),"> 24 Monate") | C53: =IFERROR(INDEX('Plan-24M'!$A$37:$A$60,MATCH(1,'Plan-24M'!$AA$37:$AA$60,0)),"> 24 Monate") | D53: =IFERROR(INDEX('Plan-24M'!$A$66:$A$89,MATCH(1,'Plan-24M'!$AA$66:$AA$89,0)),"> 24 Monate")
A54: Stufe B1 (30 Std.) — alte Fassung (UG ab Monat 1) | B54: > 24 Monate | C54: 21 | D54: 14
A55: Stufe B1 (25 Std.) — neue Fassung | B55: =IFERROR(INDEX('Plan-24M'!$A$8:$A$31,MATCH(1,'Plan-24M'!$AB$8:$AB$31,0)),"> 24 Monate") | C55: =IFERROR(INDEX('Plan-24M'!$A$37:$A$60,MATCH(1,'Plan-24M'!$AB$37:$AB$60,0)),"> 24 Monate") | D55: =IFERROR(INDEX('Plan-24M'!$A$66:$A$89,MATCH(1,'Plan-24M'!$AB$66:$AB$89,0)),"> 24 Monate")
A56: Stufe B1 (25 Std.) — alte Fassung (UG ab Monat 1) | B56: > 24 Monate | C56: 24 | D56: 16
A57: Stufe B2 — neue Fassung | B57: =IFERROR(INDEX('Plan-24M'!$A$8:$A$31,MATCH(1,'Plan-24M'!$AC$8:$AC$31,0)),"> 24 Monate") | C57: =IFERROR(INDEX('Plan-24M'!$A$37:$A$60,MATCH(1,'Plan-24M'!$AC$37:$AC$60,0)),"> 24 Monate") | D57: =IFERROR(INDEX('Plan-24M'!$A$66:$A$89,MATCH(1,'Plan-24M'!$AC$66:$AC$89,0)),"> 24 Monate")
A58: Stufe B2 — alte Fassung (UG ab Monat 1) | B58: > 24 Monate | C58: > 24 Monate | D58: > 24 Monate
A59: Teilzeitantrag (30 Std.) spätestens im Monat — 3 Monate Vorlauf, § 8/§ 9a TzBfG | B59: =IFERROR(INDEX('Plan-24M'!$A$8:$A$31,MATCH(1,'Plan-24M'!$AA$8:$AA$31,0))-'Plan-Annahmen'!$B$93,"> 24 Monate") | C59: =IFERROR(INDEX('Plan-24M'!$A$37:$A$60,MATCH(1,'Plan-24M'!$AA$37:$AA$60,0))-'Plan-Annahmen'!$B$93,"> 24 Monate") | D59: =IFERROR(INDEX('Plan-24M'!$A$66:$A$89,MATCH(1,'Plan-24M'!$AA$66:$AA$89,0))-'Plan-Annahmen'!$B$93,"> 24 Monate")
A61: 5) Umsatzsteuer — Regelbesteuerung (Verzicht nach § 19 Abs. 2 UStG, entschieden 17.09.2026)
A62: Kalenderjahr (Umsatz netto) | B62: Vorsichtig | C62: Realistisch | D62: Optimistisch
A63: 2026 (Sep–Dez) | B63: =SUM('Plan-24M'!$H$8:$H$11) | C63: =SUM('Plan-24M'!$H$37:$H$40) | D63: =SUM('Plan-24M'!$H$66:$H$69)
A64: 2027 (Jan–Dez) | B64: =SUM('Plan-24M'!$H$12:$H$23) | C64: =SUM('Plan-24M'!$H$41:$H$52) | D64: =SUM('Plan-24M'!$H$70:$H$81)
A65: 2028 (Jan–Aug, angeschnitten) | B65: =SUM('Plan-24M'!$H$24:$H$31) | C65: =SUM('Plan-24M'!$H$53:$H$60) | D65: =SUM('Plan-24M'!$H$82:$H$89)
A66: Höchster Jahreswert über 25.000 €? | B66: =IF(MAX(SUM('Plan-24M'!$H$8:$H$11),SUM('Plan-24M'!$H$12:$H$23),SUM('Plan-24M'!$H$24:$H$31))>'Plan-Annahmen'!$B$63,"ja","nein") | C66: =IF(MAX(SUM('Plan-24M'!$H$37:$H$40),SUM('Plan-24M'!$H$41:$H$52),SUM('Plan-24M'!$H$53:$H$60))>'Plan-Annahmen'!$B$63,"ja","nein") | D66: =IF(MAX(SUM('Plan-24M'!$H$66:$H$69),SUM('Plan-24M'!$H$70:$H$81),SUM('Plan-24M'!$H$82:$H$89))>'Plan-Annahmen'!$B$63,"ja","nein")
A68: GEAENDERT 17.09.2026 (Head of Finance): Sandy hat sich fuer den freiwilligen Verzicht auf die Kleinunternehmerregelung entschieden (docs/preismodell.md). Der Schalter 'Regelbesteuerung' auf 'Plan-Annahmen' steht damit auf 1. Die Werte unten sind KEINE Entscheidungsgrundlage mehr, sondern Beobachtung: Der Verzicht bindet fuenf Jahre (bis 2031), die 25.000-€-Grenze ist bis dahin ohne Bedeutung. Erklaert wird der Verzicht erst im Fragebogen zur steuerlichen Erfassung nach der Gewerbeanmeldung in KW 41 — bis dahin ist nichts beim Finanzamt.
A70: 6) Der Engpass: Zeit, nicht Geld
A71: Benötigte Stunden im Monat 24 | B71: ='Plan-Kunden'!$P$31 | C71: ='Plan-Kunden'!$P$60 | D71: ='Plan-Kunden'!$P$89
A72: Monate über der Dauerlinie (65 Std.) von 24 | B72: ='Plan-Kunden'!$Q$32 | C72: ='Plan-Kunden'!$Q$61 | D72: ='Plan-Kunden'!$Q$90
A73: Monate über der Sprintlinie (86 Std.) von 24 | B73: ='Plan-Kunden'!$R$32 | C73: ='Plan-Kunden'!$R$61 | D73: ='Plan-Kunden'!$R$90
A74: Erster Monat über der Dauerlinie | B74: =IFERROR(INDEX('Plan-Kunden'!$A$8:$A$31,MATCH(1,'Plan-Kunden'!$Q$8:$Q$31,0)),"> 24 Monate") | C74: =IFERROR(INDEX('Plan-Kunden'!$A$37:$A$60,MATCH(1,'Plan-Kunden'!$Q$37:$Q$60,0)),"> 24 Monate") | D74: =IFERROR(INDEX('Plan-Kunden'!$A$66:$A$89,MATCH(1,'Plan-Kunden'!$Q$66:$Q$89,0)),"> 24 Monate")
A76: Die Kapazitätsgrenze kommt vor der Rentabilitätsgrenze: Solange Sandy Vollzeit angestellt ist, begrenzt nicht die Nachfrage das Wachstum, sondern ihre Zeit. Stufe B1 ist der Mechanismus, der diese Grenze anhebt (43 bzw. 65 Stunden mehr im Monat), bevor die Einnahmen sie tragen müssten. Die Rechnung hängt an zwei Annahmen von mir: 18 Minuten Support je Betrieb und Monat und 25 Stunden Grundlast — beide gelb auf 'Plan-Annahmen'.
A78: Offene Zahlen, die den Plan verschieben (alle gelb): Sandys echtes Bruttogehalt · Beitrag der IT-Haftpflicht · das Steuerberater-Honorar (800 €/Jahr gilt nur, wenn Sandy die Buchhaltung selbst macht — bei voller Abgabe eher 1.500 €) · die Abwanderungsrate · Support- und Grundlast-Stunden · Anthropic-Direktrechnung einmalig oder wiederkehrend · Empfehlungs-Anreiz ein/aus.
A80: Bewusst vorsichtig gerechnet: keine Verlustverrechnung mit dem Gehalt, frei werdende Gruenderplaetze werden nicht neu vergeben, Steuer sofort zurueckgelegt, September 2026 als Monat 1 voll gezaehlt. Die Vorsteuer ist seit dem 17.09.2026 eingerechnet — je Kostenzeile (Plan-Kosten, Spalte AL), nicht pauschal, und nur dort, wo der eingetragene Betrag nachweislich brutto ist. Versicherungen, Stripe, Amtsgebuehren und die Supabase-Reverse-Charge-Rechnungen bringen keine Vorsteuer; wo eine Betragsangabe netto gemeint ist, wird nichts abgezogen. Die Umsatzsteuer auf den Umsatz ist ein durchlaufender Posten und steht deshalb nicht im Raster — der Zeitversatz zwischen Vereinnahmen und Abfuehren (Liquiditaets-vorteil) ist ebenfalls nicht angesetzt. Was diese Vorsicht bei der Verlustverrechnung wert ist, steht seit dem 21.09.2026 beziffert in Abschnitt 7.
A82: 7) Was der Plan bewusst nicht einrechnet: die Verlustverrechnung mit dem Gehalt (ergänzt 21.09.2026)
A83: Reserve — im Plan NICHT enthalten | B83: Vorsichtig | C83: Realistisch | D83: Optimistisch
A84: Summe der negativen Monatsergebnisse (Monat 2–24, vor Steuer) | B84: =SUMIF('Plan-24M'!$R$9:$R$31,"<0") | C84: =SUMIF('Plan-24M'!$R$38:$R$60,"<0") | D84: =SUMIF('Plan-24M'!$R$67:$R$89,"<0")
A85: Grenzsteuersatz auf Sandys Gehalt (Plan-Annahmen, Zeile 82) | B85: ='Plan-Annahmen'!$B$82 | C85: ='Plan-Annahmen'!$B$82 | D85: ='Plan-Annahmen'!$B$82
A86: Steuererstattung daraus über 24 Monate — die Reserve | B86: =-B84*'Plan-Annahmen'!$B$82 | C86: =-C84*'Plan-Annahmen'!$B$82 | D86: =-D84*'Plan-Annahmen'!$B$82
A88: So ist die Zeile zu lesen: Der Plan legt auf positive Monatsergebnisse Steuer zurück (Spalte „Steuerrücklage" auf Plan-24M), schreibt für negative aber nichts gut. Tatsächlich mindert der Verlust aus dem Gewerbe das zu versteuernde Einkommen — auch das aus Sandys Gehalt, von dem die Lohnsteuer längst abgeführt ist (§ 2 Abs. 3 EStG). Der Betrag kommt als Einkommensteuer-Erstattung zurück, nicht monatlich, sondern nach der jeweiligen Steuererklärung — deshalb steht er hier und nicht in den Szenarien. Bemerkenswert ist die Richtung: Der Vorteil ist im VORSICHTIGEN Szenario am größten und wirkt damit genau dort, wo es eng wird — am Liquiditäts-Tiefpunkt. Monat 1 (September 2026) bleibt außen vor, weil die Belege bis einschließlich September bereits in der getrennt gerechneten Wirkung der Altbelege stecken (18 Belege, rund 150 €); zählte man ihn mit, wären es rund 80 € mehr je Szenario. Rechenweg und Quellen: docs/chief-of-staff-finance-todos.md, Eintrag vom 21.09.2026.

Sheet Plan-Annahmen
A1: Plan-Annahmen — Finanzplan CoS-F-003 (Fassung 2, 03.09.2026)
A2: Alle Eingaben des Plans an einer Stelle. Gelb = Annahme, bitte nur hier aendern. Jede Zeile nennt ihre Quelle. Horizont September 2026 bis August 2028. Rechtsform in dieser Fassung: Einzelunternehmen / Kleingewerbe, UMSATZSTEUERLICH AB 17.09.2026: Regelbesteuerung (Verzicht nach § 19 Abs. 2 UStG, Entscheidung Sandy, docs/preismodell.md) — Schalter Zeile 61 steht auf 1. UG erst ab rund 20 aktiven Betrieben.
A6: 1) Zeitrahmen
A7: Bezeichnung | B7: Wert | C7: Einheit | D7: Quelle / Kommentar
A8: Startmonat des Plans (Monat 1) | B8: 46266 | C8: Datum | D8: Horizont Sep 2026 – Aug 2028 (24 Monate), Auftrag CoS-F-003.
A9: Gate 1 — begleitete Testnutzer ab Monat | B9: 4 | C9: Monat-Nr. | D9: Nachtrag 6: Gate 1 Anfang Dezember 2026 = Monat 4. September bis November sind reine Kosten-Monate (Oktober Vorbereitung, 02.11.–03.12. Thailand, docs/kalender.md) — bewusst nicht mit Einnahmen geglättet.
A10: Öffentlicher Launch ab Monat | B10: 5 | C10: Monat-Nr. | D10: Nachtrag 6: Januar 2027 = Monat 5.
A12: 2) Preise und Stückkosten (vormals Blatt 'Marge & Tragfähigkeit')
A13: Bezeichnung | B13: Wert | C13: Einheit | D13: Quelle / Kommentar
A14: Gründerpreis | B14: 29 | C14: €/Monat | D14: docs/preismodell.md, entschieden 03.09.2026: dauerhaft für die ersten 25 zahlenden Betriebe, kein Hochlaufen auf 49 €.
A15: Standardpreis | B15: 49 | C15: €/Monat | D15: docs/preismodell.md, entschieden 03.09.2026.
A16: Gründerpreis-Plätze | B16: 25 | C16: Kunden | D16: docs/preismodell.md. Der Preisknick bei Kunde 26 ist im Kundenmodell explizit abgebildet, nicht mit einem Mischpreis geglättet (Nachtrag 3).
A17: KI-Kosten je Angebot (konservativ) | B17: 2.5 | C17: Cent | D17: Messung Head of Product Engineering (chief-of-staff-finance-todos.md, 'Rohdaten für CoS-F-002'): gemessen 2,2 Cent (Whisper $0,0060 + Chip-Vorschau $0,0002 + volle Extraktion $0,0172). Konservative Variante 2,5 Cent, weil die Aufnahmedauer nie gemessen wurde — ausdrückliche Vorgabe Chief of Staff, diesen Wert zu verwenden.
A18: Stripe-Gebühr variabel (EU-Karten) | B18: 0.015 | C18: % (Dezimal) | D18: kosten.org, Stripe-Gebührenrechner (Abruf 03.09.2026): 1,5 % + 0,25 € für europäische Karten. stripe.com/pricing lieferte beim ersten Abruf einen US-Wert (2,9 % + 30 ¢) — verworfen.
A19: Stripe-Gebühr fix je Zahlung | B19: 0.25 | C19: € | D19: Gleiche Quelle wie Zeile oben.
A20: USD/EUR-Kurs | B20: 0.86 | C20: EUR je USD | D20: exchange-rates.org: 01.09.2026 = 0,8626, 02.09.2026 = 0,8631, YTD-Ø 0,8603. Supabase, Vercel, OpenAI und Anthropic rechnen in US-Dollar — der Kurs steht deshalb sichtbar hier. Nachgeprüft 17.09.2026 (Head of Finance): Der amtliche BMF-Umsatzsteuer-Umrechnungskurs für August 2026 beträgt 1,1593 USD je EUR = 0,8626 EUR je USD und bestätigt diesen Planwert (Abweichung 0,3 %, rund 0,33 € im Monat). Bewusst zwei verschiedene Kurse mit zwei verschiedenen Aufgaben: hier ein Planungskurs für künftige Monate, im Blatt Rechnungsjournal der amtliche Monatskurs für die Buchung bereits vorliegender Belege (§ 16 Abs. 6 UStG). Bitte nicht angleichen.
A21: Angebote je Kunde und Monat | B21: 8 | C21: Angebote | D21: Stützpunkt CoS-P-008 (Platform). Liegt über dem typischen Kunden (5 Angebote) — für die Kostenseite konservativ.
A23: 3) Deckungsbeitrag je Kunde (Antwort auf CoS-F-002, hierher übernommen)
A24: Deckungsbeitrag = Preis − KI-Kosten (Angebote × Kosten je Angebot) − Stripe-Gebühr (Preis × variable Gebühr + fixe Gebühr). Der Vielnutzer-Fall mit 40 Angebten im Monat beantwortet die Frage, ob 'unbegrenzt Angebote' trägt.
A25: Angebote / Monat | B25: KI-Kosten gesamt | C25: Stripe-Gebühr | D25: Deckungsbeitrag @29€ | E25: Deckungsbeitrag @49€ | F25: Hinweis
A26: 3 | B26: =A26*$B$17/100 | C26: =$B$15*$B$18+$B$19 | D26: =$B$14-B26-($B$14*$B$18+$B$19) | E26: =$B$15-B26-C26 | F26: Leichtnutzer
A27: 5 | B27: =A27*$B$17/100 | C27: =$B$15*$B$18+$B$19 | D27: =$B$14-B27-($B$14*$B$18+$B$19) | E27: =$B$15-B27-C27 | F27: typischer Kunde
A28: 8 | B28: =A28*$B$17/100 | C28: =$B$15*$B$18+$B$19 | D28: =$B$14-B28-($B$14*$B$18+$B$19) | E28: =$B$15-B28-C28 | F28: Planannahme dieses Modells
A29: 40 | B29: =A29*$B$17/100 | C29: =$B$15*$B$18+$B$19 | D29: =$B$14-B29-($B$14*$B$18+$B$19) | E29: =$B$15-B29-C29 | F29: Vielnutzer-Fall — testet 'unbegrenzt Angebote'
A30: Ergebnis (CoS-F-002): Auch im Vielnutzer-Fall bleiben beide Deckungsbeiträge klar positiv — 40 Angebote kosten nur 1,00 € an KI. 'Unbegrenzt Angebote' ist bei diesen Preisen finanziell unkritisch. Der Plan rechnet durchgehend mit 8 Angeboten je Kunde und Monat.
A32: 4) Kundenmodell (Kanalplan CoS-M-007 + Mundpropaganda + Abwanderung)
A33: Bezeichnung | B33: Wert | C33: Einheit | D33: Quelle / Kommentar
A34: Neukunden je Kanal und Monat | B34: siehe Blatt 'Plan-Kunden' | C34: — | D34: Zulieferung Head of Marketing, docs/gtm-kanalplan.xlsx, Blatt 'Kanal x Monat' (CoS-M-007): sechs Kanäle, drei Szenarien, 24 Monate. Summen ohne Mundpropaganda und Abwanderung: 16,5 / 52,25 / 103,5 Betriebe. Werte blau auf 'Plan-Kunden' — die Bewertung des Vertriebs liegt bei Marketing, die Rechnung bei mir.
A35: Mundpropaganda: Empfehlungen pro Jahr je aktivem Betrieb — Vorsichtig | B35: 0.1 | C35: % pro Jahr | D35: gtm-kanalplan.xlsx, Blatt 'Mundpropaganda' (Parameter von Marketing, Anwendung auf die aktive Basis bei mir).
A36: Mundpropaganda: Empfehlungen pro Jahr je aktivem Betrieb — Realistisch | B36: 0.2 | C36: % pro Jahr | D36: gtm-kanalplan.xlsx, Blatt 'Mundpropaganda' (Parameter von Marketing, Anwendung auf die aktive Basis bei mir).
A37: Mundpropaganda: Empfehlungen pro Jahr je aktivem Betrieb — Optimistisch | B37: 0.35 | C37: % pro Jahr | D37: gtm-kanalplan.xlsx, Blatt 'Mundpropaganda' (Parameter von Marketing, Anwendung auf die aktive Basis bei mir).
A38: Mundpropaganda: davon zahlend — Vorsichtig | B38: 0.4 | C38: % | D38: gtm-kanalplan.xlsx, Blatt 'Mundpropaganda'.
A39: Mundpropaganda: davon zahlend — Realistisch | B39: 0.5 | C39: % | D39: gtm-kanalplan.xlsx, Blatt 'Mundpropaganda'.
A40: Mundpropaganda: davon zahlend — Optimistisch | B40: 0.6 | C40: % | D40: gtm-kanalplan.xlsx, Blatt 'Mundpropaganda'.
A41: Mundpropaganda: Verzögerung bis zur Empfehlung — Vorsichtig | B41: 4 | C41: Monate | D41: gtm-kanalplan.xlsx: ein Handwerker empfiehlt erst, wenn es sich bewährt hat. Rechenregel: aktive Betriebe (Monat − Verzögerung) × Jahresanteil ÷ 12 × Zahlend-Anteil.
A42: Mundpropaganda: Verzögerung bis zur Empfehlung — Realistisch | B42: 3 | C42: Monate | D42: gtm-kanalplan.xlsx: ein Handwerker empfiehlt erst, wenn es sich bewährt hat. Rechenregel: aktive Betriebe (Monat − Verzögerung) × Jahresanteil ÷ 12 × Zahlend-Anteil.
A43: Mundpropaganda: Verzögerung bis zur Empfehlung — Optimistisch | B43: 2 | C43: Monate | D43: gtm-kanalplan.xlsx: ein Handwerker empfiehlt erst, wenn es sich bewährt hat. Rechenregel: aktive Betriebe (Monat − Verzögerung) × Jahresanteil ÷ 12 × Zahlend-Anteil.
A44: Abwanderung Standardkunden pro Monat — Vorsichtig | B44: 0.05 | C44: % der Kunden | D44: MEINE Annahme (Abwanderung ist laut Nachtrag 3 Finance-Annahme). Marketing nennt 3–5 % im ersten Jahr als plausibel. Es gibt keinen Erfahrungswert — laut Chief of Staff bleibt diese Zelle gelb bis mindestens März 2027. Sie ist die wirksamste Stellschraube im Modell.
A45: Abwanderung Standardkunden pro Monat — Realistisch | B45: 0.04 | C45: % der Kunden | D45: MEINE Annahme (Abwanderung ist laut Nachtrag 3 Finance-Annahme). Marketing nennt 3–5 % im ersten Jahr als plausibel. Es gibt keinen Erfahrungswert — laut Chief of Staff bleibt diese Zelle gelb bis mindestens März 2027. Sie ist die wirksamste Stellschraube im Modell.
A46: Abwanderung Standardkunden pro Monat — Optimistisch | B46: 0.03 | C46: % der Kunden | D46: MEINE Annahme (Abwanderung ist laut Nachtrag 3 Finance-Annahme). Marketing nennt 3–5 % im ersten Jahr als plausibel. Es gibt keinen Erfahrungswert — laut Chief of Staff bleibt diese Zelle gelb bis mindestens März 2027. Sie ist die wirksamste Stellschraube im Modell.
... A53: Kulanz / Erstattungen | B53: 0.01 | C53: % vom Umsatz | D53: Katalog G, meine Annahme (1 %).
A55: 5) Rechtsform — Einzelunternehmen jetzt, UG ab rund 20 Betrieben
A56: GEÄNDERT gegenüber der ersten Fassung (Nachtrag 8 + 9): Dort war UG ab Monat 1 unterstellt. Sandy hat am Abend des 03.09.2026 anders entschieden — Einzelunternehmen / Kleingewerbe ab Oktober 2026, UG erst bei rund 20 aktiven zahlenden Betrieben. Quelle: entscheidungen-fuer-sandy.md 'S-4, Teil 4', eingeordnet von Head of Legal, freigegeben vom Chief of Staff. Der Auslöser hängt bewusst an der Kundenzahl, nicht an einem Datum — dann verschiebt er sich mit der Kundenkurve mit.
A57: Bezeichnung | B57: Wert | C57: Einheit | D57: Quelle / Kommentar
A58: Gewerbeanmeldung (Einzelunternehmen) ab Monat | B58: 2 | C58: Monat-Nr. | D58: Oktober 2026 = Monat 2 (Legal, S-4 Teil 4; Terminplan legal-007-plan-fuer-sandy.md). Ab hier laufen die Betriebsausgaben der Einzelunternehmung.
A59: UG-Gründung ab … aktiven zahlenden Betrieben | B59: 20 | C59: Betriebe | D59: Sandys Vorgabe (Nachtrag 9): 'nicht 5 Kunden sondern eher 20 oder so'. Der Schalter wirkt je Szenario auf dem Blatt 'Plan-Kunden' und löst im Raster Gründungskosten, den höheren Steuerberatersatz, IHK und das Geschäftskonto aus.
A60: Vorlauf für die UG-Gründung (Notartermin bis Eintragung) | B60: 1.25 | C60: Monate | D60: Legal: 4–6 Wochen ab Notartermin. Im Deckblatt als 'Notartermin spätestens' ausgewiesen; im Raster fallen die Kosten im Monat der Schwelle an.
A61: Regelbesteuerung statt Kleinunternehmer? (1 = ja, 0 = nein) | B61: 1 | C61: Schalter | D61: GESETZT AUF 1 am 17.09.2026 (Head of Finance): Sandy hat am 17.09.2026 Variante B gewaehlt — freiwilliger Verzicht auf die Kleinunternehmerregelung nach § 19 Abs. 2 UStG, Bindung fuenf Jahre (docs/preismodell.md). Scharf geschaltet wird der Verzicht erst im Fragebogen zur steuerlichen Erfassung nach der Gewerbeanmeldung in KW 41 — der Plan rechnet ihn aber ab jetzt. Bei 1 wird die Vorsteuer je Kostenzeile erstattet (Plan-Kosten, Spalte AL), die Preise sind netto und die Umsatzsteuer auf den Umsatz ist ein durchlaufender Posten.
A62: … vorsteuerfaehiger Kostenanteil (Naeherung) — NICHT MEHR VERWENDET | B62: 0 | C62: Anteil | D62: ERSETZT am 17.09.2026 (Head of Finance). Bis dahin: pauschal 60 % aller Kosten mit 19/119. Beim Gegenpruefen gegen die 18 echten Belege war die Pauschale in beide Richtungen falsch — Versicherungen, Stripe, Amtsgebuehren und die Supabase-Reverse-Charge-Rechnungen tragen gar keine abziehbare Vorsteuer, Fachliteratur nur 7 %, und einmalige Grossposten (Anwalt, Marke) haetten die Erstattung im Monat ihres Anfalls kuenstlich aufgeblaeht. Die Vorsteuer wird jetzt je Zeile gerechnet: Plan-Kosten, Spalte AL. Diese Zelle bleibt nur als Spur stehen.
A63: Kleinunternehmergrenze Vorjahresumsatz | B63: 25000 | C63: € netto | D63: § 19 UStG, mehrfach webverifiziert am 03.09.2026 (Taxfix, Tide, Finanzamt NRW), deckt sich mit der Angabe des Legal-Teams.
A64: Kleinunternehmergrenze laufendes Jahr | B64: 100000 | C64: € netto | D64: Gleiche Quelle.
A66: 6) Zeitbudget (Nachtrag 4 — harte Nebenbedingung)
A67: Bezeichnung | B67: Wert | C67: Einheit | D67: Quelle / Kommentar
A68: Kapazitätslinie 1 — Sprint (15–20 Std./Woche) | B68: 86 | C68: Std./Monat | D68: Nachtrag 4: Sandy hat 15–20 Std./Woche, seit rund zwei Monaten so gelebt. 20 × 4,33 ≈ 86 Std. im Monat für ALLES: Produkt, Support, Verwaltung, Vertrieb.
A69: Kapazitätslinie 2 — Dauerlinie konservativ (15 Std./Woche) | B69: 65 | C69: Std./Monat | D69: Konservative Linie für den Fall, dass sich das Tempo über 24 Monate neben einer Vollzeitstelle nicht halten lässt. Der Abstand zwischen beiden Linien ist selbst die Information.
A70: Grundlast Produkt / Verwaltung / Buchhaltung | B70: 25 | C70: Std./Monat | D70: MEINE Annahme. Laut Chief of Staff kann Sandy das aus zwei Monaten Erfahrung besser schätzen — bitte überschreiben. Zusammen mit der Abwanderung die wirksamste Stellschraube.
A71: Support je aktivem Betrieb und Monat | B71: 0.3 | C71: Std. | D71: MEINE Annahme (18 Minuten je Kunde und Monat). Support ist Sandys Zeit, nicht Geld.
A72: Onboarding je neuem Betrieb (einmalig) | B72: 1 | C72: Std. | D72: MEINE Annahme: Ersteinrichtung und Begleitung des ersten Angebots.
A73: Vertriebsstunden Sandy je Monat | B73: siehe Blatt 'Plan-Kunden' | C73: — | D73: Zulieferung Marketing: 4 / 18 / 5 / 15 / 16 … ≈ 19,5 Std. im Regelbetrieb, Summe 424 Std. über 24 Monate. Marketing führt die Stunden nur einmal, nicht je Szenario — sie gelten deshalb in allen drei Szenarien gleich (im optimistischen eher zu niedrig).
A75: 7) Phase A — Sofortangebot neben der Vollzeitstelle
A76: Bezeichnung | B76: Wert | C76: Einheit | D76: Quelle / Kommentar
A77: Bruttogehalt Anstellung, Vollzeit 40 Std. (Jahr) | B77: 48000 | C77: €/Jahr | D77: ANNAHME, bitte durch Sandys echtes Brutto ersetzen: aus 'mindestens 2.500 € netto' zurückgerechnet — rund 4.000 €/Monat brutto ergeben in Steuerklasse I ohne Kirchensteuer etwa 2.650 € netto. Bestimmt den Grenzsteuersatz, mit dem der Gewinn OBEN auf das Gehalt versteuert wird.
A78: Arbeitnehmeranteil Sozialversicherung (Näherung) | B78: 0.205 | C78: Anteil vom Brutto | D78: RV 9,3 % + KV 7,3 % + halber Zusatzbeitrag + Pflege + Arbeitslosenversicherung ≈ 20,5 % (Werte 2026).
A79: Werbungskosten-Pauschbetrag | B79: 1230 | C79: €/Jahr | D79: § 9a EStG.
A80: Abzugsfähige Vorsorgeaufwendungen (Anteil vom Brutto) | B80: 0.2 | C80: Anteil | D80: Näherung für das zu versteuernde Einkommen. Der Steuerberater rechnet das exakt.
A81: Zu versteuerndes Einkommen aus dem Gehalt (Näherung) | B81: =B77-B79-B77*B80-36 | C81: €/Jahr | D81: Brutto − Werbungskosten − Vorsorge − Sonderausgaben-Pauschbetrag.
A82: Grenzsteuersatz auf den Gewinn (Phase A) | B82: =(IF(INT(MAX(0,B81+1000))<=12348,0,IF(INT(MAX(0,B81+1000))<=17799,(914.51*((INT(MAX(0,B81+1000))-12348)/10000)+1400)*((INT(MAX(0,B81+1000))-12348)/10000),IF(INT(MAX(0,B81+1000))<=69878,(173.1*((INT(MAX(0,B81+1000))-17799)/10000)+2397)*((INT(MAX(0,B81+1000))-17799)/10000)+1034.87,IF(INT(MAX(0,B81+1000))<=277825,0.42*INT(MAX(0,B81+1000))-11135.63,0.45*INT(MAX(0,B81+1000))-19470.38))))-IF(INT(MAX(0,B81))<=12348,0,IF(INT(MAX(0,B81))<=17799,(914.51*((INT(MAX(0,B81))-12348)/10000)+1400)*((INT(MAX(0,B81))-12348)/10000),IF(INT(MAX(0,B81))<=69878,(173.1*((INT(MAX(0,B81))-17799)/10000)+2397)*((INT(MAX(0,B81))-17799)/10000)+1034.87,IF(INT(MAX(0,B81))<=277825,0.42*INT(MAX(0,B81))-11135.63,0.45*INT(MAX(0,B81))-19470.38)))))/1000 | C82: % (Dezimal) | D82: Einkommensteuertarif 2026 (§ 32a EStG, Fassung ab VZ 2026, lxgesetze.de/estg/32a: Grundfreibetrag 12.348 €, Zonen bis 17.799 / 69.878 / 277.825 €) auf zvE + 1.000 € minus Tarif auf zvE. In der Einzelunternehmens-Phase ist das die RICHTIGE Rechnung: der Gewinn sind gewerbliche Einkünfte, die oben auf das Gehalt kommen. Ohne Solidaritätszuschlag (Freigrenze nicht erreicht) und ohne Kirchensteuer. Verlustverrechnung mit dem Gehalt ist NICHT eingerechnet — vorsichtig gerechnet.
A84: 8) Phase B — der Ausstieg als Treppe (Nachtrag 5)
A85: Bezeichnung | B85: Wert | C85: Einheit | D85: Quelle / Kommentar
A86: Netto-Bedarf pro Monat (Untergrenze) | B86: 2500 | C86: €/Monat | D86: Sandy: 'mein aktuelles netto gehalt … brauch ich mindestens'. Laut Chief of Staff als Untergrenze zu behandeln, nicht als Ziel.
A87: Puffer auf den Netto-Bedarf (realistische Schwelle) | B87: 0.2 | C87: Anteil | D87: MEINE Annahme: +20 % für Urlaub, schwache Monate, Rücklage.
A88: Altersvorsorge pro Monat (realistische Schwelle) | B88: 300 | C88: €/Monat | D88: MEINE Annahme: als Selbstständige entfällt der Arbeitgeberanteil zur Rente.
A89: Teilzeit-Variante 1 | B89: 30 | C89: Std./Woche | D89: Nachtrag 5: Sandy erwägt 30 oder 25 Stunden.
A90: Teilzeit-Variante 2 | B90: 25 | C90: Std./Woche | D90: Nachtrag 5.
A91: Zusätzliche Zeit für Sofortangebot bei 30 Std. | B91: 43 | C91: Std./Monat | D91: Nachtrag 5: 40 → 30 sind rund 10 Std./Woche ≈ 43 Std./Monat. Das Zeitbudget ist damit stufenabhängig, keine Konstante.
A92: Zusätzliche Zeit für Sofortangebot bei 25 Std. | B92: 65 | C92: Std./Monat | D92: Nachtrag 5: 40 → 25 sind rund 15 Std./Woche ≈ 65 Std./Monat.
A93: Vorlauf für den Teilzeitantrag | B93: 3 | C93: Monate | D93: Nachtrag 5: mindestens drei Monate vorher schriftlich (§ 8 bzw. § 9a TzBfG). Rechtsstand vom Chief of Staff nachgesehen, keine Rechtsberatung — für den konkreten Vertrag prüfen lassen. Zwei Wege: § 8 unbefristete Teilzeit (kein Rückkehrrecht) und § 9a Brückenteilzeit (ab 45 Beschäftigten, 1–5 Jahre, danach automatische Rückkehr). Die Wahl ist Sandys Entscheidung.
A95: 9) Krankenversicherung und Pflege in Stufe B2 (Werte 2026)
A96: Bezeichnung | B96: Wert | C96: Einheit | D96: Quelle / Kommentar
A97: Krankenversicherung, allgemeiner Beitragssatz | B97: 0.146 | C97: % (Dezimal) | D97: GKV 2026, freiwillig versichert, voller Beitrag ohne Arbeitgeberanteil (papierkram.de). Ermäßigt ohne Krankengeld wären 14,0 % — hier der höhere Satz.
A98: … Zusatzbeitrag (Durchschnitt 2026) | B98: 0.029 | C98: % (Dezimal) | D98: 2,9 % Durchschnitt 2026 (papierkram.de), kassenabhängig.
A99: Pflegeversicherung inkl. Zuschlag für Kinderlose | B99: 0.042 | C99: % (Dezimal) | D99: 3,6 % + 0,6 % (papierkram.de). Bei Kindern niedriger.
A100: Mindestbemessungsgrundlage | B100: 1318.33 | C100: €/Monat | D100: 2026 (papierkram.de).
A101: Beitragsbemessungsgrenze | B101: 5812.5 | C101: €/Monat | D101: 2026: 5.812,50 €/Monat = 69.750 €/Jahr (papierkram.de, bundesregierung.de).
A102: Sonderausgaben-Pauschbetrag | B102: 36 | C102: €/Jahr | D102: § 10c EStG.
A104: In Stufe B1 bleibt die Krankenversicherung beim Arbeitgeber — der größte Einzelsprung fällt erst in Stufe B2 an. Genau deshalb ist B1 deutlich früher erreichbar.

Sheet Plan-Kunden
A1: Plan-Kunden — Kundenmodell aus Kanälen und Zeitbudget
A2: Neukunden kommen aus dem Kanalplan von Head of Marketing (blau = Zulieferung aus docs/gtm-kanalplan.xlsx, CoS-M-007), ergänzt um Mundpropaganda als einzigen Selbstverstärker aus der aktiven Kundenbasis — mit Verzögerung und dadurch von Natur aus gedeckelt. Abwanderung ist getrennt nach Gründer- und Standardkunden geführt. Rechts das Zeitbudget: Vertrieb + Support je Kunde + Onboarding je Neukunde + Grundlast gegen Sandys zwei Kapazitätslinien; eine 1 heißt, dieser Monat verlangt mehr Stunden, als sie hat. Die letzte Spalte schaltet die UG scharf, sobald die aktive Kundenzahl die Schwelle aus 'Plan-Annahmen' erreicht.
A6: Szenario: Vorsichtig | C6: Kanäle Σ 16.5 Betriebe (Marketing)
A7: Monat | B7: Kalendermonat | C7: Neukunden Kanäle | D7: Neukunden Mundpropaganda | E7: Neukunden gesamt | F7: davon Gründerplätze | G7: davon Standard | H7: Gründerplätze vergeben (kum.) | I7: Gründerkunden aktiv | J7: Standardkunden aktiv | K7: Kunden aktiv gesamt | L7: Std. Vertrieb (Marketing) | M7: Std. Support | N7: Std. Onboarding | O7: Std. Grundlast | P7: Std. gesamt | Q7: über Dauerlinie (65)? | R7: über Sprintlinie (86)? | S7: UG-Schwelle erreicht?
A8: 1 | B8: =EDATE('Plan-Annahmen'!$B$8,A8-1) | C8: 0 | D8: =IF(A8-'Plan-Annahmen'!$B$41<1,0,INDEX($K$8:$K$31,A8-'Plan-Annahmen'!$B$41)*'Plan-Annahmen'!$B$35/12*'Plan-Annahmen'!$B$38*(1+'Plan-Annahmen'!$B$50*'Plan-Annahmen'!$B$51)) | E8: =C8+D8 | F8: =MIN(E8,MAX(0,'Plan-Annahmen'!$B$16-0)) | G8: =E8-F8 | H8: =0+F8 | I8: =0*(1-'Plan-Annahmen'!$B$47)+F8 | J8: =0*(1-'Plan-Annahmen'!$B$44)+G8 | K8: =I8+J8 | L8: 4 | M8: =K8*'Plan-Annahmen'!$B$71 | N8: =E8*'Plan-Annahmen'!$B$72 | O8: ='Plan-Annahmen'!$B$70 | P8: =L8+M8+N8+O8 | Q8: =IF(P8>'Plan-Annahmen'!$B$69,1,0) | R8: =IF(P8>'Plan-Annahmen'!$B$68,1,0) | S8: =IF(K8>='Plan-Annahmen'!$B$59,1,0)
A9: 2 | B9: =EDATE('Plan-Annahmen'!$B$8,A9-1) | C9: 0 | D9: =IF(A9-'Plan-Annahmen'!$B$41<1,0,INDEX($K$8:$K$31,A9-'Plan-Annahmen'!$B$41)*'Plan-Annahmen'!$B$35/12*'Plan-Annahmen'!$B$38*(1+'Plan-Annahmen'!$B$50*'Plan-Annahmen'!$B$51)) | E9: =C9+D9 | F9: =MIN(E9,MAX(0,'Plan-Annahmen'!$B$16-H8)) | G9: =E9-F9 | H9: =H8+F9 | I9: =I8*(1-'Plan-Annahmen'!$B$47)+F9 | J9: =J8*(1-'Plan-Annahmen'!$B$44)+G9 | K9: =I9+J9 | L9: 18 | M9: =K9*'Plan-Annahmen'!$B$71 | N9: =E9*'Plan-Annahmen'!$B$72 | O9: ='Plan-Annahmen'!$B$70 | P9: =L9+M9+N9+O9 | Q9: =IF(P9>'Plan-Annahmen'!$B$69,1,0) | R9: =IF(P9>'Plan-Annahmen'!$B$68,1,0) | S9: =IF(K9>='Plan-Annahmen'!$B$59,1,0)
A10: 3 | B10: =EDATE('Plan-Annahmen'!$B$8,A10-1) | C10: 0 | D10: =IF(A10-'Plan-Annahmen'!$B$41<1,0,INDEX($K$8:$K$31,A10-'Plan-Annahmen'!$B$41)*'Plan-Annahmen'!$B$35/12*'Plan-Annahmen'!$B$38*(1+'Plan-Annahmen'!$B$50*'Plan-Annahmen'!$B$51)) | E10: =C10+D10 | F10: =MIN(E10,MAX(0,'Plan-Annahmen'!$B$16-H9)) | G10: =E10-F10 | H10: =H9+F10 | I10: =I9*(1-'Plan-Annahmen'!$B$47)+F10 | J10: =J9*(1-'Plan-Annahmen'!$B$44)+G10 | K10: =I10+J10 | L10: 5 | M10: =K10*'Plan-Annahmen'!$B$71 | N10: =E10*'Plan-Annahmen'!$B$72 | O10: ='Plan-Annahmen'!$B$70 | P10: =L10+M10+N10+O10 | Q10: =IF(P10>'Plan-Annahmen'!$B$69,1,0) | R10: =IF(P10>'Plan-Annahmen'!$B$68,1,0) | S10: =IF(K10>='Plan-Annahmen'!$B$59,1,0)
A11: 4 | B11: =EDATE('Plan-Annahmen'!$B$8,A11-1) | C11: 0 | D11: =IF(A11-'Plan-Annahmen'!$B$41<1,0,INDEX($K$8:$K$31,A11-'Plan-Annahmen'!$B$41)*'Plan-Annahmen'!$B$35/12*'Plan-Annahmen'!$B$38*(1+'Plan-Annahmen'!$B$50*'Plan-Annahmen'!$B$51)) | E11: =C11+D11 | F11: =MIN(E11,MAX(0,'Plan-Annahmen'!$B$16-H10)) | G11: =E11-F11 | H11: =H10+F11 | I11: =I10*(1-'Plan-Annahmen'!$B$47)+F11 | J11: =J10*(1-'Plan-Annahmen'!$B$44)+G11 | K11: =I11+J11 | L11: 15 | M11: =K11*'Plan-Annahmen'!$B$71 | N11: =E11*'Plan-Annahmen'!$B$72 | O11: ='Plan-Annahmen'!$B$70 | P11: =L11+M11+N11+O11 | Q11: =IF(P11>'Plan-Annahmen'!$B$69,1,0) | R11: =IF(P11>'Plan-Annahmen'!$B$68,1,0) | S11: =IF(K11>='Plan-Annahmen'!$B$59,1,0)
A12: 5 | B12: =EDATE('Plan-Annahmen'!$B$8,A12-1) | C12: 1 | D12: =IF(A12-'Plan-Annahmen'!$B$41<1,0,INDEX($K$8:$K$31,A12-'Plan-Annahmen'!$B$41)*'Plan-Annahmen'!$B$35/12*'Plan-Annahmen'!$B$38*(1+'Plan-Annahmen'!$B$50*'Plan-Annahmen'!$B$51)) | E12: =C12+D12 | F12: =MIN(E12,MAX(0,'Plan-Annahmen'!$B$16-H11)) | G12: =E12-F12 | H12: =H11+F12 | I12: =I11*(1-'Plan-Annahmen'!$B$47)+F12 | J12: =J11*(1-'Plan-Annahmen'!$B$44)+G12 | K12: =I12+J12 | L12: 16 | M12: =K12*'Plan-Annahmen'!$B$71 | N12: =E12*'Plan-Annahmen'!$B$72 | O12: ='Plan-Annahmen'!$B$70 | P12: =L12+M12+N12+O12 | Q12: =IF(P12>'Plan-Annahmen'!$B$69,1,0) | R12: =IF(P12>'Plan-Annahmen'!$B$68,1,0) | S12: =IF(K12>='Plan-Annahmen'!$B$59,1,0)
A13: 6 | B13: =EDATE('Plan-Annahmen'!$B$8,A13-1) | C13: 1 | D13: =IF(A13-'Plan-Annahmen'!$B$41<1,0,INDEX($K$8:$K$31,A13-'Plan-Annahmen'!$B$41)*'Plan-Annahmen'!$B$35/12*'Plan-Annahmen'!$B$38*(1+'Plan-Annahmen'!$B$50*'Plan-Annahmen'!$B$51)) | E13: =C13+D13 | F13: =MIN(E13,MAX(0,'Plan-Annahmen'!$B$16-H12)) | G13: =E13-F13 | H13: =H12+F13 | I13: =I12*(1-'Plan-Annahmen'!$B$47)+F13 | J13: =J12*(1-'Plan-Annahmen'!$B$44)+G13 | K13: =I13+J13 | L13: 16 | M13: =K13*'Plan-Annahmen'!$B$71 | N13: =E13*'Plan-Annahmen'!$B$72 | O13: ='Plan-Annahmen'!$B$70 | P13: =L13+M13+N13+O13 | Q13: =IF(P13>'Plan-Annahmen'!$B$69,1,0) | R13: =IF(P13>'Plan-Annahmen'!$B$68,1,0) | S13: =IF(K13>='Plan-Annahmen'!$B$59,1,0)
A14: 7 | B14: =EDATE('Plan-Annahmen'!$B$8,A14-1) | C14: 1.25 | D14: =IF(A14-'Plan-Annahmen'!$B$41<1,0,INDEX($K$8:$K$31,A14-'Plan-Annahmen'!$B$41)*'Plan-Annahmen'!$B$35/12*'Plan-Annahmen'!$B$38*(1+'Plan-Annahmen'!$B$50*'Plan-Annahmen'!$B$51)) | E14: =C14+D14 | F14: =MIN(E14,MAX(0,'Plan-Annahmen'!$B$16-H13)) | G14: =E14-F14 | H14: =H13+F14 | I14: =I13*(1-'Plan-Annahmen'!$B$47)+F14 | J14: =J13*(1-'Plan-Annahmen'!$B$44)+G14 | K14: =I14+J14 | L14: 16.5 | M14: =K14*'Plan-Annahmen'!$B$71 | N14: =E14*'Plan-Annahmen'!$B$72 | O14: ='Plan-Annahmen'!$B$70 | P14: =L14+M14+N14+O14 | Q14: =IF(P14>'Plan-Annahmen'!$B$69,1,0) | R14: =IF(P14>'Plan-Annahmen'!$B$68,1,0) | S14: =IF(K14>='Plan-Annahmen'!$B$59,1,0)
A15: 8 | B15: =EDATE('Plan-Annahmen'!$B$8,A15-1) | C15: 0.25 | D15: =IF(A15-'Plan-Annahmen'!$B$41<1,0,INDEX($K$8:$K$31,A15-'Plan-Annahmen'!$B$41)*'Plan-Annahmen'!$B$35/12*'Plan-Annahmen'!$B$38*(1+'Plan-Annahmen'!$B$50*'Plan-Annahmen'!$B$51)) | E15: =C15+D15 | F15: =MIN(E15,MAX(0,'Plan-Annahmen'!$B$16-H14)) | G15: =E15-F15 | H15: =H14+F15 | I15: =I14*(1-'Plan-Annahmen'!$B$47)+F15 | J15: =J14*(1-'Plan-Annahmen'!$B$44)+G15 | K15: =I15+J15 | L15: 20.5 | M15: =K15*'Plan-Annahmen'!$B$71 | N15: =E15*'Plan-Annahmen'!$B$72 | O15: ='Plan-Annahmen'!$B$70 | P15: =L15+M15+N15+O15 | Q15: =IF(P15>'Plan-Annahmen'!$B$69,1,0) | R15: =IF(P15>'Plan-Annahmen'!$B$68,1,0) | S15: =IF(K15>='Plan-Annahmen'!$B$59,1,0)
A16: 9 | B16: =EDATE('Plan-Annahmen'!$B$8,A16-1) | C16: 0.25 | D16: =IF(A16-'Plan-Annahmen'!$B$41<1,0,INDEX($K$8:$K$31,A16-'Plan-Annahmen'!$B$41)*'Plan-Annahmen'!$B$35/12*'Plan-Annahmen'!$B$38*(1+'Plan-Annahmen'!$B$50*'Plan-Annahmen'!$B$51)) | E16: =C16+D16 | F16: =MIN(E16,MAX(0,'Plan-Annahmen'!$B$16-H15)) | G16: =E16-F16 | H16: =H15+F16 | I16: =I15*(1-'Plan-Annahmen'!$B$47)+F16 | J16: =J15*(1-'Plan-Annahmen'!$B$44)+G16 | K16: =I16+J16 | L16: 20.5 | M16: =K16*'Plan-Annahmen'!$B$71 | N16: =E16*'Plan-Annahmen'!$B$72 | O16: ='Plan-Annahmen'!$B$70 | P16: =L16+M16+N16+O16 | Q16: =IF(P16>'Plan-Annahmen'!$B$69,1,0) | R16: =IF(P16>'Plan-Annahmen'!$B$68,1,0) | S16: =IF(K16>='Plan-Annahmen'!$B$59,1,0)
A17: 10 | B17: =EDATE('Plan-Annahmen'!$B$8,A17-1) | C17: 0.75 | D17: =IF(A17-'Plan-Annahmen'!$B$41<1,0,INDEX($K$8:$K$31,A17-'Plan-Annahmen'!$B$41)*'Plan-Annahmen'!$B$35/12*'Plan-Annahmen'!$B$38*(1+'Plan-Annahmen'!$B$50*'Plan-Annahmen'!$B$51)) | E17: =C17+D17 | F17: =MIN(E17,MAX(0,'Plan-Annahmen'!$B$16-H16)) | G17: =E17-F17 | H17: =H16+F17 | I17: =I16*(1-'Plan-Annahmen'!$B$47)+F17 | J17: =J16*(1-'Plan-Annahmen'!$B$44)+G17 | K17: =I17+J17 | L17: 19.5 | M17: =K17*'Plan-Annahmen'!$B$71 | N17: =E17*'Plan-Annahmen'!$B$72 | O17: ='Plan-Annahmen'!$B$70 | P17: =L17+M17+N17+O17 | Q17: =IF(P17>'Plan-Annahmen'!$B$69,1,0) | R17: =IF(P17>'Plan-Annahmen'!$B$68,1,0) | S17: =IF(K17>='Plan-Annahmen'!$B$59,1,0)
A18: 11 | B18: =EDATE('Plan-Annahmen'!$B$8,A18-1) | C18: 0.25 | D18: =IF(A18-'Plan-Annahmen'!$B$41<1,0,INDEX($K$8:$K$31,A18-'Plan-Annahmen'!$B$41)*'Plan-Annahmen'!$B$35/12*'Plan-Annahmen'!$B$38*(1+'Plan-Annahmen'!$B$50*'Plan-Annahmen'!$B$51)) | E18: =C18+D18 | F18: =MIN(E18,MAX(0,'Plan-Annahmen'!$B$16-H17)) | G18: =E18-F18 | H18: =H17+F18 | I18: =I17*(1-'Plan-Annahmen'!$B$47)+F18 | J18: =J17*(1-'Plan-Annahmen'!$B$44)+G18 | K18: =I18+J18 | L18: 19.5 | M18: =K18*'Plan-Annahmen'!$B$71 | N18: =E18*'Plan-Annahmen'!$B$72 | O18: ='Plan-Annahmen'!$B$70 | P18: =L18+M18+N18+O18 | Q18: =IF(P18>'Plan-Annahmen'!$B$69,1,0) | R18: =IF(P18>'Plan-Annahmen'!$B$68,1,0) | S18: =IF(K18>='Plan-Annahmen'!$B$59,1,0)
A19: 12 | B19: =EDATE('Plan-Annahmen'!$B$8,A19-1) | C19: 0.25 | D19: =IF(A19-'Plan-Annahmen'!$B$41<1,0,INDEX($K$8:$K$31,A19-'Plan-Annahmen'!$B$41)*'Plan-Annahmen'!$B$35/12*'Plan-Annahmen'!$B$38*(1+'Plan-Annahmen'!$B$50*'Plan-Annahmen'!$B$51)) | E19: =C19+D19 | F19: =MIN(E19,MAX(0,'Plan-Annahmen'!$B$16-H18)) | G19: =E19-F19 | H19: =H18+F19 | I19: =I18*(1-'Plan-Annahmen'!$B$47)+F19 | J19: =J18*(1-'Plan-Annahmen'!$B$44)+G19 | K19: =I19+J19 | L19: 19.5 | M19: =K19*'Plan-Annahmen'!$B$71 | N19: =E19*'Plan-Annahmen'!$B$72 | O19: ='Plan-Annahmen'!$B$70 | P19: =L19+M19+N19+O19 | Q19: =IF(P19>'Plan-Annahmen'!$B$69,1,0) | R19: =IF(P19>'Plan-Annahmen'!$B$68,1,0) | S19: =IF(K19>='Plan-Annahmen'!$B$59,1,0)
A20: 13 | B20: =EDATE('Plan-Annahmen'!$B$8,A20-1) | C20: 0.75 | D20: =IF(A20-'Plan-Annahmen'!$B$41<1,0,INDEX($K$8:$K$31,A20-'Plan-Annahmen'!$B$41)*'Plan-Annahmen'!$B$35/12*'Plan-Annahmen'!$B$38*(1+'Plan-Annahmen'!$B$50*'Plan-Annahmen'!$B$51)) | E20: =C20+D20 | F20: =MIN(E20,MAX(0,'Plan-Annahmen'!$B$16-H19)) | G20: =E20-F20 | H20: =H19+F20 | I20: =I19*(1-'Plan-Annahmen'!$B$47)+F20 | J20: =J19*(1-'Plan-Annahmen'!$B$44)+G20 | K20: =I20+J20 | L20: 19.5 | M20: =K20*'Plan-Annahmen'!$B$71 | N20: =E20*'Plan-Annahmen'!$B$72 | O20: ='Plan-Annahmen'!$B$70 | P20: =L20+M20+N20+O20 | Q20: =IF(P20>'Plan-Annahmen'!$B$69,1,0) | R20: =IF(P20>'Plan-Annahmen'!$B$68,1,0) | S20: =IF(K20>='Plan-Annahmen'!$B$59,1,0)
... A31: 24 | B31: =EDATE('Plan-Annahmen'!$B$8,A31-1) | C31: 1 | D31: =IF(A31-'Plan-Annahmen'!$B$41<1,0,INDEX($K$8:$K$31,A31-'Plan-Annahmen'!$B$41)*'Plan-Annahmen'!$B$35/12*'Plan-Annahmen'!$B$38*(1+'Plan-Annahmen'!$B$50*'Plan-Annahmen'!$B$51)) | E31: =C31+D31 | F31: =MIN(E31,MAX(0,'Plan-Annahmen'!$B$16-H30)) | G31: =E31-F31 | H31: =H30+F31 | I31: =I30*(1-'Plan-Annahmen'!$B$47)+F31 | J31: =J30*(1-'Plan-Annahmen'!$B$44)+G31 | K31: =I31+J31 | L31: 19.5 | M31: =K31*'Plan-Annahmen'!$B$71 | N31: =E31*'Plan-Annahmen'!$B$72 | O31: ='Plan-Annahmen'!$B$70 | P31: =L31+M31+N31+O31 | Q31: =IF(P31>'Plan-Annahmen'!$B$69,1,0) | R31: =IF(P31>'Plan-Annahmen'!$B$68,1,0) | S31: =IF(K31>='Plan-Annahmen'!$B$59,1,0)
A32: Σ / Ende | C32: =SUM(C8:C31) | D32: =SUM(D8:D31) | E32: =SUM(E8:E31) | K32: =K31 | Q32: =SUM(Q8:Q31) | R32: =SUM(R8:R31) | S32: =IFERROR(INDEX($A$8:$A$31,MATCH(1,$S$8:$S$31,0)),999)
A35: Szenario: Realistisch | C35: Kanäle Σ 52.25 Betriebe (Marketing)
A36: Monat | B36: Kalendermonat | C36: Neukunden Kanäle | D36: Neukunden Mundpropaganda | E36: Neukunden gesamt | F36: davon Gründerplätze | G36: davon Standard | H36: Gründerplätze vergeben (kum.) | I36: Gründerkunden aktiv | J36: Standardkunden aktiv | K36: Kunden aktiv gesamt | L36: Std. Vertrieb (Marketing) | M36: Std. Support | N36: Std. Onboarding | O36: Std. Grundlast | P36: Std. gesamt | Q36: über Dauerlinie (65)? | R36: über Sprintlinie (86)? | S36: UG-Schwelle erreicht?
A37: 1 | B37: =EDATE('Plan-Annahmen'!$B$8,A37-1) | C37: 0 | D37: =IF(A37-'Plan-Annahmen'!$B$42<1,0,INDEX($K$37:$K$60,A37-'Plan-Annahmen'!$B$42)*'Plan-Annahmen'!$B$36/12*'Plan-Annahmen'!$B$39*(1+'Plan-Annahmen'!$B$50*'Plan-Annahmen'!$B$51)) | E37: =C37+D37 | F37: =MIN(E37,MAX(0,'Plan-Annahmen'!$B$16-0)) | G37: =E37-F37 | H37: =0+F37 | I37: =0*(1-'Plan-Annahmen'!$B$48)+F37 | J37: =0*(1-'Plan-Annahmen'!$B$45)+G37 | K37: =I37+J37 | L37: 4 | M37: =K37*'Plan-Annahmen'!$B$71 | N37: =E37*'Plan-Annahmen'!$B$72 | O37: ='Plan-Annahmen'!$B$70 | P37: =L37+M37+N37+O37 | Q37: =IF(P37>'Plan-Annahmen'!$B$69,1,0) | R37: =IF(P37>'Plan-Annahmen'!$B$68,1,0) | S37: =IF(K37>='Plan-Annahmen'!$B$59,1,0)
A38: 2 | B38: =EDATE('Plan-Annahmen'!$B$8,A38-1) | C38: 0 | D38: =IF(A38-'Plan-Annahmen'!$B$42<1,0,INDEX($K$37:$K$60,A38-'Plan-Annahmen'!$B$42)*'Plan-Annahmen'!$B$36/12*'Plan-Annahmen'!$B$39*(1+'Plan-Annahmen'!$B$50*'Plan-Annahmen'!$B$51)) | E38: =C38+D38 | F38: =MIN(E38,MAX(0,'Plan-Annahmen'!$B$16-H37)) | G38: =E38-F38 | H38: =H37+F38 | I38: =I37*(1-'Plan-Annahmen'!$B$48)+F38 | J38: =J37*(1-'Plan-Annahmen'!$B$45)+G38 | K38: =I38+J38 | L38: 18 | M38: =K38*'Plan-Annahmen'!$B$71 | N38: =E38*'Plan-Annahmen'!$B$72 | O38: ='Plan-Annahmen'!$B$70 | P38: =L38+M38+N38+O38 | Q38: =IF(P38>'Plan-Annahmen'!$B$69,1,0) | R38: =IF(P38>'Plan-Annahmen'!$B$68,1,0) | S38: =IF(K38>='Plan-Annahmen'!$B$59,1,0)
A39: 3 | B39: =EDATE('Plan-Annahmen'!$B$8,A39-1) | C39: 0 | D39: =IF(A39-'Plan-Annahmen'!$B$42<1,0,INDEX($K$37:$K$60,A39-'Plan-Annahmen'!$B$42)*'Plan-Annahmen'!$B$36/12*'Plan-Annahmen'!$B$39*(1+'Plan-Annahmen'!$B$50*'Plan-Annahmen'!$B$51)) | E39: =C39+D39 | F39: =MIN(E39,MAX(0,'Plan-Annahmen'!$B$16-H38)) | G39: =E39-F39 | H39: =H38+F39 | I39: =I38*(1-'Plan-Annahmen'!$B$48)+F39 | J39: =J38*(1-'Plan-Annahmen'!$B$45)+G39 | K39: =I39+J39 | L39: 5 | M39: =K39*'Plan-Annahmen'!$B$71 | N39: =E39*'Plan-Annahmen'!$B$72 | O39: ='Plan-Annahmen'!$B$70 | P39: =L39+M39+N39+O39 | Q39: =IF(P39>'Plan-Annahmen'!$B$69,1,0) | R39: =IF(P39>'Plan-Annahmen'!$B$68,1,0) | S39: =IF(K39>='Plan-Annahmen'!$B$59,1,0)
A40: 4 | B40: =EDATE('Plan-Annahmen'!$B$8,A40-1) | C40: 1 | D40: =IF(A40-'Plan-Annahmen'!$B$42<1,0,INDEX($K$37:$K$60,A40-'Plan-Annahmen'!$B$42)*'Plan-Annahmen'!$B$36/12*'Plan-Annahmen'!$B$39*(1+'Plan-Annahmen'!$B$50*'Plan-Annahmen'!$B$51)) | E40: =C40+D40 | F40: =MIN(E40,MAX(0,'Plan-Annahmen'!$B$16-H39)) | G40: =E40-F40 | H40: =H39+F40 | I40: =I39*(1-'Plan-Annahmen'!$B$48)+F40 | J40: =J39*(1-'Plan-Annahmen'!$B$45)+G40 | K40: =I40+J40 | L40: 15 | M40: =K40*'Plan-Annahmen'!$B$71 | N40: =E40*'Plan-Annahmen'!$B$72 | O40: ='Plan-Annahmen'!$B$70 | P40: =L40+M40+N40+O40 | Q40: =IF(P40>'Plan-Annahmen'!$B$69,1,0) | R40: =IF(P40>'Plan-Annahmen'!$B$68,1,0) | S40: =IF(K40>='Plan-Annahmen'!$B$59,1,0)
A41: 5 | B41: =EDATE('Plan-Annahmen'!$B$8,A41-1) | C41: 1.5 | D41: =IF(A41-'Plan-Annahmen'!$B$42<1,0,INDEX($K$37:$K$60,A41-'Plan-Annahmen'!$B$42)*'Plan-Annahmen'!$B$36/12*'Plan-Annahmen'!$B$39*(1+'Plan-Annahmen'!$B$50*'Plan-Annahmen'!$B$51)) | E41: =C41+D41 | F41: =MIN(E41,MAX(0,'Plan-Annahmen'!$B$16-H40)) | G41: =E41-F41 | H41: =H40+F41 | I41: =I40*(1-'Plan-Annahmen'!$B$48)+F41 | J41: =J40*(1-'Plan-Annahmen'!$B$45)+G41 | K41: =I41+J41 | L41: 16 | M41: =K41*'Plan-Annahmen'!$B$71 | N41: =E41*'Plan-Annahmen'!$B$72 | O41: ='Plan-Annahmen'!$B$70 | P41: =L41+M41+N41+O41 | Q41: =IF(P41>'Plan-Annahmen'!$B$69,1,0) | R41: =IF(P41>'Plan-Annahmen'!$B$68,1,0) | S41: =IF(K41>='Plan-Annahmen'!$B$59,1,0)
A42: 6 | B42: =EDATE('Plan-Annahmen'!$B$8,A42-1) | C42: 2.5 | D42: =IF(A42-'Plan-Annahmen'!$B$42<1,0,INDEX($K$37:$K$60,A42-'Plan-Annahmen'!$B$42)*'Plan-Annahmen'!$B$36/12*'Plan-Annahmen'!$B$39*(1+'Plan-Annahmen'!$B$50*'Plan-Annahmen'!$B$51)) | E42: =C42+D42 | F42: =MIN(E42,MAX(0,'Plan-Annahmen'!$B$16-H41)) | G42: =E42-F42 | H42: =H41+F42 | I42: =I41*(1-'Plan-Annahmen'!$B$48)+F42 | J42: =J41*(1-'Plan-Annahmen'!$B$45)+G42 | K42: =I42+J42 | L42: 16 | M42: =K42*'Plan-Annahmen'!$B$71 | N42: =E42*'Plan-Annahmen'!$B$72 | O42: ='Plan-Annahmen'!$B$70 | P42: =L42+M42+N42+O42 | Q42: =IF(P42>'Plan-Annahmen'!$B$69,1,0) | R42: =IF(P42>'Plan-Annahmen'!$B$68,1,0) | S42: =IF(K42>='Plan-Annahmen'!$B$59,1,0)
A43: 7 | B43: =EDATE('Plan-Annahmen'!$B$8,A43-1) | C43: 2 | D43: =IF(A43-'Plan-Annahmen'!$B$42<1,0,INDEX($K$37:$K$60,A43-'Plan-Annahmen'!$B$42)*'Plan-Annahmen'!$B$36/12*'Plan-Annahmen'!$B$39*(1+'Plan-Annahmen'!$B$50*'Plan-Annahmen'!$B$51)) | E43: =C43+D43 | F43: =MIN(E43,MAX(0,'Plan-Annahmen'!$B$16-H42)) | G43: =E43-F43 | H43: =H42+F43 | I43: =I42*(1-'Plan-Annahmen'!$B$48)+F43 | J43: =J42*(1-'Plan-Annahmen'!$B$45)+G43 | K43: =I43+J43 | L43: 16.5 | M43: =K43*'Plan-Annahmen'!$B$71 | N43: =E43*'Plan-Annahmen'!$B$72 | O43: ='Plan-Annahmen'!$B$70 | P43: =L43+M43+N43+O43 | Q43: =IF(P43>'Plan-Annahmen'!$B$69,1,0) | R43: =IF(P43>'Plan-Annahmen'!$B$68,1,0) | S43: =IF(K43>='Plan-Annahmen'!$B$59,1,0)
A44: 8 | B44: =EDATE('Plan-Annahmen'!$B$8,A44-1) | C44: 2 | D44: =IF(A44-'Plan-Annahmen'!$B$42<1,0,INDEX($K$37:$K$60,A44-'Plan-Annahmen'!$B$42)*'Plan-Annahmen'!$B$36/12*'Plan-Annahmen'!$B$39*(1+'Plan-Annahmen'!$B$50*'Plan-Annahmen'!$B$51)) | E44: =C44+D44 | F44: =MIN(E44,MAX(0,'Plan-Annahmen'!$B$16-H43)) | G44: =E44-F44 | H44: =H43+F44 | I44: =I43*(1-'Plan-Annahmen'!$B$48)+F44 | J44: =J43*(1-'Plan-Annahmen'!$B$45)+G44 | K44: =I44+J44 | L44: 20.5 | M44: =K44*'Plan-Annahmen'!$B$71 | N44: =E44*'Plan-Annahmen'!$B$72 | O44: ='Plan-Annahmen'!$B$70 | P44: =L44+M44+N44+O44 | Q44: =IF(P44>'Plan-Annahmen'!$B$69,1,0) | R44: =IF(P44>'Plan-Annahmen'!$B$68,1,0) | S44: =IF(K44>='Plan-Annahmen'!$B$59,1,0)
A45: 9 | B45: =EDATE('Plan-Annahmen'!$B$8,A45-1) | C45: 1.25 | D45: =IF(A45-'Plan-Annahmen'!$B$42<1,0,INDEX($K$37:$K$60,A45-'Plan-Annahmen'!$B$42)*'Plan-Annahmen'!$B$36/12*'Plan-Annahmen'!$B$39*(1+'Plan-Annahmen'!$B$50*'Plan-Annahmen'!$B$51)) | E45: =C45+D45 | F45: =MIN(E45,MAX(0,'Plan-Annahmen'!$B$16-H44)) | G45: =E45-F45 | H45: =H44+F45 | I45: =I44*(1-'Plan-Annahmen'!$B$48)+F45 | J45: =J44*(1-'Plan-Annahmen'!$B$45)+G45 | K45: =I45+J45 | L45: 20.5 | M45: =K45*'Plan-Annahmen'!$B$71 | N45: =E45*'Plan-Annahmen'!$B$72 | O45: ='Plan-Annahmen'!$B$70 | P45: =L45+M45+N45+O45 | Q45: =IF(P45>'Plan-Annahmen'!$B$69,1,0) | R45: =IF(P45>'Plan-Annahmen'!$B$68,1,0) | S45: =IF(K45>='Plan-Annahmen'!$B$59,1,0)
A46: 10 | B46: =EDATE('Plan-Annahmen'!$B$8,A46-1) | C46: 1.25 | D46: =IF(A46-'Plan-Annahmen'!$B$42<1,0,INDEX($K$37:$K$60,A46-'Plan-Annahmen'!$B$42)*'Plan-Annahmen'!$B$36/12*'Plan-Annahmen'!$B$39*(1+'Plan-Annahmen'!$B$50*'Plan-Annahmen'!$B$51)) | E46: =C46+D46 | F46: =MIN(E46,MAX(0,'Plan-Annahmen'!$B$16-H45)) | G46: =E46-F46 | H46: =H45+F46 | I46: =I45*(1-'Plan-Annahmen'!$B$48)+F46 | J46: =J45*(1-'Plan-Annahmen'!$B$45)+G46 | K46: =I46+J46 | L46: 19.5 | M46: =K46*'Plan-Annahmen'!$B$71 | N46: =E46*'Plan-Annahmen'!$B$72 | O46: ='Plan-Annahmen'!$B$70 | P46: =L46+M46+N46+O46 | Q46: =IF(P46>'Plan-Annahmen'!$B$69,1,0) | R46: =IF(P46>'Plan-Annahmen'!$B$68,1,0) | S46: =IF(K46>='Plan-Annahmen'!$B$59,1,0)
A47: 11 | B47: =EDATE('Plan-Annahmen'!$B$8,A47-1) | C47: 2.25 | D47: =IF(A47-'Plan-Annahmen'!$B$42<1,0,INDEX($K$37:$K$60,A47-'Plan-Annahmen'!$B$42)*'Plan-Annahmen'!$B$36/12*'Plan-Annahmen'!$B$39*(1+'Plan-Annahmen'!$B$50*'Plan-Annahmen'!$B$51)) | E47: =C47+D47 | F47: =MIN(E47,MAX(0,'Plan-Annahmen'!$B$16-H46)) | G47: =E47-F47 | H47: =H46+F47 | I47: =I46*(1-'Plan-Annahmen'!$B$48)+F47 | J47: =J46*(1-'Plan-Annahmen'!$B$45)+G47 | K47: =I47+J47 | L47: 19.5 | M47: =K47*'Plan-Annahmen'!$B$71 | N47: =E47*'Plan-Annahmen'!$B$72 | O47: ='Plan-Annahmen'!$B$70 | P47: =L47+M47+N47+O47 | Q47: =IF(P47>'Plan-Annahmen'!$B$69,1,0) | R47: =IF(P47>'Plan-Annahmen'!$B$68,1,0) | S47: =IF(K47>='Plan-Annahmen'!$B$59,1,0)
A48: 12 | B48: =EDATE('Plan-Annahmen'!$B$8,A48-1) | C48: 2 | D48: =IF(A48-'Plan-Annahmen'!$B$42<1,0,INDEX($K$37:$K$60,A48-'Plan-Annahmen'!$B$42)*'Plan-Annahmen'!$B$36/12*'Plan-Annahmen'!$B$39*(1+'Plan-Annahmen'!$B$50*'Plan-Annahmen'!$B$51)) | E48: =C48+D48 | F48: =MIN(E48,MAX(0,'Plan-Annahmen'!$B$16-H47)) | G48: =E48-F48 | H48: =H47+F48 | I48: =I47*(1-'Plan-Annahmen'!$B$48)+F48 | J48: =J47*(1-'Plan-Annahmen'!$B$45)+G48 | K48: =I48+J48 | L48: 19.5 | M48: =K48*'Plan-Annahmen'!$B$71 | N48: =E48*'Plan-Annahmen'!$B$72 | O48: ='Plan-Annahmen'!$B$70 | P48: =L48+M48+N48+O48 | Q48: =IF(P48>'Plan-Annahmen'!$B$69,1,0) | R48: =IF(P48>'Plan-Annahmen'!$B$68,1,0) | S48: =IF(K48>='Plan-Annahmen'!$B$59,1,0)
A49: 13 | B49: =EDATE('Plan-Annahmen'!$B$8,A49-1) | C49: 2 | D49: =IF(A49-'Plan-Annahmen'!$B$42<1,0,INDEX($K$37:$K$60,A49-'Plan-Annahmen'!$B$42)*'Plan-Annahmen'!$B$36/12*'Plan-Annahmen'!$B$39*(1+'Plan-Annahmen'!$B$50*'Plan-Annahmen'!$B$51)) | E49: =C49+D49 | F49: =MIN(E49,MAX(0,'Plan-Annahmen'!$B$16-H48)) | G49: =E49-F49 | H49: =H48+F49 | I49: =I48*(1-'Plan-Annahmen'!$B$48)+F49 | J49: =J48*(1-'Plan-Annahmen'!$B$45)+G49 | K49: =I49+J49 | L49: 19.5 | M49: =K49*'Plan-Annahmen'!$B$71 | N49: =E49*'Plan-Annahmen'!$B$72 | O49: ='Plan-Annahmen'!$B$70 | P49: =L49+M49+N49+O49 | Q49: =IF(P49>'Plan-Annahmen'!$B$69,1,0) | R49: =IF(P49>'Plan-Annahmen'!$B$68,1,0) | S49: =IF(K49>='Plan-Annahmen'!$B$59,1,0)
... A60: 24 | B60: =EDATE('Plan-Annahmen'!$B$8,A60-1) | C60: 3.5 | D60: =IF(A60-'Plan-Annahmen'!$B$42<1,0,INDEX($K$37:$K$60,A60-'Plan-Annahmen'!$B$42)*'Plan-Annahmen'!$B$36/12*'Plan-Annahmen'!$B$39*(1+'Plan-Annahmen'!$B$50*'Plan-Annahmen'!$B$51)) | E60: =C60+D60 | F60: =MIN(E60,MAX(0,'Plan-Annahmen'!$B$16-H59)) | G60: =E60-F60 | H60: =H59+F60 | I60: =I59*(1-'Plan-Annahmen'!$B$48)+F60 | J60: =J59*(1-'Plan-Annahmen'!$B$45)+G60 | K60: =I60+J60 | L60: 19.5 | M60: =K60*'Plan-Annahmen'!$B$71 | N60: =E60*'Plan-Annahmen'!$B$72 | O60: ='Plan-Annahmen'!$B$70 | P60: =L60+M60+N60+O60 | Q60: =IF(P60>'Plan-Annahmen'!$B$69,1,0) | R60: =IF(P60>'Plan-Annahmen'!$B$68,1,0) | S60: =IF(K60>='Plan-Annahmen'!$B$59,1,0)
A61: Σ / Ende | C61: =SUM(C37:C60) | D61: =SUM(D37:D60) | E61: =SUM(E37:E60) | K61: =K60 | Q61: =SUM(Q37:Q60) | R61: =SUM(R37:R60) | S61: =IFERROR(INDEX($A$37:$A$60,MATCH(1,$S$37:$S$60,0)),999)
A64: Szenario: Optimistisch | C64: Kanäle Σ 103.5 Betriebe (Marketing)
A65: Monat | B65: Kalendermonat | C65: Neukunden Kanäle | D65: Neukunden Mundpropaganda | E65: Neukunden gesamt | F65: davon Gründerplätze | G65: davon Standard | H65: Gründerplätze vergeben (kum.) | I65: Gründerkunden aktiv | J65: Standardkunden aktiv | K65: Kunden aktiv gesamt | L65: Std. Vertrieb (Marketing) | M65: Std. Support | N65: Std. Onboarding | O65: Std. Grundlast | P65: Std. gesamt | Q65: über Dauerlinie (65)? | R65: über Sprintlinie (86)? | S65: UG-Schwelle erreicht?
A66: 1 | B66: =EDATE('Plan-Annahmen'!$B$8,A66-1) | C66: 0 | D66: =IF(A66-'Plan-Annahmen'!$B$43<1,0,INDEX($K$66:$K$89,A66-'Plan-Annahmen'!$B$43)*'Plan-Annahmen'!$B$37/12*'Plan-Annahmen'!$B$40*(1+'Plan-Annahmen'!$B$50*'Plan-Annahmen'!$B$51)) | E66: =C66+D66 | F66: =MIN(E66,MAX(0,'Plan-Annahmen'!$B$16-0)) | G66: =E66-F66 | H66: =0+F66 | I66: =0*(1-'Plan-Annahmen'!$B$49)+F66 | J66: =0*(1-'Plan-Annahmen'!$B$46)+G66 | K66: =I66+J66 | L66: 4 | M66: =K66*'Plan-Annahmen'!$B$71 | N66: =E66*'Plan-Annahmen'!$B$72 | O66: ='Plan-Annahmen'!$B$70 | P66: =L66+M66+N66+O66 | Q66: =IF(P66>'Plan-Annahmen'!$B$69,1,0) | R66: =IF(P66>'Plan-Annahmen'!$B$68,1,0) | S66: =IF(K66>='Plan-Annahmen'!$B$59,1,0)
A67: 2 | B67: =EDATE('Plan-Annahmen'!$B$8,A67-1) | C67: 0 | D67: =IF(A67-'Plan-Annahmen'!$B$43<1,0,INDEX($K$66:$K$89,A67-'Plan-Annahmen'!$B$43)*'Plan-Annahmen'!$B$37/12*'Plan-Annahmen'!$B$40*(1+'Plan-Annahmen'!$B$50*'Plan-Annahmen'!$B$51)) | E67: =C67+D67 | F67: =MIN(E67,MAX(0,'Plan-Annahmen'!$B$16-H66)) | G67: =E67-F67 | H67: =H66+F67 | I67: =I66*(1-'Plan-Annahmen'!$B$49)+F67 | J67: =J66*(1-'Plan-Annahmen'!$B$46)+G67 | K67: =I67+J67 | L67: 18 | M67: =K67*'Plan-Annahmen'!$B$71 | N67: =E67*'Plan-Annahmen'!$B$72 | O67: ='Plan-Annahmen'!$B$70 | P67: =L67+M67+N67+O67 | Q67: =IF(P67>'Plan-Annahmen'!$B$69,1,0) | R67: =IF(P67>'Plan-Annahmen'!$B$68,1,0) | S67: =IF(K67>='Plan-Annahmen'!$B$59,1,0)
A68: 3 | B68: =EDATE('Plan-Annahmen'!$B$8,A68-1) | C68: 0 | D68: =IF(A68-'Plan-Annahmen'!$B$43<1,0,INDEX($K$66:$K$89,A68-'Plan-Annahmen'!$B$43)*'Plan-Annahmen'!$B$37/12*'Plan-Annahmen'!$B$40*(1+'Plan-Annahmen'!$B$50*'Plan-Annahmen'!$B$51)) | E68: =C68+D68 | F68: =MIN(E68,MAX(0,'Plan-Annahmen'!$B$16-H67)) | G68: =E68-F68 | H68: =H67+F68 | I68: =I67*(1-'Plan-Annahmen'!$B$49)+F68 | J68: =J67*(1-'Plan-Annahmen'!$B$46)+G68 | K68: =I68+J68 | L68: 5 | M68: =K68*'Plan-Annahmen'!$B$71 | N68: =E68*'Plan-Annahmen'!$B$72 | O68: ='Plan-Annahmen'!$B$70 | P68: =L68+M68+N68+O68 | Q68: =IF(P68>'Plan-Annahmen'!$B$69,1,0) | R68: =IF(P68>'Plan-Annahmen'!$B$68,1,0) | S68: =IF(K68>='Plan-Annahmen'!$B$59,1,0)
A69: 4 | B69: =EDATE('Plan-Annahmen'!$B$8,A69-1) | C69: 1 | D69: =IF(A69-'Plan-Annahmen'!$B$43<1,0,INDEX($K$66:$K$89,A69-'Plan-Annahmen'!$B$43)*'Plan-Annahmen'!$B$37/12*'Plan-Annahmen'!$B$40*(1+'Plan-Annahmen'!$B$50*'Plan-Annahmen'!$B$51)) | E69: =C69+D69 | F69: =MIN(E69,MAX(0,'Plan-Annahmen'!$B$16-H68)) | G69: =E69-F69 | H69: =H68+F69 | I69: =I68*(1-'Plan-Annahmen'!$B$49)+F69 | J69: =J68*(1-'Plan-Annahmen'!$B$46)+G69 | K69: =I69+J69 | L69: 15 | M69: =K69*'Plan-Annahmen'!$B$71 | N69: =E69*'Plan-Annahmen'!$B$72 | O69: ='Plan-Annahmen'!$B$70 | P69: =L69+M69+N69+O69 | Q69: =IF(P69>'Plan-Annahmen'!$B$69,1,0) | R69: =IF(P69>'Plan-Annahmen'!$B$68,1,0) | S69: =IF(K69>='Plan-Annahmen'!$B$59,1,0)
A70: 5 | B70: =EDATE('Plan-Annahmen'!$B$8,A70-1) | C70: 2.5 | D70: =IF(A70-'Plan-Annahmen'!$B$43<1,0,INDEX($K$66:$K$89,A70-'Plan-Annahmen'!$B$43)*'Plan-Annahmen'!$B$37/12*'Plan-Annahmen'!$B$40*(1+'Plan-Annahmen'!$B$50*'Plan-Annahmen'!$B$51)) | E70: =C70+D70 | F70: =MIN(E70,MAX(0,'Plan-Annahmen'!$B$16-H69)) | G70: =E70-F70 | H70: =H69+F70 | I70: =I69*(1-'Plan-Annahmen'!$B$49)+F70 | J70: =J69*(1-'Plan-Annahmen'!$B$46)+G70 | K70: =I70+J70 | L70: 16 | M70: =K70*'Plan-Annahmen'!$B$71 | N70: =E70*'Plan-Annahmen'!$B$72 | O70: ='Plan-Annahmen'!$B$70 | P70: =L70+M70+N70+O70 | Q70: =IF(P70>'Plan-Annahmen'!$B$69,1,0) | R70: =IF(P70>'Plan-Annahmen'!$B$68,1,0) | S70: =IF(K70>='Plan-Annahmen'!$B$59,1,0)
A71: 6 | B71: =EDATE('Plan-Annahmen'!$B$8,A71-1) | C71: 4 | D71: =IF(A71-'Plan-Annahmen'!$B$43<1,0,INDEX($K$66:$K$89,A71-'Plan-Annahmen'!$B$43)*'Plan-Annahmen'!$B$37/12*'Plan-Annahmen'!$B$40*(1+'Plan-Annahmen'!$B$50*'Plan-Annahmen'!$B$51)) | E71: =C71+D71 | F71: =MIN(E71,MAX(0,'Plan-Annahmen'!$B$16-H70)) | G71: =E71-F71 | H71: =H70+F71 | I71: =I70*(1-'Plan-Annahmen'!$B$49)+F71 | J71: =J70*(1-'Plan-Annahmen'!$B$46)+G71 | K71: =I71+J71 | L71: 16 | M71: =K71*'Plan-Annahmen'!$B$71 | N71: =E71*'Plan-Annahmen'!$B$72 | O71: ='Plan-Annahmen'!$B$70 | P71: =L71+M71+N71+O71 | Q71: =IF(P71>'Plan-Annahmen'!$B$69,1,0) | R71: =IF(P71>'Plan-Annahmen'!$B$68,1,0) | S71: =IF(K71>='Plan-Annahmen'!$B$59,1,0)
A72: 7 | B72: =EDATE('Plan-Annahmen'!$B$8,A72-1) | C72: 4 | D72: =IF(A72-'Plan-Annahmen'!$B$43<1,0,INDEX($K$66:$K$89,A72-'Plan-Annahmen'!$B$43)*'Plan-Annahmen'!$B$37/12*'Plan-Annahmen'!$B$40*(1+'Plan-Annahmen'!$B$50*'Plan-Annahmen'!$B$51)) | E72: =C72+D72 | F72: =MIN(E72,MAX(0,'Plan-Annahmen'!$B$16-H71)) | G72: =E72-F72 | H72: =H71+F72 | I72: =I71*(1-'Plan-Annahmen'!$B$49)+F72 | J72: =J71*(1-'Plan-Annahmen'!$B$46)+G72 | K72: =I72+J72 | L72: 16.5 | M72: =K72*'Plan-Annahmen'!$B$71 | N72: =E72*'Plan-Annahmen'!$B$72 | O72: ='Plan-Annahmen'!$B$70 | P72: =L72+M72+N72+O72 | Q72: =IF(P72>'Plan-Annahmen'!$B$69,1,0) | R72: =IF(P72>'Plan-Annahmen'!$B$68,1,0) | S72: =IF(K72>='Plan-Annahmen'!$B$59,1,0)
A73: 8 | B73: =EDATE('Plan-Annahmen'!$B$8,A73-1) | C73: 3 | D73: =IF(A73-'Plan-Annahmen'!$B$43<1,0,INDEX($K$66:$K$89,A73-'Plan-Annahmen'!$B$43)*'Plan-Annahmen'!$B$37/12*'Plan-Annahmen'!$B$40*(1+'Plan-Annahmen'!$B$50*'Plan-Annahmen'!$B$51)) | E73: =C73+D73 | F73: =MIN(E73,MAX(0,'Plan-Annahmen'!$B$16-H72)) | G73: =E73-F73 | H73: =H72+F73 | I73: =I72*(1-'Plan-Annahmen'!$B$49)+F73 | J73: =J72*(1-'Plan-Annahmen'!$B$46)+G73 | K73: =I73+J73 | L73: 20.5 | M73: =K73*'Plan-Annahmen'!$B$71 | N73: =E73*'Plan-Annahmen'!$B$72 | O73: ='Plan-Annahmen'!$B$70 | P73: =L73+M73+N73+O73 | Q73: =IF(P73>'Plan-Annahmen'!$B$69,1,0) | R73: =IF(P73>'Plan-Annahmen'!$B$68,1,0) | S73: =IF(K73>='Plan-Annahmen'!$B$59,1,0)
A74: 9 | B74: =EDATE('Plan-Annahmen'!$B$8,A74-1) | C74: 3.5 | D74: =IF(A74-'Plan-Annahmen'!$B$43<1,0,INDEX($K$66:$K$89,A74-'Plan-Annahmen'!$B$43)*'Plan-Annahmen'!$B$37/12*'Plan-Annahmen'!$B$40*(1+'Plan-Annahmen'!$B$50*'Plan-Annahmen'!$B$51)) | E74: =C74+D74 | F74: =MIN(E74,MAX(0,'Plan-Annahmen'!$B$16-H73)) | G74: =E74-F74 | H74: =H73+F74 | I74: =I73*(1-'Plan-Annahmen'!$B$49)+F74 | J74: =J73*(1-'Plan-Annahmen'!$B$46)+G74 | K74: =I74+J74 | L74: 20.5 | M74: =K74*'Plan-Annahmen'!$B$71 | N74: =E74*'Plan-Annahmen'!$B$72 | O74: ='Plan-Annahmen'!$B$70 | P74: =L74+M74+N74+O74 | Q74: =IF(P74>'Plan-Annahmen'!$B$69,1,0) | R74: =IF(P74>'Plan-Annahmen'!$B$68,1,0) | S74: =IF(K74>='Plan-Annahmen'!$B$59,1,0)
A75: 10 | B75: =EDATE('Plan-Annahmen'!$B$8,A75-1) | C75: 3.5 | D75: =IF(A75-'Plan-Annahmen'!$B$43<1,0,INDEX($K$66:$K$89,A75-'Plan-Annahmen'!$B$43)*'Plan-Annahmen'!$B$37/12*'Plan-Annahmen'!$B$40*(1+'Plan-Annahmen'!$B$50*'Plan-Annahmen'!$B$51)) | E75: =C75+D75 | F75: =MIN(E75,MAX(0,'Plan-Annahmen'!$B$16-H74)) | G75: =E75-F75 | H75: =H74+F75 | I75: =I74*(1-'Plan-Annahmen'!$B$49)+F75 | J75: =J74*(1-'Plan-Annahmen'!$B$46)+G75 | K75: =I75+J75 | L75: 19.5 | M75: =K75*'Plan-Annahmen'!$B$71 | N75: =E75*'Plan-Annahmen'!$B$72 | O75: ='Plan-Annahmen'!$B$70 | P75: =L75+M75+N75+O75 | Q75: =IF(P75>'Plan-Annahmen'!$B$69,1,0) | R75: =IF(P75>'Plan-Annahmen'!$B$68,1,0) | S75: =IF(K75>='Plan-Annahmen'!$B$59,1,0)
A76: 11 | B76: =EDATE('Plan-Annahmen'!$B$8,A76-1) | C76: 4 | D76: =IF(A76-'Plan-Annahmen'!$B$43<1,0,INDEX($K$66:$K$89,A76-'Plan-Annahmen'!$B$43)*'Plan-Annahmen'!$B$37/12*'Plan-Annahmen'!$B$40*(1+'Plan-Annahmen'!$B$50*'Plan-Annahmen'!$B$51)) | E76: =C76+D76 | F76: =MIN(E76,MAX(0,'Plan-Annahmen'!$B$16-H75)) | G76: =E76-F76 | H76: =H75+F76 | I76: =I75*(1-'Plan-Annahmen'!$B$49)+F76 | J76: =J75*(1-'Plan-Annahmen'!$B$46)+G76 | K76: =I76+J76 | L76: 19.5 | M76: =K76*'Plan-Annahmen'!$B$71 | N76: =E76*'Plan-Annahmen'!$B$72 | O76: ='Plan-Annahmen'!$B$70 | P76: =L76+M76+N76+O76 | Q76: =IF(P76>'Plan-Annahmen'!$B$69,1,0) | R76: =IF(P76>'Plan-Annahmen'!$B$68,1,0) | S76: =IF(K76>='Plan-Annahmen'!$B$59,1,0)
A77: 12 | B77: =EDATE('Plan-Annahmen'!$B$8,A77-1) | C77: 4.5 | D77: =IF(A77-'Plan-Annahmen'!$B$43<1,0,INDEX($K$66:$K$89,A77-'Plan-Annahmen'!$B$43)*'Plan-Annahmen'!$B$37/12*'Plan-Annahmen'!$B$40*(1+'Plan-Annahmen'!$B$50*'Plan-Annahmen'!$B$51)) | E77: =C77+D77 | F77: =MIN(E77,MAX(0,'Plan-Annahmen'!$B$16-H76)) | G77: =E77-F77 | H77: =H76+F77 | I77: =I76*(1-'Plan-Annahmen'!$B$49)+F77 | J77: =J76*(1-'Plan-Annahmen'!$B$46)+G77 | K77: =I77+J77 | L77: 19.5 | M77: =K77*'Plan-Annahmen'!$B$71 | N77: =E77*'Plan-Annahmen'!$B$72 | O77: ='Plan-Annahmen'!$B$70 | P77: =L77+M77+N77+O77 | Q77: =IF(P77>'Plan-Annahmen'!$B$69,1,0) | R77: =IF(P77>'Plan-Annahmen'!$B$68,1,0) | S77: =IF(K77>='Plan-Annahmen'!$B$59,1,0)
A78: 13 | B78: =EDATE('Plan-Annahmen'!$B$8,A78-1) | C78: 4.5 | D78: =IF(A78-'Plan-Annahmen'!$B$43<1,0,INDEX($K$66:$K$89,A78-'Plan-Annahmen'!$B$43)*'Plan-Annahmen'!$B$37/12*'Plan-Annahmen'!$B$40*(1+'Plan-Annahmen'!$B$50*'Plan-Annahmen'!$B$51)) | E78: =C78+D78 | F78: =MIN(E78,MAX(0,'Plan-Annahmen'!$B$16-H77)) | G78: =E78-F78 | H78: =H77+F78 | I78: =I77*(1-'Plan-Annahmen'!$B$49)+F78 | J78: =J77*(1-'Plan-Annahmen'!$B$46)+G78 | K78: =I78+J78 | L78: 19.5 | M78: =K78*'Plan-Annahmen'!$B$71 | N78: =E78*'Plan-Annahmen'!$B$72 | O78: ='Plan-Annahmen'!$B$70 | P78: =L78+M78+N78+O78 | Q78: =IF(P78>'Plan-Annahmen'!$B$69,1,0) | R78: =IF(P78>'Plan-Annahmen'!$B$68,1,0) | S78: =IF(K78>='Plan-Annahmen'!$B$59,1,0)
... A89: 24 | B89: =EDATE('Plan-Annahmen'!$B$8,A89-1) | C89: 7 | D89: =IF(A89-'Plan-Annahmen'!$B$43<1,0,INDEX($K$66:$K$89,A89-'Plan-Annahmen'!$B$43)*'Plan-Annahmen'!$B$37/12*'Plan-Annahmen'!$B$40*(1+'Plan-Annahmen'!$B$50*'Plan-Annahmen'!$B$51)) | E89: =C89+D89 | F89: =MIN(E89,MAX(0,'Plan-Annahmen'!$B$16-H88)) | G89: =E89-F89 | H89: =H88+F89 | I89: =I88*(1-'Plan-Annahmen'!$B$49)+F89 | J89: =J88*(1-'Plan-Annahmen'!$B$46)+G89 | K89: =I89+J89 | L89: 19.5 | M89: =K89*'Plan-Annahmen'!$B$71 | N89: =E89*'Plan-Annahmen'!$B$72 | O89: ='Plan-Annahmen'!$B$70 | P89: =L89+M89+N89+O89 | Q89: =IF(P89>'Plan-Annahmen'!$B$69,1,0) | R89: =IF(P89>'Plan-Annahmen'!$B$68,1,0) | S89: =IF(K89>='Plan-Annahmen'!$B$59,1,0)
A90: Σ / Ende | C90: =SUM(C66:C89) | D90: =SUM(D66:D89) | E90: =SUM(E66:E89) | K90: =K89 | Q90: =SUM(Q66:Q89) | R90: =SUM(R66:R89) | S90: =IFERROR(INDEX($A$66:$A$89,MATCH(1,$S$66:$S$89,0)),999)
A93: In der Summenzeile steht unter 'UG-Schwelle erreicht?' der erste Monat, in dem das Szenario die Schwelle reißt (999 = nie im Horizont) — daran hängen im Raster die UG-Kosten. Die Spalten davor zählen, in wie vielen der 24 Monate das Szenario mehr Stunden verlangt, als die jeweilige Kapazitätslinie hergibt. Ein Szenario, das die Sprintlinie regelmäßig reißt, ist nicht optimistisch, sondern nicht durchführbar, solange Sandy Vollzeit angestellt ist.

Sheet Plan-Kosten
A1: Plan-Kosten — Vollständigkeits-Katalog A–H, Rechtsform Einzelunternehmen (UG später)
A2: Jeder Posten aus dem Katalog des Chief of Staff steht als Zeile, auch die nicht zutreffenden — mit Begründung, damit kein Kästchen leer bleibt. Spalte 'Phase': 'immer' = unabhängig von der Rechtsform · 'EU' = nur in der Einzelunternehmens-Phase · 'UG' = erst ab der UG-Gründung, gesteuert über die Kundenzahl (Block unten, wird je Szenario im Raster zugeschaltet). Typ: laufend · einmalig · Monatsvektor (Werte je Monat aus einer Zulieferung) · Reserve (Liquiditätsbindung, kein Aufwand) · variabel (im Raster aus Kunden und Umsatz gerechnet). Die 17 Belege aus Mai bis August 2026 sind Privatausgaben und NICHT Teil dieser Kostenbasis — sie bleiben im Rechnungsjournal als Historie; Sandy nimmt den Anmeldetag als Startdatum.
A6: Nr | B6: Kat. | C6: Posten | D6: Typ | E6: Betrag | F6: Einheit | G6: Phase | H6: Start (Monat) | I6: € umgerechnet | J6: Quelle / Begründung | N6: 1 | O6: 2 | P6: 3 | Q6: 4 | R6: 5 | S6: 6 | T6: 7 | U6: 8 | V6: 9 | W6: 10 | X6: 11 | Y6: 12 | Z6: 13 | AA6: 14 | AB6: 15 | AC6: 16 | AD6: 17 | AE6: 18 | AF6: 19 | AG6: 20 | AH6: 21 | AI6: 22 | AJ6: 23 | AK6: 24 | AL6: Vorsteuer je € (Anteil am eingetragenen Betrag) | AM6: Basis des Betrags — warum dieser Anteil
A7: 1 | B7: A | C7: Gewerbeanmeldung Berlin (online) | D7: einmalig | E7: 15 | F7: € einmalig | G7: EU | H7: ='Plan-Annahmen'!$B$58 | I7: =IF(F7="€/Monat",E7,IF(F7="€/Jahr",E7/12,IF(F7="USD/Monat",E7*'Plan-Annahmen'!$B$20,IF(F7="USD einmalig",E7*'Plan-Annahmen'!$B$20,E7)))) | J7: 15 € online über eMeldung, 26 € persönlich im Ordnungsamt (gewerbeanmeldung.de/gewerbeamt/berlin, Abruf 03.09.2026) — deckt sich mit Legals Angabe. Statt der 1.700 € aus der ersten Planfassung. | N7: =IF(N$6=$H7,$I7,0) | O7: =IF(O$6=$H7,$I7,0) | P7: =IF(P$6=$H7,$I7,0) | Q7: =IF(Q$6=$H7,$I7,0) | R7: =IF(R$6=$H7,$I7,0) | S7: =IF(S$6=$H7,$I7,0) | T7: =IF(T$6=$H7,$I7,0) | U7: =IF(U$6=$H7,$I7,0) | ... AK7: =IF(AK$6=$H7,$I7,0) | AL7: 0 | AM7: Behoerdengebuehr (eMeldung Berlin) — hoheitliche Leistung, keine Umsatzsteuer, keine Vorsteuer.
A8: 2 | B8: A | C8: UG: Notar + Handelsregister (Musterprotokoll) | D8: UG-Block | E8: 480 | F8: € einmalig | G8: UG | I8: =IF(F8="€/Monat",E8,IF(F8="€/Jahr",E8/12,IF(F8="USD/Monat",E8*'Plan-Annahmen'!$B$20,IF(F8="USD einmalig",E8*'Plan-Annahmen'!$B$20,E8)))) | J8: entscheidungen-fuer-sandy.md S-4 (Legal): 300–480 €, oberes Ende. Fällt erst im UG-Monat an, s. UG-Block unten. | N8: → UG-Block unten | AL8: 0 | AM8: UG-Block, steht nicht in der Basissumme.
A9: 3 | B9: A | C9: UG: Eröffnungsbilanz (Steuerberater) | D9: UG-Block | E9: 500 | F9: € einmalig | G9: UG | I9: =IF(F9="€/Monat",E9,IF(F9="€/Jahr",E9/12,IF(F9="USD/Monat",E9*'Plan-Annahmen'!$B$20,IF(F9="USD einmalig",E9*'Plan-Annahmen'!$B$20,E9)))) | J9: Teil der von Legal genannten Zusatzkosten im Gründungsjahr. Annahme. | N9: → UG-Block unten | AL9: 0 | AM9: UG-Block, steht nicht in der Basissumme.
A10: 4 | B10: A | C10: UG: Stammkapital (Einzahlung) | D10: UG-Reserve | E10: 1000 | F10: € einmalig | G10: UG | I10: =IF(F10="€/Monat",E10,IF(F10="€/Jahr",E10/12,IF(F10="USD/Monat",E10*'Plan-Annahmen'!$B$20,IF(F10="USD einmalig",E10*'Plan-Annahmen'!$B$20,E10)))) | J10: Legal: 1.000 €. Kein Aufwand — bleibt Vermögen der UG, bindet aber Liquidität ab dem UG-Monat. In der Einzelunternehmens-Phase entfällt die Bindung vollständig. | N10: → UG-Block unten | AL10: 0 | AM10: Reserve, kein Aufwand.
A11: 5 | B11: A | C11: Anwalt für individuelle Satzung | D11: nicht zutreffend | E11: 0 | F11: € einmalig | G11: UG | J11: trifft nicht zu, weil Musterprotokoll (Ein-Personen-UG). Bei individueller Satzung 500–1.500 €. | AL11: 0 | AM11: trifft nicht zu.
A12: 6 | B12: A | C12: Geschäftskonto (Kontoführung) | D12: UG-Block | E12: 10 | F12: €/Monat | G12: UG | I12: =IF(F12="€/Monat",E12,IF(F12="€/Jahr",E12/12,IF(F12="USD/Monat",E12*'Plan-Annahmen'!$B$20,IF(F12="USD einmalig",E12*'Plan-Annahmen'!$B$20,E12)))) | J12: Bei der UG zwingend, beim Einzelunternehmen nicht (Legal). Für die saubere Trennung privat/geschäftlich trotzdem empfehlenswert — dann hier auf 'immer' umstellen. | N12: → UG-Block unten | AL12: 0 | AM12: UG-Block; Kontofuehrung ist ausserdem nach § 4 Nr. 8 UStG steuerfrei.
A13: 7 | B13: A | C13: IHK-Beitrag | D13: nicht zutreffend | E13: 0 | F13: €/Jahr | G13: EU | J13: trifft in der Einzelunternehmens-Phase nicht zu: Existenzgründer sind in den ersten zwei Jahren beitragsfrei (§ 3 Abs. 3 IHKG, Gewerbeertrag unter 25.000 €, nicht im Handelsregister) — das ist genau der Planhorizont. Ab UG-Gründung fällt der Grundbeitrag an, s. UG-Block. | AL13: 0 | AM13: trifft nicht zu.
A14: 8 | B14: A | C14: IHK-Beitrag ab UG-Gründung | D14: UG-Block | E14: 200 | F14: €/Jahr | G14: UG | I14: =IF(F14="€/Monat",E14,IF(F14="€/Jahr",E14/12,IF(F14="USD/Monat",E14*'Plan-Annahmen'!$B$20,IF(F14="USD einmalig",E14*'Plan-Annahmen'!$B$20,E14)))) | J14: Die UG ist im Handelsregister eingetragen, die Gründerbefreiung gilt dort nicht. Grundbeitrag je IHK und Stufe 30–300 €/Jahr, Annahme 200 €. | N14: → UG-Block unten | AL14: 0 | AM14: UG-Block; Kammerbeitrag ohne Umsatzsteuer.
A15: 9 | B15: B | C15: Anwaltliche Prüfung AGB / Datenschutz / AVV vor dem Launch | D15: einmalig | E15: 1500 | F15: € einmalig | G15: immer | H15: 3 | I15: =IF(F15="€/Monat",E15,IF(F15="€/Jahr",E15/12,IF(F15="USD/Monat",E15*'Plan-Annahmen'!$B$20,IF(F15="USD einmalig",E15*'Plan-Annahmen'!$B$20,E15)))) | J15: Katalog B, Größenordnung 800–2.500 € für ein SaaS-Rechtstextpaket, vor Gate 1 angesetzt. Die interne Legal-Rolle ersetzt keine haftende Kanzlei — ob Sandy das will, ist ihre Entscheidung, die Position gehört aber in den Plan. | N15: =IF(N$6=$H15,$I15,0) | O15: =IF(O$6=$H15,$I15,0) | P15: =IF(P$6=$H15,$I15,0) | Q15: =IF(Q$6=$H15,$I15,0) | R15: =IF(R$6=$H15,$I15,0) | S15: =IF(S$6=$H15,$I15,0) | T15: =IF(T$6=$H15,$I15,0) | U15: =IF(U$6=$H15,$I15,0) | ... AK15: =IF(AK$6=$H15,$I15,0) | AL15: 0 | AM15: Honorarspanne aus B2B-Quellen = NETTO angesetzt. Unter Regelbesteuerung ist netto der richtige Planwert; ein zusaetzlicher Abzug waere doppelt gezaehlt.
A16: 10 | B16: B | C16: Markenanmeldung DPMA (elektronisch, bis 3 Klassen) | D16: einmalig | E16: 290 | F16: € einmalig | G16: immer | H16: 4 | I16: =IF(F16="€/Monat",E16,IF(F16="€/Jahr",E16/12,IF(F16="USD/Monat",E16*'Plan-Annahmen'!$B$20,IF(F16="USD einmalig",E16*'Plan-Annahmen'!$B$20,E16)))) | J16: DPMA-Gebührenverzeichnis (fixmarke.de): 290 € elektronisch inkl. 3 Klassen, je weitere Klasse 100 €, Verlängerung nach 10 Jahren 750 € (außerhalb des Horizonts). | N16: =IF(N$6=$H16,$I16,0) | O16: =IF(O$6=$H16,$I16,0) | P16: =IF(P$6=$H16,$I16,0) | Q16: =IF(Q$6=$H16,$I16,0) | R16: =IF(R$6=$H16,$I16,0) | S16: =IF(S$6=$H16,$I16,0) | T16: =IF(T$6=$H16,$I16,0) | U16: =IF(U$6=$H16,$I16,0) | ... AK16: =IF(AK$6=$H16,$I16,0) | AL16: 0 | AM16: DPMA-Amtsgebuehr, keine Umsatzsteuer.
A17: 11 | B17: B | C17: DIN-Normtexte 18363 / 18365 | D17: einmalig | E17: 150 | F17: € einmalig | G17: immer | H17: 1 | I17: =IF(F17="€/Monat",E17,IF(F17="€/Jahr",E17/12,IF(F17="USD/Monat",E17*'Plan-Annahmen'!$B$20,IF(F17="USD einmalig",E17*'Plan-Annahmen'!$B$20,E17)))) | J17: CoS-F-Info 01.09.2026, von Sandy freigegeben; Beleg folgt. | N17: =IF(N$6=$H17,$I17,0) | O17: =IF(O$6=$H17,$I17,0) | P17: =IF(P$6=$H17,$I17,0) | Q17: =IF(Q$6=$H17,$I17,0) | R17: =IF(R$6=$H17,$I17,0) | S17: =IF(S$6=$H17,$I17,0) | T17: =IF(T$6=$H17,$I17,0) | U17: =IF(U$6=$H17,$I17,0) | ... AK17: =IF(AK$6=$H17,$I17,0) | AL17: =7/107 | AM17: Fachliteratur/E-Book: 7 % (§ 12 Abs. 2 Nr. 14 UStG), Betrag brutto — gemessen an Beleg 2026-018 (DIN Media, 54,00 € brutto = 50,47 + 3,53).
A18: 12 | B18: B | C18: Weitere Normtexte bei neuen Gewerken | D18: laufend | E18: 150 | F18: €/Jahr | G18: immer | H18: 13 | I18: =IF(F18="€/Monat",E18,IF(F18="€/Jahr",E18/12,IF(F18="USD/Monat",E18*'Plan-Annahmen'!$B$20,IF(F18="USD einmalig",E18*'Plan-Annahmen'!$B$20,E18)))) | J18: Annahme: etwa ein weiterer Normtext pro Jahr ab Jahr 2. | N18: =IF(N$6>=$H18,$I18,0) | O18: =IF(O$6>=$H18,$I18,0) | P18: =IF(P$6>=$H18,$I18,0) | Q18: =IF(Q$6>=$H18,$I18,0) | R18: =IF(R$6>=$H18,$I18,0) | S18: =IF(S$6>=$H18,$I18,0) | T18: =IF(T$6>=$H18,$I18,0) | U18: =IF(U$6>=$H18,$I18,0) | ... AK18: =IF(AK$6>=$H18,$I18,0) | AL18: =7/107 | AM18: wie Zeile darueber.
A19: 13 | B19: B | C19: Rechtstexte-Abo statt Einzelprüfung | D19: nicht zutreffend | E19: 0 | F19: €/Monat | G19: immer | J19: trifft nicht zu, weil die Einzelprüfung angesetzt ist — nicht beides. Alternative 10–30 €/Monat. | AL19: 0 | AM19: trifft nicht zu.
A20: 14 | B20: B | C20: Rücklage Abmahnung / Rechtsstreit | D20: Reserve | E20: 1000 | F20: € einmalig | G20: immer | H20: 5 | I20: =IF(F20="€/Monat",E20,IF(F20="€/Jahr",E20/12,IF(F20="USD/Monat",E20*'Plan-Annahmen'!$B$20,IF(F20="USD einmalig",E20*'Plan-Annahmen'!$B$20,E20)))) | J20: Katalog B: Liquiditätsreserve ab dem öffentlichen Launch, kein Aufwand. | N20: =IF(N$6=$H20,$I20,0) | O20: =IF(O$6=$H20,$I20,0) | P20: =IF(P$6=$H20,$I20,0) | Q20: =IF(Q$6=$H20,$I20,0) | R20: =IF(R$6=$H20,$I20,0) | S20: =IF(S$6=$H20,$I20,0) | T20: =IF(T$6=$H20,$I20,0) | U20: =IF(U$6=$H20,$I20,0) | ... AK20: =IF(AK$6=$H20,$I20,0) | AL20: 0 | AM20: Reserve, kein Aufwand.
A21: 15 | B21: C | C21: IT-Vermögensschaden-Haftpflicht (exali/Markel, 1 Mio. €) | D21: laufend | E21: 300 | F21: €/Jahr | G21: immer | H21: 3 | I21: =IF(F21="€/Monat",E21,IF(F21="€/Jahr",E21/12,IF(F21="USD/Monat",E21*'Plan-Annahmen'!$B$20,IF(F21="USD einmalig",E21*'Plan-Annahmen'!$B$20,E21)))) | J21: OFFENE ZAHL — Beitrag unbekannt, S-4 wartet auf Sandy. Früherer Stand 200–400 €/Jahr, Platzhalter 300 €. Rechtsformunabhängig, also in beiden Phasen gleich (Legal). | N21: =IF(N$6>=$H21,$I21,0) | O21: =IF(O$6>=$H21,$I21,0) | P21: =IF(P$6>=$H21,$I21,0) | Q21: =IF(Q$6>=$H21,$I21,0) | R21: =IF(R$6>=$H21,$I21,0) | S21: =IF(S$6>=$H21,$I21,0) | T21: =IF(T$6>=$H21,$I21,0) | U21: =IF(U$6>=$H21,$I21,0) | ... AK21: =IF(AK$6>=$H21,$I21,0) | AL21: 0 | AM21: Versicherungsbeitrag: steuerfrei nach § 4 Nr. 10 UStG (dafuer Versicherungsteuer) — keine Vorsteuer.
A22: 16 | B22: C | C22: Betriebshaftpflicht | D22: laufend | E22: 100 | F22: €/Jahr | G22: immer | H22: 3 | I22: =IF(F22="€/Monat",E22,IF(F22="€/Jahr",E22/12,IF(F22="USD/Monat",E22*'Plan-Annahmen'!$B$20,IF(F22="USD einmalig",E22*'Plan-Annahmen'!$B$20,E22)))) | J22: Annahme 100 €/Jahr; prüfen, ob im exali-Paket enthalten — dann 0. | N22: =IF(N$6>=$H22,$I22,0) | O22: =IF(O$6>=$H22,$I22,0) | P22: =IF(P$6>=$H22,$I22,0) | Q22: =IF(Q$6>=$H22,$I22,0) | R22: =IF(R$6>=$H22,$I22,0) | S22: =IF(S$6>=$H22,$I22,0) | T22: =IF(T$6>=$H22,$I22,0) | U22: =IF(U$6>=$H22,$I22,0) | ... AK22: =IF(AK$6>=$H22,$I22,0) | AL22: 0 | AM22: Versicherungsbeitrag: steuerfrei nach § 4 Nr. 10 UStG — keine Vorsteuer.
A23: 17 | B23: C | C23: Cyber-Deckung | D23: nicht zutreffend | E23: 0 | F23: €/Jahr | G23: immer | J23: trifft nicht zu, weil der Cyber-Drittschaden bei der IT-Haftpflicht üblicherweise enthalten ist. | AL23: 0 | AM23: trifft nicht zu.
A24: 18 | B24: D | C24: Steuerberater / Buchhaltung — Einzelunternehmen (EÜR) | D24: laufend | E24: 800 | F24: €/Jahr | G24: EU | H24: ='Plan-Annahmen'!$B$58 | I24: =IF(F24="€/Monat",E24,IF(F24="€/Jahr",E24/12,IF(F24="USD/Monat",E24*'Plan-Annahmen'!$B$20,IF(F24="USD einmalig",E24*'Plan-Annahmen'!$B$20,E24)))) | J24: Legal nennt 0–800 €/Jahr; hier das obere Ende. ACHTUNG, eigener Hinweis: Diese Spanne setzt voraus, dass Sandy die laufende Buchhaltung selbst macht (Lexware) und höchstens die EÜR prüfen lässt. Für einen Steuerberater, der alles übernimmt, liegt die belegte Spanne bei 1.000–2.500 €/Jahr (onlinebilanz.de, 2026). Wenn Sandy abgeben will, hier auf ~1.500 € erhöhen. | N24: =IF(N$6>=$H24,$I24,0) | O24: =IF(O$6>=$H24,$I24,0) | P24: =IF(P$6>=$H24,$I24,0) | Q24: =IF(Q$6>=$H24,$I24,0) | R24: =IF(R$6>=$H24,$I24,0) | S24: =IF(S$6>=$H24,$I24,0) | T24: =IF(T$6>=$H24,$I24,0) | U24: =IF(U$6>=$H24,$I24,0) | ... AK24: =IF(AK$6>=$H24,$I24,0) | AL24: 0 | AM24: Honorarspanne = NETTO angesetzt (Legal nennt 0–800 €/Jahr). Kein zusaetzlicher Abzug.
A25: 19 | B25: D | C25: Steuerberater ab UG-Gründung (Bilanz, KSt/GewSt, Offenlegung) | D25: UG-Block | E25: 3000 | F25: €/Jahr | G25: UG | I25: =IF(F25="€/Monat",E25,IF(F25="€/Jahr",E25/12,IF(F25="USD/Monat",E25*'Plan-Annahmen'!$B$20,IF(F25="USD einmalig",E25*'Plan-Annahmen'!$B$20,E25)))) | J25: onlinebilanz.de (2026): Kleinst-GmbH/UG 2.500–4.500 €/Jahr, Annahme 3.000 €. Im UG-Block wird nur die DIFFERENZ zum EÜR-Satz zugeschaltet, damit nichts doppelt zählt. | N25: → UG-Block unten | AL25: 0 | AM25: UG-Block.
A26: 20 | B26: D | C26: Buchhaltungssoftware (Lexware Office, Tarif M) | D26: laufend | E26: 14.16 | F26: €/Monat | G26: immer | H26: ='Plan-Annahmen'!$B$58 | I26: =IF(F26="€/Monat",E26,IF(F26="€/Jahr",E26/12,IF(F26="USD/Monat",E26*'Plan-Annahmen'!$B$20,IF(F26="USD einmalig",E26*'Plan-Annahmen'!$B$20,E26)))) | J26: trusted.de: 11,90 €/Monat netto = 14,16 € brutto. | N26: =IF(N$6>=$H26,$I26,0) | O26: =IF(O$6>=$H26,$I26,0) | P26: =IF(P$6>=$H26,$I26,0) | Q26: =IF(Q$6>=$H26,$I26,0) | R26: =IF(R$6>=$H26,$I26,0) | S26: =IF(S$6>=$H26,$I26,0) | T26: =IF(T$6>=$H26,$I26,0) | U26: =IF(U$6>=$H26,$I26,0) | ... AK26: =IF(AK$6>=$H26,$I26,0) | AL26: =19/119 | AM26: Betrag ausdruecklich brutto (11,90 € netto = 14,16 € brutto, Quellenzeile daneben).
A27: 21 | B27: D | C27: Einkommensteuer-Rücklage | D27: variabel | E27: ='Plan-Annahmen'!$B$82 | F27: % vom Gewinn | G27: immer | J27: Im Raster: Grenzsteuersatz auf positive Monatsergebnisse, sofort zurückgelegt statt erst beim Bescheid. In der Einzelunternehmens-Phase ist das die korrekte Rechnung (gewerbliche Einkünfte oben auf das Gehalt). | AL27: 0 | AM27: Einkommensteuer, keine Vorsteuer.
A28: 22 | B28: D | C28: Gewerbesteuer | D28: nicht zutreffend | E28: 0 | F28: €/Jahr | G28: EU | J28: trifft im ganzen Horizont nicht zu: Freibetrag 24.500 € Gewerbeertrag für natürliche Personen (§ 11 GewStG), der Gewinn bleibt weit darunter. Ab UG-Gründung entfällt der Freibetrag — Teil der nicht simulierten UG-Besteuerung. | AL28: 0 | AM28: trifft nicht zu.
A29: 23 | B29: D | C29: Körperschaft- und Gewerbesteuer der UG | D29: nicht simuliert | E29: 0 | F29: — | G29: UG | J29: VORBEHALT, hängt am UG-Schalter: Für die Einzelunternehmens-Phase ist er gegenstandslos, das Raster rechnet dort korrekt. Ab dem UG-Monat gilt er unverändert: KSt 15 % + Soli + Gewerbesteuer auf Gesellschaftsebene, danach erst Geschäftsführergehalt oder Ausschüttung. Das ist eine Steuerberater-Rechnung, die ich nicht verbindlich aufstellen darf. | AL29: 0 | AM29: nicht simuliert.
A30: 24 | B30: D | C30: Solidaritätszuschlag | D30: nicht zutreffend | E30: 0 | F30: €/Jahr | G30: EU | J30: trifft nicht zu (Freigrenze nicht erreicht). Bei der UG fällt Soli auf die Körperschaftsteuer an. | AL30: 0 | AM30: trifft nicht zu.
A31: 25 | B31: D | C31: Umsatzsteuer / Vorsteuer | D31: variabel | E31: ='Plan-Annahmen'!$B$61 | F31: Schalter | G31: immer | J31: Beide Varianten rechenbar. Die Preise sind netto und die Kunden Unternehmen — die Umsatzsteuer läuft durch, die Wirkung liegt allein im Vorsteuerabzug (Zeile unten). Die Kleinunternehmergrenze wird im Horizont nicht gerissen, s. Deckblatt. | AL31: 0 | AM31: Schalterzeile, kein Betrag.
A32: 26 | B32: D | C32: Vorsteuer-Erstattung bei Regelbesteuerung (mindernd, Näherung) | D32: variabel | E32: 0 | F32: € | G32: immer | J32: Im Raster als negative Kostenzeile: (laufende + einmalige Kosten) × vorsteuerfähiger Anteil × 19/119 × Schalter. Bei ausgeschaltetem Schalter 0. | AL32: 0 | AM32: Ergebniszeile, wird unten gerechnet.
A33: 27 | B33: E | C33: Supabase (2 Projekte, Pro-Tarif, flach) | D33: laufend | E33: 50 | F33: USD/Monat | G33: immer | H33: 1 | I33: =IF(F33="€/Monat",E33,IF(F33="€/Jahr",E33/12,IF(F33="USD/Monat",E33*'Plan-Annahmen'!$B$20,IF(F33="USD einmalig",E33*'Plan-Annahmen'!$B$20,E33)))) | J33: CoS-P-008 (Platform): 2 × 25 $ Pro-Tarif, 0 % Nutzungsaufschlag (DB 22 MB von 8 GB, Speicher 87 MB von 100 GB). Flach, wächst bis weit über den Horizont hinaus nicht mit der Kundenzahl. Der letzte Einzelbeleg lag bei 53,83 $, noch vor der Bereinigung der Extra-Projekte. | N33: =IF(N$6>=$H33,$I33,0) | O33: =IF(O$6>=$H33,$I33,0) | P33: =IF(P$6>=$H33,$I33,0) | Q33: =IF(Q$6>=$H33,$I33,0) | R33: =IF(R$6>=$H33,$I33,0) | S33: =IF(S$6>=$H33,$I33,0) | T33: =IF(T$6>=$H33,$I33,0) | U33: =IF(U$6>=$H33,$I33,0) | ... AK33: =IF(AK$6>=$H33,$I33,0) | AL33: 0 | AM33: Reverse Charge § 13b UStG: Supabase weist keine USt aus. Unter Regelbesteuerung angemeldet und im selben Zug gezogen — durchlaufend, Saldo null.
A34: 28 | B34: E | C34: Vercel (Pro-Seat) | D34: laufend | E34: 23.8 | F34: USD/Monat | G34: immer | H34: 1 | I34: =IF(F34="€/Monat",E34,IF(F34="€/Jahr",E34/12,IF(F34="USD/Monat",E34*'Plan-Annahmen'!$B$20,IF(F34="USD einmalig",E34*'Plan-Annahmen'!$B$20,E34)))) | J34: Stabil über vier Belege (Journal 2026-002/005/007/015), inkl. USt. Wächst mit Personal, nicht mit Kunden. | N34: =IF(N$6>=$H34,$I34,0) | O34: =IF(O$6>=$H34,$I34,0) | P34: =IF(P$6>=$H34,$I34,0) | Q34: =IF(Q$6>=$H34,$I34,0) | R34: =IF(R$6>=$H34,$I34,0) | S34: =IF(S$6>=$H34,$I34,0) | T34: =IF(T$6>=$H34,$I34,0) | U34: =IF(U$6>=$H34,$I34,0) | ... AK34: =IF(AK$6>=$H34,$I34,0) | AL34: =19/119 | AM34: Beleg brutto inkl. 19 % (Journal 2026-002/005/007/015, EU VAT EU056329113) — Vercel rechnet KEIN Reverse Charge ab.
A35: 29 | B35: E | C35: Anthropic — direkt (KI-Rollen, Entwicklung) | D35: laufend | E35: 53.55 | F35: USD/Monat | G35: immer | H35: 1 | I35: =IF(F35="€/Monat",E35,IF(F35="€/Jahr",E35/12,IF(F35="USD/Monat",E35*'Plan-Annahmen'!$B$20,IF(F35="USD einmalig",E35*'Plan-Annahmen'!$B$20,E35)))) | J35: Journal 2026-010 vom 17.08.2026. OFFEN, ob wiederkehrend oder einmaliger Nachkauf — hier vorsichtshalber monatlich (46 €/Monat Unterschied). | N35: =IF(N$6>=$H35,$I35,0) | O35: =IF(O$6>=$H35,$I35,0) | P35: =IF(P$6>=$H35,$I35,0) | Q35: =IF(Q$6>=$H35,$I35,0) | R35: =IF(R$6>=$H35,$I35,0) | S35: =IF(S$6>=$H35,$I35,0) | T35: =IF(T$6>=$H35,$I35,0) | U35: =IF(U$6>=$H35,$I35,0) | ... AK35: =IF(AK$6>=$H35,$I35,0) | AL35: =19/119 | AM35: Beleg brutto inkl. 19 % (Journal 2026-010, EU VAT IE4276970QH).
A36: 30 | B36: E | C36: Claude Pro (Apple/iTunes) | D36: laufend | E36: 22 | F36: €/Monat | G36: immer | H36: 1 | I36: =IF(F36="€/Monat",E36,IF(F36="€/Jahr",E36/12,IF(F36="USD/Monat",E36*'Plan-Annahmen'!$B$20,IF(F36="USD einmalig",E36*'Plan-Annahmen'!$B$20,E36)))) | J36: Von Sandy als geschäftlich bestätigt (03.09.2026). Monatlich, automatische Verlängerung. | N36: =IF(N$6>=$H36,$I36,0) | O36: =IF(O$6>=$H36,$I36,0) | P36: =IF(P$6>=$H36,$I36,0) | Q36: =IF(Q$6>=$H36,$I36,0) | R36: =IF(R$6>=$H36,$I36,0) | S36: =IF(S$6>=$H36,$I36,0) | T36: =IF(T$6>=$H36,$I36,0) | U36: =IF(U$6>=$H36,$I36,0) | ... AK36: =IF(AK$6>=$H36,$I36,0) | AL36: =19/119 | AM36: Beleg brutto inkl. 19 % (Journal 2026-001/009, Apple Distribution International).
A37: 31 | B37: E | C37: Domain / IONOS (nur Sofortangebot-Anteil) | D37: laufend | E37: =2.5+13/12 | F37: €/Monat | G37: immer | H37: 1 | I37: =IF(F37="€/Monat",E37,IF(F37="€/Jahr",E37/12,IF(F37="USD/Monat",E37*'Plan-Annahmen'!$B$20,IF(F37="USD einmalig",E37*'Plan-Annahmen'!$B$20,E37)))) | J37: 2,50 €/Monat (IONOS Mail Basic 5) + 13,00 €/Jahr (Domain .app + Domain Guard) anteilig = 2,50 + 13/12. Fremde Domains auf denselben Rechnungen bleiben ausgeschlossen (Rechnungsjournal, Spalte 'Sofortangebot-Anteil'). | N37: =IF(N$6>=$H37,$I37,0) | O37: =IF(O$6>=$H37,$I37,0) | P37: =IF(P$6>=$H37,$I37,0) | Q37: =IF(Q$6>=$H37,$I37,0) | R37: =IF(R$6>=$H37,$I37,0) | S37: =IF(S$6>=$H37,$I37,0) | T37: =IF(T$6>=$H37,$I37,0) | U37: =IF(U$6>=$H37,$I37,0) | ... AK37: =IF(AK$6>=$H37,$I37,0) | AL37: =19/119 | AM37: Beleg brutto inkl. 19 % (Journal 2026-011 bis -017, IONOS SE, USt-IdNr. DE815563912).
A38: 32 | B38: E | C38: Resend / Sentry / GitHub-Plan | D38: laufend | E38: 0 | F38: €/Monat | G38: immer | H38: 1 | I38: =IF(F38="€/Monat",E38,IF(F38="€/Jahr",E38/12,IF(F38="USD/Monat",E38*'Plan-Annahmen'!$B$20,IF(F38="USD einmalig",E38*'Plan-Annahmen'!$B$20,E38)))) | J38: Aktuell 0 € (Free-Tier, keine Belege). Im Code bestätigt. | N38: =IF(N$6>=$H38,$I38,0) | O38: =IF(O$6>=$H38,$I38,0) | P38: =IF(P$6>=$H38,$I38,0) | Q38: =IF(Q$6>=$H38,$I38,0) | R38: =IF(R$6>=$H38,$I38,0) | S38: =IF(S$6>=$H38,$I38,0) | T38: =IF(T$6>=$H38,$I38,0) | U38: =IF(U$6>=$H38,$I38,0) | ... AK38: =IF(AK$6>=$H38,$I38,0) | AL38: 0 | AM38: Betrag 0.
A39: 33 | B39: E | C39: Resend Pro ab ~200 aktiven Betrieben | D39: nicht zutreffend | E39: 0 | F39: USD/Monat | G39: immer | J39: trifft im Horizont nicht zu: selbst das optimistische Szenario erreicht keine 200 Betriebe (Schwelle aus CoS-P-008). | AL39: 0 | AM39: trifft nicht zu.
A40: 34 | B40: E | C40: OpenAI (Whisper + GPT-4o) — KI-Kosten je Angebot | D40: variabel | E40: ='Plan-Annahmen'!$B$17 | F40: Cent/Angebot | G40: immer | J40: Im Raster: aktive Kunden × Angebote × 2,5 Cent. Bewusst nicht zusätzlich als Fixkosten — sonst Doppelzählung. | AL40: 0 | AM40: variabel, laeuft im Raster ueber Plan-24M Spalte K (unveraendert). Die 2,5 Cent sind ein Netto-Listenpreis in USD — unter Regelbesteuerung damit bereits der richtige Kostenwert.
A41: 35 | B41: E | C41: Stripe-Transaktionsgebühren | D41: variabel | E41: ='Plan-Annahmen'!$B$18 | F41: % + fix | G41: immer | J41: Im Raster je zahlendem Kunden und Monat: 1,5 % + 0,25 €. | AL41: 0 | AM41: Zahlungsdienstleistung, steuerfrei nach § 4 Nr. 8 UStG — keine Vorsteuer.
A42: 36 | B42: E | C42: Objektspeicher Sprachaufnahmen / Fotos | D42: nicht zutreffend | E42: 0 | F42: €/Monat | G42: immer | J42: trifft im Horizont nicht zu: 87 MB von 100 GB inklusive. Vorbehalt Platform: der 30-Tage-Aufräumjob läuft noch nicht (CRON_SECRET) — auch linear wachsend bleibt es weit unter dem Limit. | AL42: 0 | AM42: trifft nicht zu.
A43: 37 | B43: E | C43: Apple Developer Program (native App) | D43: laufend | E43: 99 | F43: €/Jahr | G43: immer | H43: 10 | I43: =IF(F43="€/Monat",E43,IF(F43="€/Jahr",E43/12,IF(F43="USD/Monat",E43*'Plan-Annahmen'!$B$20,IF(F43="USD einmalig",E43*'Plan-Annahmen'!$B$20,E43)))) | J43: 99 €/Jahr; native App ab Mitte 2027 fest eingeplant (docs/vision-strategie.md) = Monat 10. | N43: =IF(N$6>=$H43,$I43,0) | O43: =IF(O$6>=$H43,$I43,0) | P43: =IF(P$6>=$H43,$I43,0) | Q43: =IF(Q$6>=$H43,$I43,0) | R43: =IF(R$6>=$H43,$I43,0) | S43: =IF(S$6>=$H43,$I43,0) | T43: =IF(T$6>=$H43,$I43,0) | U43: =IF(U$6>=$H43,$I43,0) | ... AK43: =IF(AK$6>=$H43,$I43,0) | AL43: 0 | AM43: als NETTO angesetzt, bis der erste Beleg vorliegt: Apple stellt Entwicklern mit USt-IdNr. ohne deutsche USt. Sobald ein Beleg mit USt-Ausweis da ist, hier 19/119 eintragen.
A44: 38 | B44: E | C44: Google Play Console (Registrierung) | D44: einmalig | E44: 25 | F44: USD einmalig | G44: immer | H44: 10 | I44: =IF(F44="€/Monat",E44,IF(F44="€/Jahr",E44/12,IF(F44="USD/Monat",E44*'Plan-Annahmen'!$B$20,IF(F44="USD einmalig",E44*'Plan-Annahmen'!$B$20,E44)))) | J44: 25 $ einmalig. Im Katalog fehlten die Store-Gebühren neben Apple — ergänzt. | N44: =IF(N$6=$H44,$I44,0) | O44: =IF(O$6=$H44,$I44,0) | P44: =IF(P$6=$H44,$I44,0) | Q44: =IF(Q$6=$H44,$I44,0) | R44: =IF(R$6=$H44,$I44,0) | S44: =IF(S$6=$H44,$I44,0) | T44: =IF(T$6=$H44,$I44,0) | U44: =IF(U$6=$H44,$I44,0) | ... AK44: =IF(AK$6=$H44,$I44,0) | AL44: 0 | AM44: als NETTO angesetzt, bis der erste Beleg vorliegt — wie Apple Developer.
A45: 39 | B45: E | C45: KI-Rollen-Ausbau nach Gate 1 | D45: laufend | E45: 50 | F45: USD/Monat | G45: immer | H45: 7 | I45: =IF(F45="€/Monat",E45,IF(F45="€/Jahr",E45/12,IF(F45="USD/Monat",E45*'Plan-Annahmen'!$B$20,IF(F45="USD einmalig",E45*'Plan-Annahmen'!$B$20,E45)))) | J45: Das Team besteht aus KI-Rollen: jede neue Rolle erhöht die Anthropic-Kosten statt der Lohnkosten. Platzhalter +50 $/Monat, Höhe und Zeitpunkt offen. | N45: =IF(N$6>=$H45,$I45,0) | O45: =IF(O$6>=$H45,$I45,0) | P45: =IF(P$6>=$H45,$I45,0) | Q45: =IF(Q$6>=$H45,$I45,0) | R45: =IF(R$6>=$H45,$I45,0) | S45: =IF(S$6>=$H45,$I45,0) | T45: =IF(T$6>=$H45,$I45,0) | U45: =IF(U$6>=$H45,$I45,0) | ... AK45: =IF(AK$6>=$H45,$I45,0) | AL45: =19/119 | AM45: Platzhalter fuer zusaetzliche Anthropic-Kosten — wie Zeile 29 brutto inkl. 19 %.
A46: 40 | B46: F | C46: Bezahltes Werbebudget | D46: nicht zutreffend | E46: 0 | F46: €/Monat | G46: immer | J46: trifft nicht zu — bewusste Festlegung (docs/vision-strategie.md). Der Kanalplan rechnet ausdrücklich ohne Werbebudget. | AL46: 0 | AM46: trifft nicht zu.
A47: 41 | B47: F | C47: Marketing-Sachkosten laut Kanalplan | D47: Monatsvektor | E47: 1350 | F47: € Σ 24 M | G47: immer | J47: Zulieferung Marketing (gtm-kanalplan.xlsx, 'Sachkosten — gesamt'): Oktober 180 € (Flyer, Aufsteller, Ansteckmikro/Stativ), dann 10–20 €/Monat, ab April 2027 je 100 € pro kaltem Fachhandel-Laden. Summe 1.350 €. Werte je Monat rechts — Größenordnungen, keine Angebote. Alle Beträge BRUTTO (von Marketing am 23.09.2026 bestätigt) — Vorsteuer siehe Spalte AL/AM. GEÄNDERT am 23.09.2026: die zwei Dessau-Fahrten im Oktober 2026 (vorher 80 €) stehen auf 0 €, weil Sandys Deutschlandticket sie abdeckt — die Summe sinkt von 1.430 € auf 1.350 €. | N47: 0 | O47: 180 | P47: 0 | Q47: 20 | R47: 20 | S47: 20 | T47: 20 | U47: 120 | V47: 20 | W47: 110 | X47: 10 | Y47: 110 | Z47: 10 | AA47: 110 | AB47: 10 | AC47: 110 | AD47: 10 | AE47: 110 | AF47: 10 | AG47: 110 | AH47: 10 | AI47: 110 | AJ47: 10 | AK47: 110 | AL47: =(660*19/119+360*7/107+60*19/119+270*19/119)/1350 | AM47: Groessenordnungen von Marketing (gtm-kanalplan.xlsx, Blatt „Annahmen"), am 23.09.2026 von Marketing ausdruecklich als BRUTTO bestaetigt (Endpreise inkl. USt). STAND 23.09.2026, 10:00 UTC — ERSETZT die Fassung von 07:00 UTC (1.430 EUR / 186,85 EUR), weil Sandy die Fahrtfrage beantwortet hat. Zusammensetzung der 1.350 EUR und Steuersaetze: Druck Flyer/Aufsteller 660 EUR zu 19 % = 105,38 EUR - Fahrten 360 EUR zu 7 % = 23,55 EUR - Ausruestung Ansteckmikro/Stativ 60 EUR zu 19 % = 9,58 EUR - laufender Kleinbedarf 270 EUR zu 19 % = 43,11 EUR. Summe Vorsteuer ueber 24 Monate 181,62 EUR, Anteil am Betrag 0,1345323176. FAHRTEN — zwei verschiedene Faelle, bewusst unterschiedlich behandelt: (a) Die zwei Dessau-Fahrten im Oktober 2026 (frueher 2 x 40 EUR = 80 EUR) stehen auf 0 EUR. Sandy faehrt mit dem Deutschlandticket, das sie fuer ihren Angestelltenjob ohnehin haelt und privat bezahlt (Sandys Antwort, 23.09.2026). Eine privat gehaltene Monatskarte, die ohne den Betrieb genauso gekauft wuerde, verursacht keine zusaetzliche Betriebsausgabe; es gibt keine auf den Betrieb lautende Rechnung und damit auch keinen Vorsteuerabzug nach § 15 Abs. 1 UStG. Deshalb 0 EUR Kosten UND 0 EUR Vorsteuer, nicht 80 EUR zu 7 %. (b) Die 9 Fahrten zu kalten Fachhandel-Laeden ab April 2027 (9 x 40 EUR = 360 EUR) bleiben mit 7 % stehen. Begruendung: das Ticket haengt an Sandys Angestelltenjob, dieser Kanal startet erst in 19 Monaten, und welche Laeden es werden, steht nicht fest. Das ist der vorsichtige Ansatz - faellt das Ticket dort ebenfalls an, wird der Plan um bis zu 360 EUR billiger, nicht teurer. UEBERNACHTUNG: keine eigene Zeile, und das ist eine Entscheidung. Dessau ist von Berlin mit dem RE7 ohne Umsteigen in rund zwei Stunden je Richtung erreichbar; alle Besuche sind als Tagesfahrten geplant (Marketing, gtm-kanalplan.xlsx Feld F2). Sandy hat am 23.09.2026 zusaetzlich gesagt, sie koenne „ggfs" kostenlos bei Clemens uebernachten - das ist eine Moeglichkeit, keine Zusage, und der Plan stuetzt sich nicht darauf. Groessenordnung, falls doch: eine Uebernachtung in Dessau kostet 60-90 EUR brutto (7 % auf die Beherbergung, § 12 Abs. 2 Nr. 11 UStG, 19 % auf Fruehstueck). Ab etwa vier Uebernachtungen in den 24 Monaten waere eine eigene Zeile faellig; darunter geht es im Kleinbedarf unter. MISCHSATZ: Die Zelle traegt bewusst einen Mischsatz, weil die Spalte genau einen Faktor je Zeile erlaubt, die Zeile aber ein Monatsvektor mit wechselnder Zusammensetzung ist. Ueber die 24 Monate stimmt die Vorsteuer auf den Cent (181,6186 EUR exakt wie gemischt). Die groesste Abweichung in einem einzelnen Monat ist jetzt 4,52 EUR und liegt im Oktober 2026 (exakt 28,74 EUR, gemischt 24,22 EUR) - vorher waren es 0,58 EUR. Der Sprung kommt daher, dass der Oktober nach dem Wegfall der Bahnfahrten nur noch 19-%-Posten enthaelt, der Mischsatz aber die 7 % der spaeteren Fahrten mittraegt. Eine eigene Zeile fuer die Fahrten wuerde das auf null bringen, verschoebe aber die Zeilennummern, an denen $AL$7:$AL$55 und die Raster haengen; 4,52 EUR in einem einzigen Monat rechtfertigen dieses Risiko nicht. In allen uebrigen Monaten liegt die Abweichung unter 1,01 EUR. VORBEHALT: Die 270 EUR Kleinbedarf sind nicht aufgeschluesselt; Kleinkram ohne Rechnung mit ausgewiesener Steuer senkt die 43,11 EUR, schlimmstenfalls auf 0. Loest der erste echte Beleg, nicht eine weitere Frage. Quellen: Antwort Head of Marketing 23.09.2026 07:20 UTC und Kanalplan-Stand 09:52 UTC (Felder F2, F4, F6, A13, A14) - Sandys Antwort zur Fahrtfrage, weitergegeben vom Chief of Staff, 23.09.2026 08:10 UTC, docs/chief-of-staff-finance-todos.md - § 12 Abs. 2 Nr. 10 UStG (Schienen-Nahverkehr 7 %) - § 15 Abs. 1 UStG (Vorsteuerabzug setzt Leistungsbezug fuer das Unternehmen voraus).
A48: 42 | B48: F | C48: Social-Media- / Scheduling-Tools | D48: nicht zutreffend | E48: 0 | F48: €/Monat | G48: immer | J48: trifft nach Marketing-Einschätzung nicht zu: die kostenlosen Stufen sollten reichen. | AL48: 0 | AM48: trifft nicht zu.
A49: 43 | B49: F | C49: Domain- / Markenvarianten | D49: nicht zutreffend | E49: =2.5+13/12 | F49: €/Jahr | G49: immer | J49: trifft nicht zu: die weiteren Domains auf den IONOS-Rechnungen gehören anderen Projekten. | AL49: 0 | AM49: trifft nicht zu.
A50: 44 | B50: F | C50: Arbeitszeit Sandy / Clemens / KI-Rollen | D50: nicht zutreffend | E50: 0 | F50: € | G50: immer | J50: kein Geldposten — aber der eigentliche Engpass. Als Stundenmodell auf 'Plan-Kunden' geführt. | AL50: 0 | AM50: trifft nicht zu.
A51: 45 | B51: G | C51: Zahlungsausfälle / Lastschrift-Rückläufer | D51: variabel | E51: ='Plan-Annahmen'!$B$52 | F51: % vom Umsatz | G51: immer | J51: Im Raster als Abzug vom Umsatz. | AL51: 0 | AM51: Erloesminderung, keine Vorsteuer.
A52: 46 | B52: G | C52: Kulanz / Erstattungen | D52: variabel | E52: ='Plan-Annahmen'!$B$53 | F52: % vom Umsatz | G52: immer | J52: Im Raster als Abzug vom Umsatz. | AL52: 0 | AM52: Erloesminderung, keine Vorsteuer.
A53: 47 | B53: G | C53: Gründerpreis 29 € dauerhaft für die ersten 25 | D53: variabel | E53: ='Plan-Annahmen'!$B$16 | F53: Kunden | G53: immer | J53: Im Kundenmodell explizit abgebildet: die Gründerkohorte wird getrennt geführt, mit eigener, niedrigerer Abwanderungsrate. Frei werdende Gründerplätze werden NICHT neu vergeben — vorsichtig. | AL53: 0 | AM53: Preiszeile, kein Kostenbetrag.
A54: 48 | B54: G | C54: Empfehlungs-Anreiz 'ein Kollege, ein Monat geschenkt' | D54: variabel | E54: ='Plan-Annahmen'!$B$50 | F54: Schalter | G54: immer | J54: Marketing schlägt vor, Sandy entscheidet — Schalter, standardmäßig aus. Bei 1 kostet jede Empfehlungs-Neukundin einmalig 49 € Umsatz. | AL54: 0 | AM54: Schalterzeile, kein Betrag.
A55: 49 | B55: H | C55: Netto-Bedarf, Krankenversicherung, Altersvorsorge, Übergangspuffer | D55: nicht zutreffend | E55: 0 | F55: € | G55: immer | J55: keine Betriebskosten — vollständig auf 'Plan-Phase B' als Stufenmodell gerechnet. | AL55: 0 | AM55: trifft nicht zu.
C57: Summe laufende Kosten Basis (€/Monat) | N57: =SUMIF($D$7:$D$55,"laufend",N7:N55)+SUMIF($D$7:$D$55,"Monatsvektor",N7:N55) | O57: =SUMIF($D$7:$D$55,"laufend",O7:O55)+SUMIF($D$7:$D$55,"Monatsvektor",O7:O55) | P57: =SUMIF($D$7:$D$55,"laufend",P7:P55)+SUMIF($D$7:$D$55,"Monatsvektor",P7:P55) | Q57: =SUMIF($D$7:$D$55,"laufend",Q7:Q55)+SUMIF($D$7:$D$55,"Monatsvektor",Q7:Q55) | R57: =SUMIF($D$7:$D$55,"laufend",R7:R55)+SUMIF($D$7:$D$55,"Monatsvektor",R7:R55) | S57: =SUMIF($D$7:$D$55,"laufend",S7:S55)+SUMIF($D$7:$D$55,"Monatsvektor",S7:S55) | T57: =SUMIF($D$7:$D$55,"laufend",T7:T55)+SUMIF($D$7:$D$55,"Monatsvektor",T7:T55) | U57: =SUMIF($D$7:$D$55,"laufend",U7:U55)+SUMIF($D$7:$D$55,"Monatsvektor",U7:U55) | ... AK57: =SUMIF($D$7:$D$55,"laufend",AK7:AK55)+SUMIF($D$7:$D$55,"Monatsvektor",AK7:AK55)
C58: Summe Einmalkosten Basis (€ im Monat) | N58: =SUMIF($D$7:$D$55,"einmalig",N7:N55) | O58: =SUMIF($D$7:$D$55,"einmalig",O7:O55) | P58: =SUMIF($D$7:$D$55,"einmalig",P7:P55) | Q58: =SUMIF($D$7:$D$55,"einmalig",Q7:Q55) | R58: =SUMIF($D$7:$D$55,"einmalig",R7:R55) | S58: =SUMIF($D$7:$D$55,"einmalig",S7:S55) | T58: =SUMIF($D$7:$D$55,"einmalig",T7:T55) | U58: =SUMIF($D$7:$D$55,"einmalig",U7:U55) | ... AK58: =SUMIF($D$7:$D$55,"einmalig",AK7:AK55)
C59: Summe Reserven Basis (€ im Monat) | N59: =SUMIF($D$7:$D$55,"Reserve",N7:N55) | O59: =SUMIF($D$7:$D$55,"Reserve",O7:O55) | P59: =SUMIF($D$7:$D$55,"Reserve",P7:P55) | Q59: =SUMIF($D$7:$D$55,"Reserve",Q7:Q55) | R59: =SUMIF($D$7:$D$55,"Reserve",R7:R55) | S59: =SUMIF($D$7:$D$55,"Reserve",S7:S55) | T59: =SUMIF($D$7:$D$55,"Reserve",T7:T55) | U59: =SUMIF($D$7:$D$55,"Reserve",U7:U55) | ... AK59: =SUMIF($D$7:$D$55,"Reserve",AK7:AK55)
C60: Vorsteuer-Erstattung bei Regelbesteuerung (mindernd) — je Zeile aus Spalte AL, nicht pauschal | N60: =-SUMPRODUCT($AL$7:$AL$55,IF(ISNUMBER(N$7:N$55),N$7:N$55,0))*'Plan-Annahmen'!$B$61 | O60: =-SUMPRODUCT($AL$7:$AL$55,IF(ISNUMBER(O$7:O$55),O$7:O$55,0))*'Plan-Annahmen'!$B$61 | P60: =-SUMPRODUCT($AL$7:$AL$55,IF(ISNUMBER(P$7:P$55),P$7:P$55,0))*'Plan-Annahmen'!$B$61 | Q60: =-SUMPRODUCT($AL$7:$AL$55,IF(ISNUMBER(Q$7:Q$55),Q$7:Q$55,0))*'Plan-Annahmen'!$B$61 | R60: =-SUMPRODUCT($AL$7:$AL$55,IF(ISNUMBER(R$7:R$55),R$7:R$55,0))*'Plan-Annahmen'!$B$61 | S60: =-SUMPRODUCT($AL$7:$AL$55,IF(ISNUMBER(S$7:S$55),S$7:S$55,0))*'Plan-Annahmen'!$B$61 | T60: =-SUMPRODUCT($AL$7:$AL$55,IF(ISNUMBER(T$7:T$55),T$7:T$55,0))*'Plan-Annahmen'!$B$61 | U60: =-SUMPRODUCT($AL$7:$AL$55,IF(ISNUMBER(U$7:U$55),U$7:U$55,0))*'Plan-Annahmen'!$B$61 | ... AK60: =-SUMPRODUCT($AL$7:$AL$55,IF(ISNUMBER(AK$7:AK$55),AK$7:AK$55,0))*'Plan-Annahmen'!$B$61
C61: Laufende Kosten Basis nach Vorsteuer (€/Monat) — geht ins Raster | N61: =N57+N60 | O61: =O57+O60 | P61: =P57+P60 | Q61: =Q57+Q60 | R61: =R57+R60 | S61: =S57+S60 | T61: =T57+T60 | U61: =U57+U60 | ... AK61: =AK57+AK60
C63: UG-Block — wird je Szenario ab dem UG-Monat zugeschaltet
C64: Posten | D64: Betrag | E64: Einheit | F64: €/Monat bzw. € einmalig
C65: Steuerberater-Mehrkosten UG gegenüber EÜR | E65: laufend | F65: =3000/12-800/12
C66: Geschäftskonto (bei der UG zwingend) | E66: laufend | F66: =10
C67: IHK-Grundbeitrag (Gründerbefreiung gilt nicht) | E67: laufend | F67: =200/12
C68: Notar + Handelsregister (einmalig) | E68: einmalig | F68: =480
C69: Eröffnungsbilanz (einmalig) | E69: einmalig | F69: =500
C70: Stammkapital (Reserve, kein Aufwand) | E70: Reserve | F70: =1000
C71: UG-Mehrkosten laufend gesamt (€/Monat) | F71: =F65+F66+F67
C72: UG-Einmalkosten gesamt (€ im UG-Monat) | F72: =F68+F69
C73: UG-Reserve (€ im UG-Monat, bleibt Vermögen) | F73: =F70
A75: Warum der UG-Block separat steht: Der Zeitpunkt der UG-Gründung hängt an der Kundenzahl (rund 20 aktive Betriebe) und ist deshalb in jedem Szenario ein anderer Monat. Die Basiskosten oben gelten für alle Szenarien gleich; das Raster schaltet den UG-Block je Szenario ab dem Monat zu, in dem die Schwelle fällt. Beim Steuerberater wird nur die Differenz zugeschaltet (3.000 statt 800 €/Jahr), damit nichts doppelt zählt.
A77: Im Katalog A–H nicht enthalten und von mir ergänzt: Google-Play-Registrierung neben der Apple-Gebühr · Kontoführung des bei der UG zwingenden Geschäftskontos · Marketing-Sachkosten als Monatsvektor · die schaltbare Vorsteuer-Zeile. Als 'trifft nicht zu' geführt statt weggelassen: Werbebudget, Social-Tools, Cyber-Deckung, Rechtstexte-Abo, Objektspeicher, Resend Pro, Domainvarianten, Solidaritätszuschlag, Gewerbesteuer, IHK (Gründerbefreiung), individuelle Satzung. — NACHTRAG 17.09.2026 (Head of Finance): Die Vorsteuerzeile 60 rechnet seit heute je Kostenzeile ueber Spalte AL statt mit einer 60-%-Pauschale. Spalte AM sagt je Zeile, ob der eingetragene Betrag brutto oder netto gemeint ist — das ist die Angabe, an der die Pauschale gescheitert ist.

Sheet Plan-24M
A1: Plan-24M — Monatsraster September 2026 bis August 2028, drei Szenarien
A2: Kundenzahlen kommen vom Blatt 'Plan-Kunden', Kosten vom Blatt 'Plan-Kosten'. Umsatz: Gründerkunden × 29 € + Standardkunden × 49 €, abzüglich Ausfall und Kulanz. Die Spalten 'UG-Mehrkosten' und 'UG-Einmalkosten' schalten sich in dem Monat zu, in dem das jeweilige Szenario rund 20 aktive Betriebe erreicht — der UG-Monat steht in der Kopfzeile jedes Szenarios. Steuerrücklage: Grenzsteuersatz auf positive Monatsergebnisse, sofort zurückgelegt. Liquidität = kumulierter Cashflow minus gebundene Reserven; ihr Tiefpunkt ist der Betrag, den Sandy vorstrecken muss.
A6: Szenario: Vorsichtig | H6: Liquiditäts-Tiefpunkt in Monat: | K6: =MATCH(MIN(W8:W31),W8:W31,0) | M6: UG-Gründung in Monat: | O6: ='Plan-Kunden'!$S$32
A7: Monat | B7: Kalendermonat | C7: Neukunden | D7: Kunden aktiv | E7: Kunden @29€ | F7: Kunden @49€ | G7: Angebote | H7: Umsatz netto | I7: Ausfall + Kulanz | J7: Stripe-Gebühren | K7: KI-Kosten | L7: Empfehlungs-Anreiz | M7: Laufende Kosten Basis | N7: UG-Mehrkosten laufend | O7: Einmalkosten Basis | P7: UG-Einmalkosten | Q7: Kosten gesamt | R7: Ergebnis vor Steuer | S7: Steuerrücklage | T7: Cashflow nach Steuer | U7: kumuliert | V7: Reserven kumuliert | W7: Liquidität | X7: Ergebnis > 0? | Y7: Std. gesamt | Z7: über Dauerlinie? | AA7: Kunden ≥ B1 (30 Std.)? | AB7: Kunden ≥ B1 (25 Std.)? | AC7: Kunden ≥ B2? | AD7: Liquidität ≥ 0 nach Tiefpunkt? | AE7: UG aktiv?
A8: 1 | B8: ='Plan-Kunden'!B8 | C8: ='Plan-Kunden'!E8 | D8: ='Plan-Kunden'!K8 | E8: ='Plan-Kunden'!I8 | F8: ='Plan-Kunden'!J8 | G8: =D8*'Plan-Annahmen'!$B$21 | H8: =E8*'Plan-Annahmen'!$B$14+F8*'Plan-Annahmen'!$B$15 | I8: =H8*('Plan-Annahmen'!$B$52+'Plan-Annahmen'!$B$53) | J8: =E8*('Plan-Annahmen'!$B$14*'Plan-Annahmen'!$B$18+'Plan-Annahmen'!$B$19)+F8*('Plan-Annahmen'!$B$15*'Plan-Annahmen'!$B$18+'Plan-Annahmen'!$B$19) | K8: =G8*'Plan-Annahmen'!$B$17/100 | L8: ='Plan-Kunden'!D8*'Plan-Annahmen'!$B$15*'Plan-Annahmen'!$B$50 | M8: ='Plan-Kosten'!N$61 | N8: =IF(A8>=$O$6,'Plan-Kosten'!$F$71,0) | O8: ='Plan-Kosten'!N$58 | P8: =IF(A8=$O$6,'Plan-Kosten'!$F$72,0) | Q8: =I8+J8+K8+L8+M8+N8+O8+P8 | R8: =H8-Q8 | S8: =MAX(0,R8*'Plan-Annahmen'!$B$82) | T8: =R8-S8 | U8: =T8 | V8: ='Plan-Kosten'!N$59+IF(A8=$O$6,'Plan-Kosten'!$F$73,0) | W8: =U8-V8 | X8: =IF(R8>0,1,0) | Y8: ='Plan-Kunden'!P8 | Z8: ='Plan-Kunden'!Q8 | AA8: =IF(D8>='Plan-Phase B'!$C$22,1,0) | AB8: =IF(D8>='Plan-Phase B'!$D$22,1,0) | AC8: =IF(D8>='Plan-Phase B'!$E$22,1,0) | AD8: =IF(AND(W8>=0,A8>$K$6),1,0) | AE8: =IF(A8>=$O$6,1,0)
A9: 2 | B9: ='Plan-Kunden'!B9 | C9: ='Plan-Kunden'!E9 | D9: ='Plan-Kunden'!K9 | E9: ='Plan-Kunden'!I9 | F9: ='Plan-Kunden'!J9 | G9: =D9*'Plan-Annahmen'!$B$21 | H9: =E9*'Plan-Annahmen'!$B$14+F9*'Plan-Annahmen'!$B$15 | I9: =H9*('Plan-Annahmen'!$B$52+'Plan-Annahmen'!$B$53) | J9: =E9*('Plan-Annahmen'!$B$14*'Plan-Annahmen'!$B$18+'Plan-Annahmen'!$B$19)+F9*('Plan-Annahmen'!$B$15*'Plan-Annahmen'!$B$18+'Plan-Annahmen'!$B$19) | K9: =G9*'Plan-Annahmen'!$B$17/100 | L9: ='Plan-Kunden'!D9*'Plan-Annahmen'!$B$15*'Plan-Annahmen'!$B$50 | M9: ='Plan-Kosten'!O$61 | N9: =IF(A9>=$O$6,'Plan-Kosten'!$F$71,0) | O9: ='Plan-Kosten'!O$58 | P9: =IF(A9=$O$6,'Plan-Kosten'!$F$72,0) | Q9: =I9+J9+K9+L9+M9+N9+O9+P9 | R9: =H9-Q9 | S9: =MAX(0,R9*'Plan-Annahmen'!$B$82) | T9: =R9-S9 | U9: =U8+T9 | V9: =V8+'Plan-Kosten'!O$59+IF(A9=$O$6,'Plan-Kosten'!$F$73,0) | W9: =U9-V9 | X9: =IF(R9>0,1,0) | Y9: ='Plan-Kunden'!P9 | Z9: ='Plan-Kunden'!Q9 | AA9: =IF(D9>='Plan-Phase B'!$C$22,1,0) | AB9: =IF(D9>='Plan-Phase B'!$D$22,1,0) | AC9: =IF(D9>='Plan-Phase B'!$E$22,1,0) | AD9: =IF(AND(W9>=0,A9>$K$6),1,0) | AE9: =IF(A9>=$O$6,1,0)
A10: 3 | B10: ='Plan-Kunden'!B10 | C10: ='Plan-Kunden'!E10 | D10: ='Plan-Kunden'!K10 | E10: ='Plan-Kunden'!I10 | F10: ='Plan-Kunden'!J10 | G10: =D10*'Plan-Annahmen'!$B$21 | H10: =E10*'Plan-Annahmen'!$B$14+F10*'Plan-Annahmen'!$B$15 | I10: =H10*('Plan-Annahmen'!$B$52+'Plan-Annahmen'!$B$53) | J10: =E10*('Plan-Annahmen'!$B$14*'Plan-Annahmen'!$B$18+'Plan-Annahmen'!$B$19)+F10*('Plan-Annahmen'!$B$15*'Plan-Annahmen'!$B$18+'Plan-Annahmen'!$B$19) | K10: =G10*'Plan-Annahmen'!$B$17/100 | L10: ='Plan-Kunden'!D10*'Plan-Annahmen'!$B$15*'Plan-Annahmen'!$B$50 | M10: ='Plan-Kosten'!P$61 | N10: =IF(A10>=$O$6,'Plan-Kosten'!$F$71,0) | O10: ='Plan-Kosten'!P$58 | P10: =IF(A10=$O$6,'Plan-Kosten'!$F$72,0) | Q10: =I10+J10+K10+L10+M10+N10+O10+P10 | R10: =H10-Q10 | S10: =MAX(0,R10*'Plan-Annahmen'!$B$82) | T10: =R10-S10 | U10: =U9+T10 | V10: =V9+'Plan-Kosten'!P$59+IF(A10=$O$6,'Plan-Kosten'!$F$73,0) | W10: =U10-V10 | X10: =IF(R10>0,1,0) | Y10: ='Plan-Kunden'!P10 | Z10: ='Plan-Kunden'!Q10 | AA10: =IF(D10>='Plan-Phase B'!$C$22,1,0) | AB10: =IF(D10>='Plan-Phase B'!$D$22,1,0) | AC10: =IF(D10>='Plan-Phase B'!$E$22,1,0) | AD10: =IF(AND(W10>=0,A10>$K$6),1,0) | AE10: =IF(A10>=$O$6,1,0)
A11: 4 | B11: ='Plan-Kunden'!B11 | C11: ='Plan-Kunden'!E11 | D11: ='Plan-Kunden'!K11 | E11: ='Plan-Kunden'!I11 | F11: ='Plan-Kunden'!J11 | G11: =D11*'Plan-Annahmen'!$B$21 | H11: =E11*'Plan-Annahmen'!$B$14+F11*'Plan-Annahmen'!$B$15 | I11: =H11*('Plan-Annahmen'!$B$52+'Plan-Annahmen'!$B$53) | J11: =E11*('Plan-Annahmen'!$B$14*'Plan-Annahmen'!$B$18+'Plan-Annahmen'!$B$19)+F11*('Plan-Annahmen'!$B$15*'Plan-Annahmen'!$B$18+'Plan-Annahmen'!$B$19) | K11: =G11*'Plan-Annahmen'!$B$17/100 | L11: ='Plan-Kunden'!D11*'Plan-Annahmen'!$B$15*'Plan-Annahmen'!$B$50 | M11: ='Plan-Kosten'!Q$61 | N11: =IF(A11>=$O$6,'Plan-Kosten'!$F$71,0) | O11: ='Plan-Kosten'!Q$58 | P11: =IF(A11=$O$6,'Plan-Kosten'!$F$72,0) | Q11: =I11+J11+K11+L11+M11+N11+O11+P11 | R11: =H11-Q11 | S11: =MAX(0,R11*'Plan-Annahmen'!$B$82) | T11: =R11-S11 | U11: =U10+T11 | V11: =V10+'Plan-Kosten'!Q$59+IF(A11=$O$6,'Plan-Kosten'!$F$73,0) | W11: =U11-V11 | X11: =IF(R11>0,1,0) | Y11: ='Plan-Kunden'!P11 | Z11: ='Plan-Kunden'!Q11 | AA11: =IF(D11>='Plan-Phase B'!$C$22,1,0) | AB11: =IF(D11>='Plan-Phase B'!$D$22,1,0) | AC11: =IF(D11>='Plan-Phase B'!$E$22,1,0) | AD11: =IF(AND(W11>=0,A11>$K$6),1,0) | AE11: =IF(A11>=$O$6,1,0)
A12: 5 | B12: ='Plan-Kunden'!B12 | C12: ='Plan-Kunden'!E12 | D12: ='Plan-Kunden'!K12 | E12: ='Plan-Kunden'!I12 | F12: ='Plan-Kunden'!J12 | G12: =D12*'Plan-Annahmen'!$B$21 | H12: =E12*'Plan-Annahmen'!$B$14+F12*'Plan-Annahmen'!$B$15 | I12: =H12*('Plan-Annahmen'!$B$52+'Plan-Annahmen'!$B$53) | J12: =E12*('Plan-Annahmen'!$B$14*'Plan-Annahmen'!$B$18+'Plan-Annahmen'!$B$19)+F12*('Plan-Annahmen'!$B$15*'Plan-Annahmen'!$B$18+'Plan-Annahmen'!$B$19) | K12: =G12*'Plan-Annahmen'!$B$17/100 | L12: ='Plan-Kunden'!D12*'Plan-Annahmen'!$B$15*'Plan-Annahmen'!$B$50 | M12: ='Plan-Kosten'!R$61 | N12: =IF(A12>=$O$6,'Plan-Kosten'!$F$71,0) | O12: ='Plan-Kosten'!R$58 | P12: =IF(A12=$O$6,'Plan-Kosten'!$F$72,0) | Q12: =I12+J12+K12+L12+M12+N12+O12+P12 | R12: =H12-Q12 | S12: =MAX(0,R12*'Plan-Annahmen'!$B$82) | T12: =R12-S12 | U12: =U11+T12 | V12: =V11+'Plan-Kosten'!R$59+IF(A12=$O$6,'Plan-Kosten'!$F$73,0) | W12: =U12-V12 | X12: =IF(R12>0,1,0) | Y12: ='Plan-Kunden'!P12 | Z12: ='Plan-Kunden'!Q12 | AA12: =IF(D12>='Plan-Phase B'!$C$22,1,0) | AB12: =IF(D12>='Plan-Phase B'!$D$22,1,0) | AC12: =IF(D12>='Plan-Phase B'!$E$22,1,0) | AD12: =IF(AND(W12>=0,A12>$K$6),1,0) | AE12: =IF(A12>=$O$6,1,0)
A13: 6 | B13: ='Plan-Kunden'!B13 | C13: ='Plan-Kunden'!E13 | D13: ='Plan-Kunden'!K13 | E13: ='Plan-Kunden'!I13 | F13: ='Plan-Kunden'!J13 | G13: =D13*'Plan-Annahmen'!$B$21 | H13: =E13*'Plan-Annahmen'!$B$14+F13*'Plan-Annahmen'!$B$15 | I13: =H13*('Plan-Annahmen'!$B$52+'Plan-Annahmen'!$B$53) | J13: =E13*('Plan-Annahmen'!$B$14*'Plan-Annahmen'!$B$18+'Plan-Annahmen'!$B$19)+F13*('Plan-Annahmen'!$B$15*'Plan-Annahmen'!$B$18+'Plan-Annahmen'!$B$19) | K13: =G13*'Plan-Annahmen'!$B$17/100 | L13: ='Plan-Kunden'!D13*'Plan-Annahmen'!$B$15*'Plan-Annahmen'!$B$50 | M13: ='Plan-Kosten'!S$61 | N13: =IF(A13>=$O$6,'Plan-Kosten'!$F$71,0) | O13: ='Plan-Kosten'!S$58 | P13: =IF(A13=$O$6,'Plan-Kosten'!$F$72,0) | Q13: =I13+J13+K13+L13+M13+N13+O13+P13 | R13: =H13-Q13 | S13: =MAX(0,R13*'Plan-Annahmen'!$B$82) | T13: =R13-S13 | U13: =U12+T13 | V13: =V12+'Plan-Kosten'!S$59+IF(A13=$O$6,'Plan-Kosten'!$F$73,0) | W13: =U13-V13 | X13: =IF(R13>0,1,0) | Y13: ='Plan-Kunden'!P13 | Z13: ='Plan-Kunden'!Q13 | AA13: =IF(D13>='Plan-Phase B'!$C$22,1,0) | AB13: =IF(D13>='Plan-Phase B'!$D$22,1,0) | AC13: =IF(D13>='Plan-Phase B'!$E$22,1,0) | AD13: =IF(AND(W13>=0,A13>$K$6),1,0) | AE13: =IF(A13>=$O$6,1,0)
A14: 7 | B14: ='Plan-Kunden'!B14 | C14: ='Plan-Kunden'!E14 | D14: ='Plan-Kunden'!K14 | E14: ='Plan-Kunden'!I14 | F14: ='Plan-Kunden'!J14 | G14: =D14*'Plan-Annahmen'!$B$21 | H14: =E14*'Plan-Annahmen'!$B$14+F14*'Plan-Annahmen'!$B$15 | I14: =H14*('Plan-Annahmen'!$B$52+'Plan-Annahmen'!$B$53) | J14: =E14*('Plan-Annahmen'!$B$14*'Plan-Annahmen'!$B$18+'Plan-Annahmen'!$B$19)+F14*('Plan-Annahmen'!$B$15*'Plan-Annahmen'!$B$18+'Plan-Annahmen'!$B$19) | K14: =G14*'Plan-Annahmen'!$B$17/100 | L14: ='Plan-Kunden'!D14*'Plan-Annahmen'!$B$15*'Plan-Annahmen'!$B$50 | M14: ='Plan-Kosten'!T$61 | N14: =IF(A14>=$O$6,'Plan-Kosten'!$F$71,0) | O14: ='Plan-Kosten'!T$58 | P14: =IF(A14=$O$6,'Plan-Kosten'!$F$72,0) | Q14: =I14+J14+K14+L14+M14+N14+O14+P14 | R14: =H14-Q14 | S14: =MAX(0,R14*'Plan-Annahmen'!$B$82) | T14: =R14-S14 | U14: =U13+T14 | V14: =V13+'Plan-Kosten'!T$59+IF(A14=$O$6,'Plan-Kosten'!$F$73,0) | W14: =U14-V14 | X14: =IF(R14>0,1,0) | Y14: ='Plan-Kunden'!P14 | Z14: ='Plan-Kunden'!Q14 | AA14: =IF(D14>='Plan-Phase B'!$C$22,1,0) | AB14: =IF(D14>='Plan-Phase B'!$D$22,1,0) | AC14: =IF(D14>='Plan-Phase B'!$E$22,1,0) | AD14: =IF(AND(W14>=0,A14>$K$6),1,0) | AE14: =IF(A14>=$O$6,1,0)
A15: 8 | B15: ='Plan-Kunden'!B15 | C15: ='Plan-Kunden'!E15 | D15: ='Plan-Kunden'!K15 | E15: ='Plan-Kunden'!I15 | F15: ='Plan-Kunden'!J15 | G15: =D15*'Plan-Annahmen'!$B$21 | H15: =E15*'Plan-Annahmen'!$B$14+F15*'Plan-Annahmen'!$B$15 | I15: =H15*('Plan-Annahmen'!$B$52+'Plan-Annahmen'!$B$53) | J15: =E15*('Plan-Annahmen'!$B$14*'Plan-Annahmen'!$B$18+'Plan-Annahmen'!$B$19)+F15*('Plan-Annahmen'!$B$15*'Plan-Annahmen'!$B$18+'Plan-Annahmen'!$B$19) | K15: =G15*'Plan-Annahmen'!$B$17/100 | L15: ='Plan-Kunden'!D15*'Plan-Annahmen'!$B$15*'Plan-Annahmen'!$B$50 | M15: ='Plan-Kosten'!U$61 | N15: =IF(A15>=$O$6,'Plan-Kosten'!$F$71,0) | O15: ='Plan-Kosten'!U$58 | P15: =IF(A15=$O$6,'Plan-Kosten'!$F$72,0) | Q15: =I15+J15+K15+L15+M15+N15+O15+P15 | R15: =H15-Q15 | S15: =MAX(0,R15*'Plan-Annahmen'!$B$82) | T15: =R15-S15 | U15: =U14+T15 | V15: =V14+'Plan-Kosten'!U$59+IF(A15=$O$6,'Plan-Kosten'!$F$73,0) | W15: =U15-V15 | X15: =IF(R15>0,1,0) | Y15: ='Plan-Kunden'!P15 | Z15: ='Plan-Kunden'!Q15 | AA15: =IF(D15>='Plan-Phase B'!$C$22,1,0) | AB15: =IF(D15>='Plan-Phase B'!$D$22,1,0) | AC15: =IF(D15>='Plan-Phase B'!$E$22,1,0) | AD15: =IF(AND(W15>=0,A15>$K$6),1,0) | AE15: =IF(A15>=$O$6,1,0)
A16: 9 | B16: ='Plan-Kunden'!B16 | C16: ='Plan-Kunden'!E16 | D16: ='Plan-Kunden'!K16 | E16: ='Plan-Kunden'!I16 | F16: ='Plan-Kunden'!J16 | G16: =D16*'Plan-Annahmen'!$B$21 | H16: =E16*'Plan-Annahmen'!$B$14+F16*'Plan-Annahmen'!$B$15 | I16: =H16*('Plan-Annahmen'!$B$52+'Plan-Annahmen'!$B$53) | J16: =E16*('Plan-Annahmen'!$B$14*'Plan-Annahmen'!$B$18+'Plan-Annahmen'!$B$19)+F16*('Plan-Annahmen'!$B$15*'Plan-Annahmen'!$B$18+'Plan-Annahmen'!$B$19) | K16: =G16*'Plan-Annahmen'!$B$17/100 | L16: ='Plan-Kunden'!D16*'Plan-Annahmen'!$B$15*'Plan-Annahmen'!$B$50 | M16: ='Plan-Kosten'!V$61 | N16: =IF(A16>=$O$6,'Plan-Kosten'!$F$71,0) | O16: ='Plan-Kosten'!V$58 | P16: =IF(A16=$O$6,'Plan-Kosten'!$F$72,0) | Q16: =I16+J16+K16+L16+M16+N16+O16+P16 | R16: =H16-Q16 | S16: =MAX(0,R16*'Plan-Annahmen'!$B$82) | T16: =R16-S16 | U16: =U15+T16 | V16: =V15+'Plan-Kosten'!V$59+IF(A16=$O$6,'Plan-Kosten'!$F$73,0) | W16: =U16-V16 | X16: =IF(R16>0,1,0) | Y16: ='Plan-Kunden'!P16 | Z16: ='Plan-Kunden'!Q16 | AA16: =IF(D16>='Plan-Phase B'!$C$22,1,0) | AB16: =IF(D16>='Plan-Phase B'!$D$22,1,0) | AC16: =IF(D16>='Plan-Phase B'!$E$22,1,0) | AD16: =IF(AND(W16>=0,A16>$K$6),1,0) | AE16: =IF(A16>=$O$6,1,0)
A17: 10 | B17: ='Plan-Kunden'!B17 | C17: ='Plan-Kunden'!E17 | D17: ='Plan-Kunden'!K17 | E17: ='Plan-Kunden'!I17 | F17: ='Plan-Kunden'!J17 | G17: =D17*'Plan-Annahmen'!$B$21 | H17: =E17*'Plan-Annahmen'!$B$14+F17*'Plan-Annahmen'!$B$15 | I17: =H17*('Plan-Annahmen'!$B$52+'Plan-Annahmen'!$B$53) | J17: =E17*('Plan-Annahmen'!$B$14*'Plan-Annahmen'!$B$18+'Plan-Annahmen'!$B$19)+F17*('Plan-Annahmen'!$B$15*'Plan-Annahmen'!$B$18+'Plan-Annahmen'!$B$19) | K17: =G17*'Plan-Annahmen'!$B$17/100 | L17: ='Plan-Kunden'!D17*'Plan-Annahmen'!$B$15*'Plan-Annahmen'!$B$50 | M17: ='Plan-Kosten'!W$61 | N17: =IF(A17>=$O$6,'Plan-Kosten'!$F$71,0) | O17: ='Plan-Kosten'!W$58 | P17: =IF(A17=$O$6,'Plan-Kosten'!$F$72,0) | Q17: =I17+J17+K17+L17+M17+N17+O17+P17 | R17: =H17-Q17 | S17: =MAX(0,R17*'Plan-Annahmen'!$B$82) | T17: =R17-S17 | U17: =U16+T17 | V17: =V16+'Plan-Kosten'!W$59+IF(A17=$O$6,'Plan-Kosten'!$F$73,0) | W17: =U17-V17 | X17: =IF(R17>0,1,0) | Y17: ='Plan-Kunden'!P17 | Z17: ='Plan-Kunden'!Q17 | AA17: =IF(D17>='Plan-Phase B'!$C$22,1,0) | AB17: =IF(D17>='Plan-Phase B'!$D$22,1,0) | AC17: =IF(D17>='Plan-Phase B'!$E$22,1,0) | AD17: =IF(AND(W17>=0,A17>$K$6),1,0) | AE17: =IF(A17>=$O$6,1,0)
A18: 11 | B18: ='Plan-Kunden'!B18 | C18: ='Plan-Kunden'!E18 | D18: ='Plan-Kunden'!K18 | E18: ='Plan-Kunden'!I18 | F18: ='Plan-Kunden'!J18 | G18: =D18*'Plan-Annahmen'!$B$21 | H18: =E18*'Plan-Annahmen'!$B$14+F18*'Plan-Annahmen'!$B$15 | I18: =H18*('Plan-Annahmen'!$B$52+'Plan-Annahmen'!$B$53) | J18: =E18*('Plan-Annahmen'!$B$14*'Plan-Annahmen'!$B$18+'Plan-Annahmen'!$B$19)+F18*('Plan-Annahmen'!$B$15*'Plan-Annahmen'!$B$18+'Plan-Annahmen'!$B$19) | K18: =G18*'Plan-Annahmen'!$B$17/100 | L18: ='Plan-Kunden'!D18*'Plan-Annahmen'!$B$15*'Plan-Annahmen'!$B$50 | M18: ='Plan-Kosten'!X$61 | N18: =IF(A18>=$O$6,'Plan-Kosten'!$F$71,0) | O18: ='Plan-Kosten'!X$58 | P18: =IF(A18=$O$6,'Plan-Kosten'!$F$72,0) | Q18: =I18+J18+K18+L18+M18+N18+O18+P18 | R18: =H18-Q18 | S18: =MAX(0,R18*'Plan-Annahmen'!$B$82) | T18: =R18-S18 | U18: =U17+T18 | V18: =V17+'Plan-Kosten'!X$59+IF(A18=$O$6,'Plan-Kosten'!$F$73,0) | W18: =U18-V18 | X18: =IF(R18>0,1,0) | Y18: ='Plan-Kunden'!P18 | Z18: ='Plan-Kunden'!Q18 | AA18: =IF(D18>='Plan-Phase B'!$C$22,1,0) | AB18: =IF(D18>='Plan-Phase B'!$D$22,1,0) | AC18: =IF(D18>='Plan-Phase B'!$E$22,1,0) | AD18: =IF(AND(W18>=0,A18>$K$6),1,0) | AE18: =IF(A18>=$O$6,1,0)
A19: 12 | B19: ='Plan-Kunden'!B19 | C19: ='Plan-Kunden'!E19 | D19: ='Plan-Kunden'!K19 | E19: ='Plan-Kunden'!I19 | F19: ='Plan-Kunden'!J19 | G19: =D19*'Plan-Annahmen'!$B$21 | H19: =E19*'Plan-Annahmen'!$B$14+F19*'Plan-Annahmen'!$B$15 | I19: =H19*('Plan-Annahmen'!$B$52+'Plan-Annahmen'!$B$53) | J19: =E19*('Plan-Annahmen'!$B$14*'Plan-Annahmen'!$B$18+'Plan-Annahmen'!$B$19)+F19*('Plan-Annahmen'!$B$15*'Plan-Annahmen'!$B$18+'Plan-Annahmen'!$B$19) | K19: =G19*'Plan-Annahmen'!$B$17/100 | L19: ='Plan-Kunden'!D19*'Plan-Annahmen'!$B$15*'Plan-Annahmen'!$B$50 | M19: ='Plan-Kosten'!Y$61 | N19: =IF(A19>=$O$6,'Plan-Kosten'!$F$71,0) | O19: ='Plan-Kosten'!Y$58 | P19: =IF(A19=$O$6,'Plan-Kosten'!$F$72,0) | Q19: =I19+J19+K19+L19+M19+N19+O19+P19 | R19: =H19-Q19 | S19: =MAX(0,R19*'Plan-Annahmen'!$B$82) | T19: =R19-S19 | U19: =U18+T19 | V19: =V18+'Plan-Kosten'!Y$59+IF(A19=$O$6,'Plan-Kosten'!$F$73,0) | W19: =U19-V19 | X19: =IF(R19>0,1,0) | Y19: ='Plan-Kunden'!P19 | Z19: ='Plan-Kunden'!Q19 | AA19: =IF(D19>='Plan-Phase B'!$C$22,1,0) | AB19: =IF(D19>='Plan-Phase B'!$D$22,1,0) | AC19: =IF(D19>='Plan-Phase B'!$E$22,1,0) | AD19: =IF(AND(W19>=0,A19>$K$6),1,0) | AE19: =IF(A19>=$O$6,1,0)
A20: 13 | B20: ='Plan-Kunden'!B20 | C20: ='Plan-Kunden'!E20 | D20: ='Plan-Kunden'!K20 | E20: ='Plan-Kunden'!I20 | F20: ='Plan-Kunden'!J20 | G20: =D20*'Plan-Annahmen'!$B$21 | H20: =E20*'Plan-Annahmen'!$B$14+F20*'Plan-Annahmen'!$B$15 | I20: =H20*('Plan-Annahmen'!$B$52+'Plan-Annahmen'!$B$53) | J20: =E20*('Plan-Annahmen'!$B$14*'Plan-Annahmen'!$B$18+'Plan-Annahmen'!$B$19)+F20*('Plan-Annahmen'!$B$15*'Plan-Annahmen'!$B$18+'Plan-Annahmen'!$B$19) | K20: =G20*'Plan-Annahmen'!$B$17/100 | L20: ='Plan-Kunden'!D20*'Plan-Annahmen'!$B$15*'Plan-Annahmen'!$B$50 | M20: ='Plan-Kosten'!Z$61 | N20: =IF(A20>=$O$6,'Plan-Kosten'!$F$71,0) | O20: ='Plan-Kosten'!Z$58 | P20: =IF(A20=$O$6,'Plan-Kosten'!$F$72,0) | Q20: =I20+J20+K20+L20+M20+N20+O20+P20 | R20: =H20-Q20 | S20: =MAX(0,R20*'Plan-Annahmen'!$B$82) | T20: =R20-S20 | U20: =U19+T20 | V20: =V19+'Plan-Kosten'!Z$59+IF(A20=$O$6,'Plan-Kosten'!$F$73,0) | W20: =U20-V20 | X20: =IF(R20>0,1,0) | Y20: ='Plan-Kunden'!P20 | Z20: ='Plan-Kunden'!Q20 | AA20: =IF(D20>='Plan-Phase B'!$C$22,1,0) | AB20: =IF(D20>='Plan-Phase B'!$D$22,1,0) | AC20: =IF(D20>='Plan-Phase B'!$E$22,1,0) | AD20: =IF(AND(W20>=0,A20>$K$6),1,0) | AE20: =IF(A20>=$O$6,1,0)
A21: 14 | B21: ='Plan-Kunden'!B21 | C21: ='Plan-Kunden'!E21 | D21: ='Plan-Kunden'!K21 | E21: ='Plan-Kunden'!I21 | F21: ='Plan-Kunden'!J21 | G21: =D21*'Plan-Annahmen'!$B$21 | H21: =E21*'Plan-Annahmen'!$B$14+F21*'Plan-Annahmen'!$B$15 | I21: =H21*('Plan-Annahmen'!$B$52+'Plan-Annahmen'!$B$53) | J21: =E21*('Plan-Annahmen'!$B$14*'Plan-Annahmen'!$B$18+'Plan-Annahmen'!$B$19)+F21*('Plan-Annahmen'!$B$15*'Plan-Annahmen'!$B$18+'Plan-Annahmen'!$B$19) | K21: =G21*'Plan-Annahmen'!$B$17/100 | L21: ='Plan-Kunden'!D21*'Plan-Annahmen'!$B$15*'Plan-Annahmen'!$B$50 | M21: ='Plan-Kosten'!AA$61 | N21: =IF(A21>=$O$6,'Plan-Kosten'!$F$71,0) | O21: ='Plan-Kosten'!AA$58 | P21: =IF(A21=$O$6,'Plan-Kosten'!$F$72,0) | Q21: =I21+J21+K21+L21+M21+N21+O21+P21 | R21: =H21-Q21 | S21: =MAX(0,R21*'Plan-Annahmen'!$B$82) | T21: =R21-S21 | U21: =U20+T21 | V21: =V20+'Plan-Kosten'!AA$59+IF(A21=$O$6,'Plan-Kosten'!$F$73,0) | W21: =U21-V21 | X21: =IF(R21>0,1,0) | Y21: ='Plan-Kunden'!P21 | Z21: ='Plan-Kunden'!Q21 | AA21: =IF(D21>='Plan-Phase B'!$C$22,1,0) | AB21: =IF(D21>='Plan-Phase B'!$D$22,1,0) | AC21: =IF(D21>='Plan-Phase B'!$E$22,1,0) | AD21: =IF(AND(W21>=0,A21>$K$6),1,0) | AE21: =IF(A21>=$O$6,1,0)
A22: 15 | B22: ='Plan-Kunden'!B22 | C22: ='Plan-Kunden'!E22 | D22: ='Plan-Kunden'!K22 | E22: ='Plan-Kunden'!I22 | F22: ='Plan-Kunden'!J22 | G22: =D22*'Plan-Annahmen'!$B$21 | H22: =E22*'Plan-Annahmen'!$B$14+F22*'Plan-Annahmen'!$B$15 | I22: =H22*('Plan-Annahmen'!$B$52+'Plan-Annahmen'!$B$53) | J22: =E22*('Plan-Annahmen'!$B$14*'Plan-Annahmen'!$B$18+'Plan-Annahmen'!$B$19)+F22*('Plan-Annahmen'!$B$15*'Plan-Annahmen'!$B$18+'Plan-Annahmen'!$B$19) | K22: =G22*'Plan-Annahmen'!$B$17/100 | L22: ='Plan-Kunden'!D22*'Plan-Annahmen'!$B$15*'Plan-Annahmen'!$B$50 | M22: ='Plan-Kosten'!AB$61 | N22: =IF(A22>=$O$6,'Plan-Kosten'!$F$71,0) | O22: ='Plan-Kosten'!AB$58 | P22: =IF(A22=$O$6,'Plan-Kosten'!$F$72,0) | Q22: =I22+J22+K22+L22+M22+N22+O22+P22 | R22: =H22-Q22 | S22: =MAX(0,R22*'Plan-Annahmen'!$B$82) | T22: =R22-S22 | U22: =U21+T22 | V22: =V21+'Plan-Kosten'!AB$59+IF(A22=$O$6,'Plan-Kosten'!$F$73,0) | W22: =U22-V22 | X22: =IF(R22>0,1,0) | Y22: ='Plan-Kunden'!P22 | Z22: ='Plan-Kunden'!Q22 | AA22: =IF(D22>='Plan-Phase B'!$C$22,1,0) | AB22: =IF(D22>='Plan-Phase B'!$D$22,1,0) | AC22: =IF(D22>='Plan-Phase B'!$E$22,1,0) | AD22: =IF(AND(W22>=0,A22>$K$6),1,0) | AE22: =IF(A22>=$O$6,1,0)
A23: 16 | B23: ='Plan-Kunden'!B23 | C23: ='Plan-Kunden'!E23 | D23: ='Plan-Kunden'!K23 | E23: ='Plan-Kunden'!I23 | F23: ='Plan-Kunden'!J23 | G23: =D23*'Plan-Annahmen'!$B$21 | H23: =E23*'Plan-Annahmen'!$B$14+F23*'Plan-Annahmen'!$B$15 | I23: =H23*('Plan-Annahmen'!$B$52+'Plan-Annahmen'!$B$53) | J23: =E23*('Plan-Annahmen'!$B$14*'Plan-Annahmen'!$B$18+'Plan-Annahmen'!$B$19)+F23*('Plan-Annahmen'!$B$15*'Plan-Annahmen'!$B$18+'Plan-Annahmen'!$B$19) | K23: =G23*'Plan-Annahmen'!$B$17/100 | L23: ='Plan-Kunden'!D23*'Plan-Annahmen'!$B$15*'Plan-Annahmen'!$B$50 | M23: ='Plan-Kosten'!AC$61 | N23: =IF(A23>=$O$6,'Plan-Kosten'!$F$71,0) | O23: ='Plan-Kosten'!AC$58 | P23: =IF(A23=$O$6,'Plan-Kosten'!$F$72,0) | Q23: =I23+J23+K23+L23+M23+N23+O23+P23 | R23: =H23-Q23 | S23: =MAX(0,R23*'Plan-Annahmen'!$B$82) | T23: =R23-S23 | U23: =U22+T23 | V23: =V22+'Plan-Kosten'!AC$59+IF(A23=$O$6,'Plan-Kosten'!$F$73,0) | W23: =U23-V23 | X23: =IF(R23>0,1,0) | Y23: ='Plan-Kunden'!P23 | Z23: ='Plan-Kunden'!Q23 | AA23: =IF(D23>='Plan-Phase B'!$C$22,1,0) | AB23: =IF(D23>='Plan-Phase B'!$D$22,1,0) | AC23: =IF(D23>='Plan-Phase B'!$E$22,1,0) | AD23: =IF(AND(W23>=0,A23>$K$6),1,0) | AE23: =IF(A23>=$O$6,1,0)
A24: 17 | B24: ='Plan-Kunden'!B24 | C24: ='Plan-Kunden'!E24 | D24: ='Plan-Kunden'!K24 | E24: ='Plan-Kunden'!I24 | F24: ='Plan-Kunden'!J24 | G24: =D24*'Plan-Annahmen'!$B$21 | H24: =E24*'Plan-Annahmen'!$B$14+F24*'Plan-Annahmen'!$B$15 | I24: =H24*('Plan-Annahmen'!$B$52+'Plan-Annahmen'!$B$53) | J24: =E24*('Plan-Annahmen'!$B$14*'Plan-Annahmen'!$B$18+'Plan-Annahmen'!$B$19)+F24*('Plan-Annahmen'!$B$15*'Plan-Annahmen'!$B$18+'Plan-Annahmen'!$B$19) | K24: =G24*'Plan-Annahmen'!$B$17/100 | L24: ='Plan-Kunden'!D24*'Plan-Annahmen'!$B$15*'Plan-Annahmen'!$B$50 | M24: ='Plan-Kosten'!AD$61 | N24: =IF(A24>=$O$6,'Plan-Kosten'!$F$71,0) | O24: ='Plan-Kosten'!AD$58 | P24: =IF(A24=$O$6,'Plan-Kosten'!$F$72,0) | Q24: =I24+J24+K24+L24+M24+N24+O24+P24 | R24: =H24-Q24 | S24: =MAX(0,R24*'Plan-Annahmen'!$B$82) | T24: =R24-S24 | U24: =U23+T24 | V24: =V23+'Plan-Kosten'!AD$59+IF(A24=$O$6,'Plan-Kosten'!$F$73,0) | W24: =U24-V24 | X24: =IF(R24>0,1,0) | Y24: ='Plan-Kunden'!P24 | Z24: ='Plan-Kunden'!Q24 | AA24: =IF(D24>='Plan-Phase B'!$C$22,1,0) | AB24: =IF(D24>='Plan-Phase B'!$D$22,1,0) | AC24: =IF(D24>='Plan-Phase B'!$E$22,1,0) | AD24: =IF(AND(W24>=0,A24>$K$6),1,0) | AE24: =IF(A24>=$O$6,1,0)
A25: 18 | B25: ='Plan-Kunden'!B25 | C25: ='Plan-Kunden'!E25 | D25: ='Plan-Kunden'!K25 | E25: ='Plan-Kunden'!I25 | F25: ='Plan-Kunden'!J25 | G25: =D25*'Plan-Annahmen'!$B$21 | H25: =E25*'Plan-Annahmen'!$B$14+F25*'Plan-Annahmen'!$B$15 | I25: =H25*('Plan-Annahmen'!$B$52+'Plan-Annahmen'!$B$53) | J25: =E25*('Plan-Annahmen'!$B$14*'Plan-Annahmen'!$B$18+'Plan-Annahmen'!$B$19)+F25*('Plan-Annahmen'!$B$15*'Plan-Annahmen'!$B$18+'Plan-Annahmen'!$B$19) | K25: =G25*'Plan-Annahmen'!$B$17/100 | L25: ='Plan-Kunden'!D25*'Plan-Annahmen'!$B$15*'Plan-Annahmen'!$B$50 | M25: ='Plan-Kosten'!AE$61 | N25: =IF(A25>=$O$6,'Plan-Kosten'!$F$71,0) | O25: ='Plan-Kosten'!AE$58 | P25: =IF(A25=$O$6,'Plan-Kosten'!$F$72,0) | Q25: =I25+J25+K25+L25+M25+N25+O25+P25 | R25: =H25-Q25 | S25: =MAX(0,R25*'Plan-Annahmen'!$B$82) | T25: =R25-S25 | U25: =U24+T25 | V25: =V24+'Plan-Kosten'!AE$59+IF(A25=$O$6,'Plan-Kosten'!$F$73,0) | W25: =U25-V25 | X25: =IF(R25>0,1,0) | Y25: ='Plan-Kunden'!P25 | Z25: ='Plan-Kunden'!Q25 | AA25: =IF(D25>='Plan-Phase B'!$C$22,1,0) | AB25: =IF(D25>='Plan-Phase B'!$D$22,1,0) | AC25: =IF(D25>='Plan-Phase B'!$E$22,1,0) | AD25: =IF(AND(W25>=0,A25>$K$6),1,0) | AE25: =IF(A25>=$O$6,1,0)
A26: 19 | B26: ='Plan-Kunden'!B26 | C26: ='Plan-Kunden'!E26 | D26: ='Plan-Kunden'!K26 | E26: ='Plan-Kunden'!I26 | F26: ='Plan-Kunden'!J26 | G26: =D26*'Plan-Annahmen'!$B$21 | H26: =E26*'Plan-Annahmen'!$B$14+F26*'Plan-Annahmen'!$B$15 | I26: =H26*('Plan-Annahmen'!$B$52+'Plan-Annahmen'!$B$53) | J26: =E26*('Plan-Annahmen'!$B$14*'Plan-Annahmen'!$B$18+'Plan-Annahmen'!$B$19)+F26*('Plan-Annahmen'!$B$15*'Plan-Annahmen'!$B$18+'Plan-Annahmen'!$B$19) | K26: =G26*'Plan-Annahmen'!$B$17/100 | L26: ='Plan-Kunden'!D26*'Plan-Annahmen'!$B$15*'Plan-Annahmen'!$B$50 | M26: ='Plan-Kosten'!AF$61 | N26: =IF(A26>=$O$6,'Plan-Kosten'!$F$71,0) | O26: ='Plan-Kosten'!AF$58 | P26: =IF(A26=$O$6,'Plan-Kosten'!$F$72,0) | Q26: =I26+J26+K26+L26+M26+N26+O26+P26 | R26: =H26-Q26 | S26: =MAX(0,R26*'Plan-Annahmen'!$B$82) | T26: =R26-S26 | U26: =U25+T26 | V26: =V25+'Plan-Kosten'!AF$59+IF(A26=$O$6,'Plan-Kosten'!$F$73,0) | W26: =U26-V26 | X26: =IF(R26>0,1,0) | Y26: ='Plan-Kunden'!P26 | Z26: ='Plan-Kunden'!Q26 | AA26: =IF(D26>='Plan-Phase B'!$C$22,1,0) | AB26: =IF(D26>='Plan-Phase B'!$D$22,1,0) | AC26: =IF(D26>='Plan-Phase B'!$E$22,1,0) | AD26: =IF(AND(W26>=0,A26>$K$6),1,0) | AE26: =IF(A26>=$O$6,1,0)
A27: 20 | B27: ='Plan-Kunden'!B27 | C27: ='Plan-Kunden'!E27 | D27: ='Plan-Kunden'!K27 | E27: ='Plan-Kunden'!I27 | F27: ='Plan-Kunden'!J27 | G27: =D27*'Plan-Annahmen'!$B$21 | H27: =E27*'Plan-Annahmen'!$B$14+F27*'Plan-Annahmen'!$B$15 | I27: =H27*('Plan-Annahmen'!$B$52+'Plan-Annahmen'!$B$53) | J27: =E27*('Plan-Annahmen'!$B$14*'Plan-Annahmen'!$B$18+'Plan-Annahmen'!$B$19)+F27*('Plan-Annahmen'!$B$15*'Plan-Annahmen'!$B$18+'Plan-Annahmen'!$B$19) | K27: =G27*'Plan-Annahmen'!$B$17/100 | L27: ='Plan-Kunden'!D27*'Plan-Annahmen'!$B$15*'Plan-Annahmen'!$B$50 | M27: ='Plan-Kosten'!AG$61 | N27: =IF(A27>=$O$6,'Plan-Kosten'!$F$71,0) | O27: ='Plan-Kosten'!AG$58 | P27: =IF(A27=$O$6,'Plan-Kosten'!$F$72,0) | Q27: =I27+J27+K27+L27+M27+N27+O27+P27 | R27: =H27-Q27 | S27: =MAX(0,R27*'Plan-Annahmen'!$B$82) | T27: =R27-S27 | U27: =U26+T27 | V27: =V26+'Plan-Kosten'!AG$59+IF(A27=$O$6,'Plan-Kosten'!$F$73,0) | W27: =U27-V27 | X27: =IF(R27>0,1,0) | Y27: ='Plan-Kunden'!P27 | Z27: ='Plan-Kunden'!Q27 | AA27: =IF(D27>='Plan-Phase B'!$C$22,1,0) | AB27: =IF(D27>='Plan-Phase B'!$D$22,1,0) | AC27: =IF(D27>='Plan-Phase B'!$E$22,1,0) | AD27: =IF(AND(W27>=0,A27>$K$6),1,0) | AE27: =IF(A27>=$O$6,1,0)
A28: 21 | B28: ='Plan-Kunden'!B28 | C28: ='Plan-Kunden'!E28 | D28: ='Plan-Kunden'!K28 | E28: ='Plan-Kunden'!I28 | F28: ='Plan-Kunden'!J28 | G28: =D28*'Plan-Annahmen'!$B$21 | H28: =E28*'Plan-Annahmen'!$B$14+F28*'Plan-Annahmen'!$B$15 | I28: =H28*('Plan-Annahmen'!$B$52+'Plan-Annahmen'!$B$53) | J28: =E28*('Plan-Annahmen'!$B$14*'Plan-Annahmen'!$B$18+'Plan-Annahmen'!$B$19)+F28*('Plan-Annahmen'!$B$15*'Plan-Annahmen'!$B$18+'Plan-Annahmen'!$B$19) | K28: =G28*'Plan-Annahmen'!$B$17/100 | L28: ='Plan-Kunden'!D28*'Plan-Annahmen'!$B$15*'Plan-Annahmen'!$B$50 | M28: ='Plan-Kosten'!AH$61 | N28: =IF(A28>=$O$6,'Plan-Kosten'!$F$71,0) | O28: ='Plan-Kosten'!AH$58 | P28: =IF(A28=$O$6,'Plan-Kosten'!$F$72,0) | Q28: =I28+J28+K28+L28+M28+N28+O28+P28 | R28: =H28-Q28 | S28: =MAX(0,R28*'Plan-Annahmen'!$B$82) | T28: =R28-S28 | U28: =U27+T28 | V28: =V27+'Plan-Kosten'!AH$59+IF(A28=$O$6,'Plan-Kosten'!$F$73,0) | W28: =U28-V28 | X28: =IF(R28>0,1,0) | Y28: ='Plan-Kunden'!P28 | Z28: ='Plan-Kunden'!Q28 | AA28: =IF(D28>='Plan-Phase B'!$C$22,1,0) | AB28: =IF(D28>='Plan-Phase B'!$D$22,1,0) | AC28: =IF(D28>='Plan-Phase B'!$E$22,1,0) | AD28: =IF(AND(W28>=0,A28>$K$6),1,0) | AE28: =IF(A28>=$O$6,1,0)
A29: 22 | B29: ='Plan-Kunden'!B29 | C29: ='Plan-Kunden'!E29 | D29: ='Plan-Kunden'!K29 | E29: ='Plan-Kunden'!I29 | F29: ='Plan-Kunden'!J29 | G29: =D29*'Plan-Annahmen'!$B$21 | H29: =E29*'Plan-Annahmen'!$B$14+F29*'Plan-Annahmen'!$B$15 | I29: =H29*('Plan-Annahmen'!$B$52+'Plan-Annahmen'!$B$53) | J29: =E29*('Plan-Annahmen'!$B$14*'Plan-Annahmen'!$B$18+'Plan-Annahmen'!$B$19)+F29*('Plan-Annahmen'!$B$15*'Plan-Annahmen'!$B$18+'Plan-Annahmen'!$B$19) | K29: =G29*'Plan-Annahmen'!$B$17/100 | L29: ='Plan-Kunden'!D29*'Plan-Annahmen'!$B$15*'Plan-Annahmen'!$B$50 | M29: ='Plan-Kosten'!AI$61 | N29: =IF(A29>=$O$6,'Plan-Kosten'!$F$71,0) | O29: ='Plan-Kosten'!AI$58 | P29: =IF(A29=$O$6,'Plan-Kosten'!$F$72,0) | Q29: =I29+J29+K29+L29+M29+N29+O29+P29 | R29: =H29-Q29 | S29: =MAX(0,R29*'Plan-Annahmen'!$B$82) | T29: =R29-S29 | U29: =U28+T29 | V29: =V28+'Plan-Kosten'!AI$59+IF(A29=$O$6,'Plan-Kosten'!$F$73,0) | W29: =U29-V29 | X29: =IF(R29>0,1,0) | Y29: ='Plan-Kunden'!P29 | Z29: ='Plan-Kunden'!Q29 | AA29: =IF(D29>='Plan-Phase B'!$C$22,1,0) | AB29: =IF(D29>='Plan-Phase B'!$D$22,1,0) | AC29: =IF(D29>='Plan-Phase B'!$E$22,1,0) | AD29: =IF(AND(W29>=0,A29>$K$6),1,0) | AE29: =IF(A29>=$O$6,1,0)
A30: 23 | B30: ='Plan-Kunden'!B30 | C30: ='Plan-Kunden'!E30 | D30: ='Plan-Kunden'!K30 | E30: ='Plan-Kunden'!I30 | F30: ='Plan-Kunden'!J30 | G30: =D30*'Plan-Annahmen'!$B$21 | H30: =E30*'Plan-Annahmen'!$B$14+F30*'Plan-Annahmen'!$B$15 | I30: =H30*('Plan-Annahmen'!$B$52+'Plan-Annahmen'!$B$53) | J30: =E30*('Plan-Annahmen'!$B$14*'Plan-Annahmen'!$B$18+'Plan-Annahmen'!$B$19)+F30*('Plan-Annahmen'!$B$15*'Plan-Annahmen'!$B$18+'Plan-Annahmen'!$B$19) | K30: =G30*'Plan-Annahmen'!$B$17/100 | L30: ='Plan-Kunden'!D30*'Plan-Annahmen'!$B$15*'Plan-Annahmen'!$B$50 | M30: ='Plan-Kosten'!AJ$61 | N30: =IF(A30>=$O$6,'Plan-Kosten'!$F$71,0) | O30: ='Plan-Kosten'!AJ$58 | P30: =IF(A30=$O$6,'Plan-Kosten'!$F$72,0) | Q30: =I30+J30+K30+L30+M30+N30+O30+P30 | R30: =H30-Q30 | S30: =MAX(0,R30*'Plan-Annahmen'!$B$82) | T30: =R30-S30 | U30: =U29+T30 | V30: =V29+'Plan-Kosten'!AJ$59+IF(A30=$O$6,'Plan-Kosten'!$F$73,0) | W30: =U30-V30 | X30: =IF(R30>0,1,0) | Y30: ='Plan-Kunden'!P30 | Z30: ='Plan-Kunden'!Q30 | AA30: =IF(D30>='Plan-Phase B'!$C$22,1,0) | AB30: =IF(D30>='Plan-Phase B'!$D$22,1,0) | AC30: =IF(D30>='Plan-Phase B'!$E$22,1,0) | AD30: =IF(AND(W30>=0,A30>$K$6),1,0) | AE30: =IF(A30>=$O$6,1,0)
A31: 24 | B31: ='Plan-Kunden'!B31 | C31: ='Plan-Kunden'!E31 | D31: ='Plan-Kunden'!K31 | E31: ='Plan-Kunden'!I31 | F31: ='Plan-Kunden'!J31 | G31: =D31*'Plan-Annahmen'!$B$21 | H31: =E31*'Plan-Annahmen'!$B$14+F31*'Plan-Annahmen'!$B$15 | I31: =H31*('Plan-Annahmen'!$B$52+'Plan-Annahmen'!$B$53) | J31: =E31*('Plan-Annahmen'!$B$14*'Plan-Annahmen'!$B$18+'Plan-Annahmen'!$B$19)+F31*('Plan-Annahmen'!$B$15*'Plan-Annahmen'!$B$18+'Plan-Annahmen'!$B$19) | K31: =G31*'Plan-Annahmen'!$B$17/100 | L31: ='Plan-Kunden'!D31*'Plan-Annahmen'!$B$15*'Plan-Annahmen'!$B$50 | M31: ='Plan-Kosten'!AK$61 | N31: =IF(A31>=$O$6,'Plan-Kosten'!$F$71,0) | O31: ='Plan-Kosten'!AK$58 | P31: =IF(A31=$O$6,'Plan-Kosten'!$F$72,0) | Q31: =I31+J31+K31+L31+M31+N31+O31+P31 | R31: =H31-Q31 | S31: =MAX(0,R31*'Plan-Annahmen'!$B$82) | T31: =R31-S31 | U31: =U30+T31 | V31: =V30+'Plan-Kosten'!AK$59+IF(A31=$O$6,'Plan-Kosten'!$F$73,0) | W31: =U31-V31 | X31: =IF(R31>0,1,0) | Y31: ='Plan-Kunden'!P31 | Z31: ='Plan-Kunden'!Q31 | AA31: =IF(D31>='Plan-Phase B'!$C$22,1,0) | AB31: =IF(D31>='Plan-Phase B'!$D$22,1,0) | AC31: =IF(D31>='Plan-Phase B'!$E$22,1,0) | AD31: =IF(AND(W31>=0,A31>$K$6),1,0) | AE31: =IF(A31>=$O$6,1,0)
A32: Σ 24 Monate | H32: =SUM(H8:H31) | I32: =SUM(I8:I31) | J32: =SUM(J8:J31) | K32: =SUM(K8:K31) | L32: =SUM(L8:L31) | M32: =SUM(M8:M31) | N32: =SUM(N8:N31) | O32: =SUM(O8:O31) | ... T32: =SUM(T8:T31)
A35: Szenario: Realistisch | H35: Liquiditäts-Tiefpunkt in Monat: | K35: =MATCH(MIN(W37:W60),W37:W60,0) | M35: UG-Gründung in Monat: | O35: ='Plan-Kunden'!$S$61
A36: Monat | B36: Kalendermonat | C36: Neukunden | D36: Kunden aktiv | E36: Kunden @29€ | F36: Kunden @49€ | G36: Angebote | H36: Umsatz netto | I36: Ausfall + Kulanz | J36: Stripe-Gebühren | K36: KI-Kosten | L36: Empfehlungs-Anreiz | M36: Laufende Kosten Basis | N36: UG-Mehrkosten laufend | O36: Einmalkosten Basis | P36: UG-Einmalkosten | Q36: Kosten gesamt | R36: Ergebnis vor Steuer | S36: Steuerrücklage | T36: Cashflow nach Steuer | U36: kumuliert | V36: Reserven kumuliert | W36: Liquidität | X36: Ergebnis > 0? | Y36: Std. gesamt | Z36: über Dauerlinie? | AA36: Kunden ≥ B1 (30 Std.)? | AB36: Kunden ≥ B1 (25 Std.)? | AC36: Kunden ≥ B2? | AD36: Liquidität ≥ 0 nach Tiefpunkt? | AE36: UG aktiv?
A37: 1 | B37: ='Plan-Kunden'!B37 | C37: ='Plan-Kunden'!E37 | D37: ='Plan-Kunden'!K37 | E37: ='Plan-Kunden'!I37 | F37: ='Plan-Kunden'!J37 | G37: =D37*'Plan-Annahmen'!$B$21 | H37: =E37*'Plan-Annahmen'!$B$14+F37*'Plan-Annahmen'!$B$15 | I37: =H37*('Plan-Annahmen'!$B$52+'Plan-Annahmen'!$B$53) | J37: =E37*('Plan-Annahmen'!$B$14*'Plan-Annahmen'!$B$18+'Plan-Annahmen'!$B$19)+F37*('Plan-Annahmen'!$B$15*'Plan-Annahmen'!$B$18+'Plan-Annahmen'!$B$19) | K37: =G37*'Plan-Annahmen'!$B$17/100 | L37: ='Plan-Kunden'!D37*'Plan-Annahmen'!$B$15*'Plan-Annahmen'!$B$50 | M37: ='Plan-Kosten'!N$61 | N37: =IF(A37>=$O$35,'Plan-Kosten'!$F$71,0) | O37: ='Plan-Kosten'!N$58 | P37: =IF(A37=$O$35,'Plan-Kosten'!$F$72,0) | Q37: =I37+J37+K37+L37+M37+N37+O37+P37 | R37: =H37-Q37 | S37: =MAX(0,R37*'Plan-Annahmen'!$B$82) | T37: =R37-S37 | U37: =T37 | V37: ='Plan-Kosten'!N$59+IF(A37=$O$35,'Plan-Kosten'!$F$73,0) | W37: =U37-V37 | X37: =IF(R37>0,1,0) | Y37: ='Plan-Kunden'!P37 | Z37: ='Plan-Kunden'!Q37 | AA37: =IF(D37>='Plan-Phase B'!$C$22,1,0) | AB37: =IF(D37>='Plan-Phase B'!$D$22,1,0) | AC37: =IF(D37>='Plan-Phase B'!$E$22,1,0) | AD37: =IF(AND(W37>=0,A37>$K$35),1,0) | AE37: =IF(A37>=$O$35,1,0)
A38: 2 | B38: ='Plan-Kunden'!B38 | C38: ='Plan-Kunden'!E38 | D38: ='Plan-Kunden'!K38 | E38: ='Plan-Kunden'!I38 | F38: ='Plan-Kunden'!J38 | G38: =D38*'Plan-Annahmen'!$B$21 | H38: =E38*'Plan-Annahmen'!$B$14+F38*'Plan-Annahmen'!$B$15 | I38: =H38*('Plan-Annahmen'!$B$52+'Plan-Annahmen'!$B$53) | J38: =E38*('Plan-Annahmen'!$B$14*'Plan-Annahmen'!$B$18+'Plan-Annahmen'!$B$19)+F38*('Plan-Annahmen'!$B$15*'Plan-Annahmen'!$B$18+'Plan-Annahmen'!$B$19) | K38: =G38*'Plan-Annahmen'!$B$17/100 | L38: ='Plan-Kunden'!D38*'Plan-Annahmen'!$B$15*'Plan-Annahmen'!$B$50 | M38: ='Plan-Kosten'!O$61 | N38: =IF(A38>=$O$35,'Plan-Kosten'!$F$71,0) | O38: ='Plan-Kosten'!O$58 | P38: =IF(A38=$O$35,'Plan-Kosten'!$F$72,0) | Q38: =I38+J38+K38+L38+M38+N38+O38+P38 | R38: =H38-Q38 | S38: =MAX(0,R38*'Plan-Annahmen'!$B$82) | T38: =R38-S38 | U38: =U37+T38 | V38: =V37+'Plan-Kosten'!O$59+IF(A38=$O$35,'Plan-Kosten'!$F$73,0) | W38: =U38-V38 | X38: =IF(R38>0,1,0) | Y38: ='Plan-Kunden'!P38 | Z38: ='Plan-Kunden'!Q38 | AA38: =IF(D38>='Plan-Phase B'!$C$22,1,0) | AB38: =IF(D38>='Plan-Phase B'!$D$22,1,0) | AC38: =IF(D38>='Plan-Phase B'!$E$22,1,0) | AD38: =IF(AND(W38>=0,A38>$K$35),1,0) | AE38: =IF(A38>=$O$35,1,0)
A39: 3 | B39: ='Plan-Kunden'!B39 | C39: ='Plan-Kunden'!E39 | D39: ='Plan-Kunden'!K39 | E39: ='Plan-Kunden'!I39 | F39: ='Plan-Kunden'!J39 | G39: =D39*'Plan-Annahmen'!$B$21 | H39: =E39*'Plan-Annahmen'!$B$14+F39*'Plan-Annahmen'!$B$15 | I39: =H39*('Plan-Annahmen'!$B$52+'Plan-Annahmen'!$B$53) | J39: =E39*('Plan-Annahmen'!$B$14*'Plan-Annahmen'!$B$18+'Plan-Annahmen'!$B$19)+F39*('Plan-Annahmen'!$B$15*'Plan-Annahmen'!$B$18+'Plan-Annahmen'!$B$19) | K39: =G39*'Plan-Annahmen'!$B$17/100 | L39: ='Plan-Kunden'!D39*'Plan-Annahmen'!$B$15*'Plan-Annahmen'!$B$50 | M39: ='Plan-Kosten'!P$61 | N39: =IF(A39>=$O$35,'Plan-Kosten'!$F$71,0) | O39: ='Plan-Kosten'!P$58 | P39: =IF(A39=$O$35,'Plan-Kosten'!$F$72,0) | Q39: =I39+J39+K39+L39+M39+N39+O39+P39 | R39: =H39-Q39 | S39: =MAX(0,R39*'Plan-Annahmen'!$B$82) | T39: =R39-S39 | U39: =U38+T39 | V39: =V38+'Plan-Kosten'!P$59+IF(A39=$O$35,'Plan-Kosten'!$F$73,0) | W39: =U39-V39 | X39: =IF(R39>0,1,0) | Y39: ='Plan-Kunden'!P39 | Z39: ='Plan-Kunden'!Q39 | AA39: =IF(D39>='Plan-Phase B'!$C$22,1,0) | AB39: =IF(D39>='Plan-Phase B'!$D$22,1,0) | AC39: =IF(D39>='Plan-Phase B'!$E$22,1,0) | AD39: =IF(AND(W39>=0,A39>$K$35),1,0) | AE39: =IF(A39>=$O$35,1,0)
A40: 4 | B40: ='Plan-Kunden'!B40 | C40: ='Plan-Kunden'!E40 | D40: ='Plan-Kunden'!K40 | E40: ='Plan-Kunden'!I40 | F40: ='Plan-Kunden'!J40 | G40: =D40*'Plan-Annahmen'!$B$21 | H40: =E40*'Plan-Annahmen'!$B$14+F40*'Plan-Annahmen'!$B$15 | I40: =H40*('Plan-Annahmen'!$B$52+'Plan-Annahmen'!$B$53) | J40: =E40*('Plan-Annahmen'!$B$14*'Plan-Annahmen'!$B$18+'Plan-Annahmen'!$B$19)+F40*('Plan-Annahmen'!$B$15*'Plan-Annahmen'!$B$18+'Plan-Annahmen'!$B$19) | K40: =G40*'Plan-Annahmen'!$B$17/100 | L40: ='Plan-Kunden'!D40*'Plan-Annahmen'!$B$15*'Plan-Annahmen'!$B$50 | M40: ='Plan-Kosten'!Q$61 | N40: =IF(A40>=$O$35,'Plan-Kosten'!$F$71,0) | O40: ='Plan-Kosten'!Q$58 | P40: =IF(A40=$O$35,'Plan-Kosten'!$F$72,0) | Q40: =I40+J40+K40+L40+M40+N40+O40+P40 | R40: =H40-Q40 | S40: =MAX(0,R40*'Plan-Annahmen'!$B$82) | T40: =R40-S40 | U40: =U39+T40 | V40: =V39+'Plan-Kosten'!Q$59+IF(A40=$O$35,'Plan-Kosten'!$F$73,0) | W40: =U40-V40 | X40: =IF(R40>0,1,0) | Y40: ='Plan-Kunden'!P40 | Z40: ='Plan-Kunden'!Q40 | AA40: =IF(D40>='Plan-Phase B'!$C$22,1,0) | AB40: =IF(D40>='Plan-Phase B'!$D$22,1,0) | AC40: =IF(D40>='Plan-Phase B'!$E$22,1,0) | AD40: =IF(AND(W40>=0,A40>$K$35),1,0) | AE40: =IF(A40>=$O$35,1,0)
A41: 5 | B41: ='Plan-Kunden'!B41 | C41: ='Plan-Kunden'!E41 | D41: ='Plan-Kunden'!K41 | E41: ='Plan-Kunden'!I41 | F41: ='Plan-Kunden'!J41 | G41: =D41*'Plan-Annahmen'!$B$21 | H41: =E41*'Plan-Annahmen'!$B$14+F41*'Plan-Annahmen'!$B$15 | I41: =H41*('Plan-Annahmen'!$B$52+'Plan-Annahmen'!$B$53) | J41: =E41*('Plan-Annahmen'!$B$14*'Plan-Annahmen'!$B$18+'Plan-Annahmen'!$B$19)+F41*('Plan-Annahmen'!$B$15*'Plan-Annahmen'!$B$18+'Plan-Annahmen'!$B$19) | K41: =G41*'Plan-Annahmen'!$B$17/100 | L41: ='Plan-Kunden'!D41*'Plan-Annahmen'!$B$15*'Plan-Annahmen'!$B$50 | M41: ='Plan-Kosten'!R$61 | N41: =IF(A41>=$O$35,'Plan-Kosten'!$F$71,0) | O41: ='Plan-Kosten'!R$58 | P41: =IF(A41=$O$35,'Plan-Kosten'!$F$72,0) | Q41: =I41+J41+K41+L41+M41+N41+O41+P41 | R41: =H41-Q41 | S41: =MAX(0,R41*'Plan-Annahmen'!$B$82) | T41: =R41-S41 | U41: =U40+T41 | V41: =V40+'Plan-Kosten'!R$59+IF(A41=$O$35,'Plan-Kosten'!$F$73,0) | W41: =U41-V41 | X41: =IF(R41>0,1,0) | Y41: ='Plan-Kunden'!P41 | Z41: ='Plan-Kunden'!Q41 | AA41: =IF(D41>='Plan-Phase B'!$C$22,1,0) | AB41: =IF(D41>='Plan-Phase B'!$D$22,1,0) | AC41: =IF(D41>='Plan-Phase B'!$E$22,1,0) | AD41: =IF(AND(W41>=0,A41>$K$35),1,0) | AE41: =IF(A41>=$O$35,1,0)
A42: 6 | B42: ='Plan-Kunden'!B42 | C42: ='Plan-Kunden'!E42 | D42: ='Plan-Kunden'!K42 | E42: ='Plan-Kunden'!I42 | F42: ='Plan-Kunden'!J42 | G42: =D42*'Plan-Annahmen'!$B$21 | H42: =E42*'Plan-Annahmen'!$B$14+F42*'Plan-Annahmen'!$B$15 | I42: =H42*('Plan-Annahmen'!$B$52+'Plan-Annahmen'!$B$53) | J42: =E42*('Plan-Annahmen'!$B$14*'Plan-Annahmen'!$B$18+'Plan-Annahmen'!$B$19)+F42*('Plan-Annahmen'!$B$15*'Plan-Annahmen'!$B$18+'Plan-Annahmen'!$B$19) | K42: =G42*'Plan-Annahmen'!$B$17/100 | L42: ='Plan-Kunden'!D42*'Plan-Annahmen'!$B$15*'Plan-Annahmen'!$B$50 | M42: ='Plan-Kosten'!S$61 | N42: =IF(A42>=$O$35,'Plan-Kosten'!$F$71,0) | O42: ='Plan-Kosten'!S$58 | P42: =IF(A42=$O$35,'Plan-Kosten'!$F$72,0) | Q42: =I42+J42+K42+L42+M42+N42+O42+P42 | R42: =H42-Q42 | S42: =MAX(0,R42*'Plan-Annahmen'!$B$82) | T42: =R42-S42 | U42: =U41+T42 | V42: =V41+'Plan-Kosten'!S$59+IF(A42=$O$35,'Plan-Kosten'!$F$73,0) | W42: =U42-V42 | X42: =IF(R42>0,1,0) | Y42: ='Plan-Kunden'!P42 | Z42: ='Plan-Kunden'!Q42 | AA42: =IF(D42>='Plan-Phase B'!$C$22,1,0) | AB42: =IF(D42>='Plan-Phase B'!$D$22,1,0) | AC42: =IF(D42>='Plan-Phase B'!$E$22,1,0) | AD42: =IF(AND(W42>=0,A42>$K$35),1,0) | AE42: =IF(A42>=$O$35,1,0)
A43: 7 | B43: ='Plan-Kunden'!B43 | C43: ='Plan-Kunden'!E43 | D43: ='Plan-Kunden'!K43 | E43: ='Plan-Kunden'!I43 | F43: ='Plan-Kunden'!J43 | G43: =D43*'Plan-Annahmen'!$B$21 | H43: =E43*'Plan-Annahmen'!$B$14+F43*'Plan-Annahmen'!$B$15 | I43: =H43*('Plan-Annahmen'!$B$52+'Plan-Annahmen'!$B$53) | J43: =E43*('Plan-Annahmen'!$B$14*'Plan-Annahmen'!$B$18+'Plan-Annahmen'!$B$19)+F43*('Plan-Annahmen'!$B$15*'Plan-Annahmen'!$B$18+'Plan-Annahmen'!$B$19) | K43: =G43*'Plan-Annahmen'!$B$17/100 | L43: ='Plan-Kunden'!D43*'Plan-Annahmen'!$B$15*'Plan-Annahmen'!$B$50 | M43: ='Plan-Kosten'!T$61 | N43: =IF(A43>=$O$35,'Plan-Kosten'!$F$71,0) | O43: ='Plan-Kosten'!T$58 | P43: =IF(A43=$O$35,'Plan-Kosten'!$F$72,0) | Q43: =I43+J43+K43+L43+M43+N43+O43+P43 | R43: =H43-Q43 | S43: =MAX(0,R43*'Plan-Annahmen'!$B$82) | T43: =R43-S43 | U43: =U42+T43 | V43: =V42+'Plan-Kosten'!T$59+IF(A43=$O$35,'Plan-Kosten'!$F$73,0) | W43: =U43-V43 | X43: =IF(R43>0,1,0) | Y43: ='Plan-Kunden'!P43 | Z43: ='Plan-Kunden'!Q43 | AA43: =IF(D43>='Plan-Phase B'!$C$22,1,0) | AB43: =IF(D43>='Plan-Phase B'!$D$22,1,0) | AC43: =IF(D43>='Plan-Phase B'!$E$22,1,0) | AD43: =IF(AND(W43>=0,A43>$K$35),1,0) | AE43: =IF(A43>=$O$35,1,0)
A44: 8 | B44: ='Plan-Kunden'!B44 | C44: ='Plan-Kunden'!E44 | D44: ='Plan-Kunden'!K44 | E44: ='Plan-Kunden'!I44 | F44: ='Plan-Kunden'!J44 | G44: =D44*'Plan-Annahmen'!$B$21 | H44: =E44*'Plan-Annahmen'!$B$14+F44*'Plan-Annahmen'!$B$15 | I44: =H44*('Plan-Annahmen'!$B$52+'Plan-Annahmen'!$B$53) | J44: =E44*('Plan-Annahmen'!$B$14*'Plan-Annahmen'!$B$18+'Plan-Annahmen'!$B$19)+F44*('Plan-Annahmen'!$B$15*'Plan-Annahmen'!$B$18+'Plan-Annahmen'!$B$19) | K44: =G44*'Plan-Annahmen'!$B$17/100 | L44: ='Plan-Kunden'!D44*'Plan-Annahmen'!$B$15*'Plan-Annahmen'!$B$50 | M44: ='Plan-Kosten'!U$61 | N44: =IF(A44>=$O$35,'Plan-Kosten'!$F$71,0) | O44: ='Plan-Kosten'!U$58 | P44: =IF(A44=$O$35,'Plan-Kosten'!$F$72,0) | Q44: =I44+J44+K44+L44+M44+N44+O44+P44 | R44: =H44-Q44 | S44: =MAX(0,R44*'Plan-Annahmen'!$B$82) | T44: =R44-S44 | U44: =U43+T44 | V44: =V43+'Plan-Kosten'!U$59+IF(A44=$O$35,'Plan-Kosten'!$F$73,0) | W44: =U44-V44 | X44: =IF(R44>0,1,0) | Y44: ='Plan-Kunden'!P44 | Z44: ='Plan-Kunden'!Q44 | AA44: =IF(D44>='Plan-Phase B'!$C$22,1,0) | AB44: =IF(D44>='Plan-Phase B'!$D$22,1,0) | AC44: =IF(D44>='Plan-Phase B'!$E$22,1,0) | AD44: =IF(AND(W44>=0,A44>$K$35),1,0) | AE44: =IF(A44>=$O$35,1,0)
A45: 9 | B45: ='Plan-Kunden'!B45 | C45: ='Plan-Kunden'!E45 | D45: ='Plan-Kunden'!K45 | E45: ='Plan-Kunden'!I45 | F45: ='Plan-Kunden'!J45 | G45: =D45*'Plan-Annahmen'!$B$21 | H45: =E45*'Plan-Annahmen'!$B$14+F45*'Plan-Annahmen'!$B$15 | I45: =H45*('Plan-Annahmen'!$B$52+'Plan-Annahmen'!$B$53) | J45: =E45*('Plan-Annahmen'!$B$14*'Plan-Annahmen'!$B$18+'Plan-Annahmen'!$B$19)+F45*('Plan-Annahmen'!$B$15*'Plan-Annahmen'!$B$18+'Plan-Annahmen'!$B$19) | K45: =G45*'Plan-Annahmen'!$B$17/100 | L45: ='Plan-Kunden'!D45*'Plan-Annahmen'!$B$15*'Plan-Annahmen'!$B$50 | M45: ='Plan-Kosten'!V$61 | N45: =IF(A45>=$O$35,'Plan-Kosten'!$F$71,0) | O45: ='Plan-Kosten'!V$58 | P45: =IF(A45=$O$35,'Plan-Kosten'!$F$72,0) | Q45: =I45+J45+K45+L45+M45+N45+O45+P45 | R45: =H45-Q45 | S45: =MAX(0,R45*'Plan-Annahmen'!$B$82) | T45: =R45-S45 | U45: =U44+T45 | V45: =V44+'Plan-Kosten'!V$59+IF(A45=$O$35,'Plan-Kosten'!$F$73,0) | W45: =U45-V45 | X45: =IF(R45>0,1,0) | Y45: ='Plan-Kunden'!P45 | Z45: ='Plan-Kunden'!Q45 | AA45: =IF(D45>='Plan-Phase B'!$C$22,1,0) | AB45: =IF(D45>='Plan-Phase B'!$D$22,1,0) | AC45: =IF(D45>='Plan-Phase B'!$E$22,1,0) | AD45: =IF(AND(W45>=0,A45>$K$35),1,0) | AE45: =IF(A45>=$O$35,1,0)
A46: 10 | B46: ='Plan-Kunden'!B46 | C46: ='Plan-Kunden'!E46 | D46: ='Plan-Kunden'!K46 | E46: ='Plan-Kunden'!I46 | F46: ='Plan-Kunden'!J46 | G46: =D46*'Plan-Annahmen'!$B$21 | H46: =E46*'Plan-Annahmen'!$B$14+F46*'Plan-Annahmen'!$B$15 | I46: =H46*('Plan-Annahmen'!$B$52+'Plan-Annahmen'!$B$53) | J46: =E46*('Plan-Annahmen'!$B$14*'Plan-Annahmen'!$B$18+'Plan-Annahmen'!$B$19)+F46*('Plan-Annahmen'!$B$15*'Plan-Annahmen'!$B$18+'Plan-Annahmen'!$B$19) | K46: =G46*'Plan-Annahmen'!$B$17/100 | L46: ='Plan-Kunden'!D46*'Plan-Annahmen'!$B$15*'Plan-Annahmen'!$B$50 | M46: ='Plan-Kosten'!W$61 | N46: =IF(A46>=$O$35,'Plan-Kosten'!$F$71,0) | O46: ='Plan-Kosten'!W$58 | P46: =IF(A46=$O$35,'Plan-Kosten'!$F$72,0) | Q46: =I46+J46+K46+L46+M46+N46+O46+P46 | R46: =H46-Q46 | S46: =MAX(0,R46*'Plan-Annahmen'!$B$82) | T46: =R46-S46 | U46: =U45+T46 | V46: =V45+'Plan-Kosten'!W$59+IF(A46=$O$35,'Plan-Kosten'!$F$73,0) | W46: =U46-V46 | X46: =IF(R46>0,1,0) | Y46: ='Plan-Kunden'!P46 | Z46: ='Plan-Kunden'!Q46 | AA46: =IF(D46>='Plan-Phase B'!$C$22,1,0) | AB46: =IF(D46>='Plan-Phase B'!$D$22,1,0) | AC46: =IF(D46>='Plan-Phase B'!$E$22,1,0) | AD46: =IF(AND(W46>=0,A46>$K$35),1,0) | AE46: =IF(A46>=$O$35,1,0)
A47: 11 | B47: ='Plan-Kunden'!B47 | C47: ='Plan-Kunden'!E47 | D47: ='Plan-Kunden'!K47 | E47: ='Plan-Kunden'!I47 | F47: ='Plan-Kunden'!J47 | G47: =D47*'Plan-Annahmen'!$B$21 | H47: =E47*'Plan-Annahmen'!$B$14+F47*'Plan-Annahmen'!$B$15 | I47: =H47*('Plan-Annahmen'!$B$52+'Plan-Annahmen'!$B$53) | J47: =E47*('Plan-Annahmen'!$B$14*'Plan-Annahmen'!$B$18+'Plan-Annahmen'!$B$19)+F47*('Plan-Annahmen'!$B$15*'Plan-Annahmen'!$B$18+'Plan-Annahmen'!$B$19) | K47: =G47*'Plan-Annahmen'!$B$17/100 | L47: ='Plan-Kunden'!D47*'Plan-Annahmen'!$B$15*'Plan-Annahmen'!$B$50 | M47: ='Plan-Kosten'!X$61 | N47: =IF(A47>=$O$35,'Plan-Kosten'!$F$71,0) | O47: ='Plan-Kosten'!X$58 | P47: =IF(A47=$O$35,'Plan-Kosten'!$F$72,0) | Q47: =I47+J47+K47+L47+M47+N47+O47+P47 | R47: =H47-Q47 | S47: =MAX(0,R47*'Plan-Annahmen'!$B$82) | T47: =R47-S47 | U47: =U46+T47 | V47: =V46+'Plan-Kosten'!X$59+IF(A47=$O$35,'Plan-Kosten'!$F$73,0) | W47: =U47-V47 | X47: =IF(R47>0,1,0) | Y47: ='Plan-Kunden'!P47 | Z47: ='Plan-Kunden'!Q47 | AA47: =IF(D47>='Plan-Phase B'!$C$22,1,0) | AB47: =IF(D47>='Plan-Phase B'!$D$22,1,0) | AC47: =IF(D47>='Plan-Phase B'!$E$22,1,0) | AD47: =IF(AND(W47>=0,A47>$K$35),1,0) | AE47: =IF(A47>=$O$35,1,0)
A48: 12 | B48: ='Plan-Kunden'!B48 | C48: ='Plan-Kunden'!E48 | D48: ='Plan-Kunden'!K48 | E48: ='Plan-Kunden'!I48 | F48: ='Plan-Kunden'!J48 | G48: =D48*'Plan-Annahmen'!$B$21 | H48: =E48*'Plan-Annahmen'!$B$14+F48*'Plan-Annahmen'!$B$15 | I48: =H48*('Plan-Annahmen'!$B$52+'Plan-Annahmen'!$B$53) | J48: =E48*('Plan-Annahmen'!$B$14*'Plan-Annahmen'!$B$18+'Plan-Annahmen'!$B$19)+F48*('Plan-Annahmen'!$B$15*'Plan-Annahmen'!$B$18+'Plan-Annahmen'!$B$19) | K48: =G48*'Plan-Annahmen'!$B$17/100 | L48: ='Plan-Kunden'!D48*'Plan-Annahmen'!$B$15*'Plan-Annahmen'!$B$50 | M48: ='Plan-Kosten'!Y$61 | N48: =IF(A48>=$O$35,'Plan-Kosten'!$F$71,0) | O48: ='Plan-Kosten'!Y$58 | P48: =IF(A48=$O$35,'Plan-Kosten'!$F$72,0) | Q48: =I48+J48+K48+L48+M48+N48+O48+P48 | R48: =H48-Q48 | S48: =MAX(0,R48*'Plan-Annahmen'!$B$82) | T48: =R48-S48 | U48: =U47+T48 | V48: =V47+'Plan-Kosten'!Y$59+IF(A48=$O$35,'Plan-Kosten'!$F$73,0) | W48: =U48-V48 | X48: =IF(R48>0,1,0) | Y48: ='Plan-Kunden'!P48 | Z48: ='Plan-Kunden'!Q48 | AA48: =IF(D48>='Plan-Phase B'!$C$22,1,0) | AB48: =IF(D48>='Plan-Phase B'!$D$22,1,0) | AC48: =IF(D48>='Plan-Phase B'!$E$22,1,0) | AD48: =IF(AND(W48>=0,A48>$K$35),1,0) | AE48: =IF(A48>=$O$35,1,0)
A49: 13 | B49: ='Plan-Kunden'!B49 | C49: ='Plan-Kunden'!E49 | D49: ='Plan-Kunden'!K49 | E49: ='Plan-Kunden'!I49 | F49: ='Plan-Kunden'!J49 | G49: =D49*'Plan-Annahmen'!$B$21 | H49: =E49*'Plan-Annahmen'!$B$14+F49*'Plan-Annahmen'!$B$15 | I49: =H49*('Plan-Annahmen'!$B$52+'Plan-Annahmen'!$B$53) | J49: =E49*('Plan-Annahmen'!$B$14*'Plan-Annahmen'!$B$18+'Plan-Annahmen'!$B$19)+F49*('Plan-Annahmen'!$B$15*'Plan-Annahmen'!$B$18+'Plan-Annahmen'!$B$19) | K49: =G49*'Plan-Annahmen'!$B$17/100 | L49: ='Plan-Kunden'!D49*'Plan-Annahmen'!$B$15*'Plan-Annahmen'!$B$50 | M49: ='Plan-Kosten'!Z$61 | N49: =IF(A49>=$O$35,'Plan-Kosten'!$F$71,0) | O49: ='Plan-Kosten'!Z$58 | P49: =IF(A49=$O$35,'Plan-Kosten'!$F$72,0) | Q49: =I49+J49+K49+L49+M49+N49+O49+P49 | R49: =H49-Q49 | S49: =MAX(0,R49*'Plan-Annahmen'!$B$82) | T49: =R49-S49 | U49: =U48+T49 | V49: =V48+'Plan-Kosten'!Z$59+IF(A49=$O$35,'Plan-Kosten'!$F$73,0) | W49: =U49-V49 | X49: =IF(R49>0,1,0) | Y49: ='Plan-Kunden'!P49 | Z49: ='Plan-Kunden'!Q49 | AA49: =IF(D49>='Plan-Phase B'!$C$22,1,0) | AB49: =IF(D49>='Plan-Phase B'!$D$22,1,0) | AC49: =IF(D49>='Plan-Phase B'!$E$22,1,0) | AD49: =IF(AND(W49>=0,A49>$K$35),1,0) | AE49: =IF(A49>=$O$35,1,0)
A50: 14 | B50: ='Plan-Kunden'!B50 | C50: ='Plan-Kunden'!E50 | D50: ='Plan-Kunden'!K50 | E50: ='Plan-Kunden'!I50 | F50: ='Plan-Kunden'!J50 | G50: =D50*'Plan-Annahmen'!$B$21 | H50: =E50*'Plan-Annahmen'!$B$14+F50*'Plan-Annahmen'!$B$15 | I50: =H50*('Plan-Annahmen'!$B$52+'Plan-Annahmen'!$B$53) | J50: =E50*('Plan-Annahmen'!$B$14*'Plan-Annahmen'!$B$18+'Plan-Annahmen'!$B$19)+F50*('Plan-Annahmen'!$B$15*'Plan-Annahmen'!$B$18+'Plan-Annahmen'!$B$19) | K50: =G50*'Plan-Annahmen'!$B$17/100 | L50: ='Plan-Kunden'!D50*'Plan-Annahmen'!$B$15*'Plan-Annahmen'!$B$50 | M50: ='Plan-Kosten'!AA$61 | N50: =IF(A50>=$O$35,'Plan-Kosten'!$F$71,0) | O50: ='Plan-Kosten'!AA$58 | P50: =IF(A50=$O$35,'Plan-Kosten'!$F$72,0) | Q50: =I50+J50+K50+L50+M50+N50+O50+P50 | R50: =H50-Q50 | S50: =MAX(0,R50*'Plan-Annahmen'!$B$82) | T50: =R50-S50 | U50: =U49+T50 | V50: =V49+'Plan-Kosten'!AA$59+IF(A50=$O$35,'Plan-Kosten'!$F$73,0) | W50: =U50-V50 | X50: =IF(R50>0,1,0) | Y50: ='Plan-Kunden'!P50 | Z50: ='Plan-Kunden'!Q50 | AA50: =IF(D50>='Plan-Phase B'!$C$22,1,0) | AB50: =IF(D50>='Plan-Phase B'!$D$22,1,0) | AC50: =IF(D50>='Plan-Phase B'!$E$22,1,0) | AD50: =IF(AND(W50>=0,A50>$K$35),1,0) | AE50: =IF(A50>=$O$35,1,0)
A51: 15 | B51: ='Plan-Kunden'!B51 | C51: ='Plan-Kunden'!E51 | D51: ='Plan-Kunden'!K51 | E51: ='Plan-Kunden'!I51 | F51: ='Plan-Kunden'!J51 | G51: =D51*'Plan-Annahmen'!$B$21 | H51: =E51*'Plan-Annahmen'!$B$14+F51*'Plan-Annahmen'!$B$15 | I51: =H51*('Plan-Annahmen'!$B$52+'Plan-Annahmen'!$B$53) | J51: =E51*('Plan-Annahmen'!$B$14*'Plan-Annahmen'!$B$18+'Plan-Annahmen'!$B$19)+F51*('Plan-Annahmen'!$B$15*'Plan-Annahmen'!$B$18+'Plan-Annahmen'!$B$19) | K51: =G51*'Plan-Annahmen'!$B$17/100 | L51: ='Plan-Kunden'!D51*'Plan-Annahmen'!$B$15*'Plan-Annahmen'!$B$50 | M51: ='Plan-Kosten'!AB$61 | N51: =IF(A51>=$O$35,'Plan-Kosten'!$F$71,0) | O51: ='Plan-Kosten'!AB$58 | P51: =IF(A51=$O$35,'Plan-Kosten'!$F$72,0) | Q51: =I51+J51+K51+L51+M51+N51+O51+P51 | R51: =H51-Q51 | S51: =MAX(0,R51*'Plan-Annahmen'!$B$82) | T51: =R51-S51 | U51: =U50+T51 | V51: =V50+'Plan-Kosten'!AB$59+IF(A51=$O$35,'Plan-Kosten'!$F$73,0) | W51: =U51-V51 | X51: =IF(R51>0,1,0) | Y51: ='Plan-Kunden'!P51 | Z51: ='Plan-Kunden'!Q51 | AA51: =IF(D51>='Plan-Phase B'!$C$22,1,0) | AB51: =IF(D51>='Plan-Phase B'!$D$22,1,0) | AC51: =IF(D51>='Plan-Phase B'!$E$22,1,0) | AD51: =IF(AND(W51>=0,A51>$K$35),1,0) | AE51: =IF(A51>=$O$35,1,0)
A52: 16 | B52: ='Plan-Kunden'!B52 | C52: ='Plan-Kunden'!E52 | D52: ='Plan-Kunden'!K52 | E52: ='Plan-Kunden'!I52 | F52: ='Plan-Kunden'!J52 | G52: =D52*'Plan-Annahmen'!$B$21 | H52: =E52*'Plan-Annahmen'!$B$14+F52*'Plan-Annahmen'!$B$15 | I52: =H52*('Plan-Annahmen'!$B$52+'Plan-Annahmen'!$B$53) | J52: =E52*('Plan-Annahmen'!$B$14*'Plan-Annahmen'!$B$18+'Plan-Annahmen'!$B$19)+F52*('Plan-Annahmen'!$B$15*'Plan-Annahmen'!$B$18+'Plan-Annahmen'!$B$19) | K52: =G52*'Plan-Annahmen'!$B$17/100 | L52: ='Plan-Kunden'!D52*'Plan-Annahmen'!$B$15*'Plan-Annahmen'!$B$50 | M52: ='Plan-Kosten'!AC$61 | N52: =IF(A52>=$O$35,'Plan-Kosten'!$F$71,0) | O52: ='Plan-Kosten'!AC$58 | P52: =IF(A52=$O$35,'Plan-Kosten'!$F$72,0) | Q52: =I52+J52+K52+L52+M52+N52+O52+P52 | R52: =H52-Q52 | S52: =MAX(0,R52*'Plan-Annahmen'!$B$82) | T52: =R52-S52 | U52: =U51+T52 | V52: =V51+'Plan-Kosten'!AC$59+IF(A52=$O$35,'Plan-Kosten'!$F$73,0) | W52: =U52-V52 | X52: =IF(R52>0,1,0) | Y52: ='Plan-Kunden'!P52 | Z52: ='Plan-Kunden'!Q52 | AA52: =IF(D52>='Plan-Phase B'!$C$22,1,0) | AB52: =IF(D52>='Plan-Phase B'!$D$22,1,0) | AC52: =IF(D52>='Plan-Phase B'!$E$22,1,0) | AD52: =IF(AND(W52>=0,A52>$K$35),1,0) | AE52: =IF(A52>=$O$35,1,0)
A53: 17 | B53: ='Plan-Kunden'!B53 | C53: ='Plan-Kunden'!E53 | D53: ='Plan-Kunden'!K53 | E53: ='Plan-Kunden'!I53 | F53: ='Plan-Kunden'!J53 | G53: =D53*'Plan-Annahmen'!$B$21 | H53: =E53*'Plan-Annahmen'!$B$14+F53*'Plan-Annahmen'!$B$15 | I53: =H53*('Plan-Annahmen'!$B$52+'Plan-Annahmen'!$B$53) | J53: =E53*('Plan-Annahmen'!$B$14*'Plan-Annahmen'!$B$18+'Plan-Annahmen'!$B$19)+F53*('Plan-Annahmen'!$B$15*'Plan-Annahmen'!$B$18+'Plan-Annahmen'!$B$19) | K53: =G53*'Plan-Annahmen'!$B$17/100 | L53: ='Plan-Kunden'!D53*'Plan-Annahmen'!$B$15*'Plan-Annahmen'!$B$50 | M53: ='Plan-Kosten'!AD$61 | N53: =IF(A53>=$O$35,'Plan-Kosten'!$F$71,0) | O53: ='Plan-Kosten'!AD$58 | P53: =IF(A53=$O$35,'Plan-Kosten'!$F$72,0) | Q53: =I53+J53+K53+L53+M53+N53+O53+P53 | R53: =H53-Q53 | S53: =MAX(0,R53*'Plan-Annahmen'!$B$82) | T53: =R53-S53 | U53: =U52+T53 | V53: =V52+'Plan-Kosten'!AD$59+IF(A53=$O$35,'Plan-Kosten'!$F$73,0) | W53: =U53-V53 | X53: =IF(R53>0,1,0) | Y53: ='Plan-Kunden'!P53 | Z53: ='Plan-Kunden'!Q53 | AA53: =IF(D53>='Plan-Phase B'!$C$22,1,0) | AB53: =IF(D53>='Plan-Phase B'!$D$22,1,0) | AC53: =IF(D53>='Plan-Phase B'!$E$22,1,0) | AD53: =IF(AND(W53>=0,A53>$K$35),1,0) | AE53: =IF(A53>=$O$35,1,0)
A54: 18 | B54: ='Plan-Kunden'!B54 | C54: ='Plan-Kunden'!E54 | D54: ='Plan-Kunden'!K54 | E54: ='Plan-Kunden'!I54 | F54: ='Plan-Kunden'!J54 | G54: =D54*'Plan-Annahmen'!$B$21 | H54: =E54*'Plan-Annahmen'!$B$14+F54*'Plan-Annahmen'!$B$15 | I54: =H54*('Plan-Annahmen'!$B$52+'Plan-Annahmen'!$B$53) | J54: =E54*('Plan-Annahmen'!$B$14*'Plan-Annahmen'!$B$18+'Plan-Annahmen'!$B$19)+F54*('Plan-Annahmen'!$B$15*'Plan-Annahmen'!$B$18+'Plan-Annahmen'!$B$19) | K54: =G54*'Plan-Annahmen'!$B$17/100 | L54: ='Plan-Kunden'!D54*'Plan-Annahmen'!$B$15*'Plan-Annahmen'!$B$50 | M54: ='Plan-Kosten'!AE$61 | N54: =IF(A54>=$O$35,'Plan-Kosten'!$F$71,0) | O54: ='Plan-Kosten'!AE$58 | P54: =IF(A54=$O$35,'Plan-Kosten'!$F$72,0) | Q54: =I54+J54+K54+L54+M54+N54+O54+P54 | R54: =H54-Q54 | S54: =MAX(0,R54*'Plan-Annahmen'!$B$82) | T54: =R54-S54 | U54: =U53+T54 | V54: =V53+'Plan-Kosten'!AE$59+IF(A54=$O$35,'Plan-Kosten'!$F$73,0) | W54: =U54-V54 | X54: =IF(R54>0,1,0) | Y54: ='Plan-Kunden'!P54 | Z54: ='Plan-Kunden'!Q54 | AA54: =IF(D54>='Plan-Phase B'!$C$22,1,0) | AB54: =IF(D54>='Plan-Phase B'!$D$22,1,0) | AC54: =IF(D54>='Plan-Phase B'!$E$22,1,0) | AD54: =IF(AND(W54>=0,A54>$K$35),1,0) | AE54: =IF(A54>=$O$35,1,0)
A55: 19 | B55: ='Plan-Kunden'!B55 | C55: ='Plan-Kunden'!E55 | D55: ='Plan-Kunden'!K55 | E55: ='Plan-Kunden'!I55 | F55: ='Plan-Kunden'!J55 | G55: =D55*'Plan-Annahmen'!$B$21 | H55: =E55*'Plan-Annahmen'!$B$14+F55*'Plan-Annahmen'!$B$15 | I55: =H55*('Plan-Annahmen'!$B$52+'Plan-Annahmen'!$B$53) | J55: =E55*('Plan-Annahmen'!$B$14*'Plan-Annahmen'!$B$18+'Plan-Annahmen'!$B$19)+F55*('Plan-Annahmen'!$B$15*'Plan-Annahmen'!$B$18+'Plan-Annahmen'!$B$19) | K55: =G55*'Plan-Annahmen'!$B$17/100 | L55: ='Plan-Kunden'!D55*'Plan-Annahmen'!$B$15*'Plan-Annahmen'!$B$50 | M55: ='Plan-Kosten'!AF$61 | N55: =IF(A55>=$O$35,'Plan-Kosten'!$F$71,0) | O55: ='Plan-Kosten'!AF$58 | P55: =IF(A55=$O$35,'Plan-Kosten'!$F$72,0) | Q55: =I55+J55+K55+L55+M55+N55+O55+P55 | R55: =H55-Q55 | S55: =MAX(0,R55*'Plan-Annahmen'!$B$82) | T55: =R55-S55 | U55: =U54+T55 | V55: =V54+'Plan-Kosten'!AF$59+IF(A55=$O$35,'Plan-Kosten'!$F$73,0) | W55: =U55-V55 | X55: =IF(R55>0,1,0) | Y55: ='Plan-Kunden'!P55 | Z55: ='Plan-Kunden'!Q55 | AA55: =IF(D55>='Plan-Phase B'!$C$22,1,0) | AB55: =IF(D55>='Plan-Phase B'!$D$22,1,0) | AC55: =IF(D55>='Plan-Phase B'!$E$22,1,0) | AD55: =IF(AND(W55>=0,A55>$K$35),1,0) | AE55: =IF(A55>=$O$35,1,0)
A56: 20 | B56: ='Plan-Kunden'!B56 | C56: ='Plan-Kunden'!E56 | D56: ='Plan-Kunden'!K56 | E56: ='Plan-Kunden'!I56 | F56: ='Plan-Kunden'!J56 | G56: =D56*'Plan-Annahmen'!$B$21 | H56: =E56*'Plan-Annahmen'!$B$14+F56*'Plan-Annahmen'!$B$15 | I56: =H56*('Plan-Annahmen'!$B$52+'Plan-Annahmen'!$B$53) | J56: =E56*('Plan-Annahmen'!$B$14*'Plan-Annahmen'!$B$18+'Plan-Annahmen'!$B$19)+F56*('Plan-Annahmen'!$B$15*'Plan-Annahmen'!$B$18+'Plan-Annahmen'!$B$19) | K56: =G56*'Plan-Annahmen'!$B$17/100 | L56: ='Plan-Kunden'!D56*'Plan-Annahmen'!$B$15*'Plan-Annahmen'!$B$50 | M56: ='Plan-Kosten'!AG$61 | N56: =IF(A56>=$O$35,'Plan-Kosten'!$F$71,0) | O56: ='Plan-Kosten'!AG$58 | P56: =IF(A56=$O$35,'Plan-Kosten'!$F$72,0) | Q56: =I56+J56+K56+L56+M56+N56+O56+P56 | R56: =H56-Q56 | S56: =MAX(0,R56*'Plan-Annahmen'!$B$82) | T56: =R56-S56 | U56: =U55+T56 | V56: =V55+'Plan-Kosten'!AG$59+IF(A56=$O$35,'Plan-Kosten'!$F$73,0) | W56: =U56-V56 | X56: =IF(R56>0,1,0) | Y56: ='Plan-Kunden'!P56 | Z56: ='Plan-Kunden'!Q56 | AA56: =IF(D56>='Plan-Phase B'!$C$22,1,0) | AB56: =IF(D56>='Plan-Phase B'!$D$22,1,0) | AC56: =IF(D56>='Plan-Phase B'!$E$22,1,0) | AD56: =IF(AND(W56>=0,A56>$K$35),1,0) | AE56: =IF(A56>=$O$35,1,0)
A57: 21 | B57: ='Plan-Kunden'!B57 | C57: ='Plan-Kunden'!E57 | D57: ='Plan-Kunden'!K57 | E57: ='Plan-Kunden'!I57 | F57: ='Plan-Kunden'!J57 | G57: =D57*'Plan-Annahmen'!$B$21 | H57: =E57*'Plan-Annahmen'!$B$14+F57*'Plan-Annahmen'!$B$15 | I57: =H57*('Plan-Annahmen'!$B$52+'Plan-Annahmen'!$B$53) | J57: =E57*('Plan-Annahmen'!$B$14*'Plan-Annahmen'!$B$18+'Plan-Annahmen'!$B$19)+F57*('Plan-Annahmen'!$B$15*'Plan-Annahmen'!$B$18+'Plan-Annahmen'!$B$19) | K57: =G57*'Plan-Annahmen'!$B$17/100 | L57: ='Plan-Kunden'!D57*'Plan-Annahmen'!$B$15*'Plan-Annahmen'!$B$50 | M57: ='Plan-Kosten'!AH$61 | N57: =IF(A57>=$O$35,'Plan-Kosten'!$F$71,0) | O57: ='Plan-Kosten'!AH$58 | P57: =IF(A57=$O$35,'Plan-Kosten'!$F$72,0) | Q57: =I57+J57+K57+L57+M57+N57+O57+P57 | R57: =H57-Q57 | S57: =MAX(0,R57*'Plan-Annahmen'!$B$82) | T57: =R57-S57 | U57: =U56+T57 | V57: =V56+'Plan-Kosten'!AH$59+IF(A57=$O$35,'Plan-Kosten'!$F$73,0) | W57: =U57-V57 | X57: =IF(R57>0,1,0) | Y57: ='Plan-Kunden'!P57 | Z57: ='Plan-Kunden'!Q57 | AA57: =IF(D57>='Plan-Phase B'!$C$22,1,0) | AB57: =IF(D57>='Plan-Phase B'!$D$22,1,0) | AC57: =IF(D57>='Plan-Phase B'!$E$22,1,0) | AD57: =IF(AND(W57>=0,A57>$K$35),1,0) | AE57: =IF(A57>=$O$35,1,0)
